Workbook

Sheet М_июль 1 цк
A2: Предельные уровни нерегулируемых цен на электрическую энергию (мощность), поставляемую АО "Мосэнергосбыт" потребителям
A3: с максимальной мощностью энергопринимающих устройств не менее 10 МВт
A4: г. Москва
A5: Июль 2025 г.
A7: I. Первая ценовая категория для объемов покупки электрической энергии (мощности), учет которых осуществляется в целом за расчетный период
A9: 1. Предельный уровень нерегулируемых цен, руб./МВт∙ч без НДС
A11: № п/п | B11: Группа потребителей | C11: Уровень напряжения
C12: ВН | D12: СН I | E12: СН II | F12: НН
A13: 1.1. | B13: Прочие потребители
A14: 1.1.1. | B14: Иные прочие потребители | C14: =C15+C16+C17+C19+C18 -> 4968.4 | D14: =D15+D16+D17+D19+D18 -> 5758.33 | E14: =E15+E16+E17+E19+E18 -> 6410.34 | F14: =F15+F16+F17+F19+F18 -> 8086.5
B15: - средневзв. стоимость э/э (м) | C15: 3602.47 | D15: =C15 -> 3602.47 | E15: =C15 -> 3602.47 | F15: =C15 -> 3602.47
B16: - услуги по передаче | C16: 1283.66 | D16: 2073.59 | E16: 2725.6 | F16: 4401.76
B17: - сбытовая надбавка ГП | C17: 75.85 | D17: =C17 -> 75.85 | E17: =C17 -> 75.85 | F17: =C17 -> 75.85
B18: - плата за услуги по управлению изменением режима потребления электрической энергии | C18: 1.07 | D18: 1.07 | E18: 1.07 | F18: 1.07
B19: - инфраструктурные платежи | C19: 5.35 | D19: =C19 -> 5.35 | E19: =C19 -> 5.35 | F19: =C19 -> 5.35
A20: 1.1.2. | B20: Потребители, рассчитывающиеся по договорам купли-продажи | C20: =C21+C22+C24+C23 -> 3684.74 | D20: =D21+D22+D24+D23 -> 3684.74 | E20: =E21+E22+E24+E23 -> 3684.74 | F20: =F21+F22+F24+F23 -> 3684.74
B21: - средневзв. стоимость э/э (м) | C21: =C15 -> 3602.47 | D21: =C21 -> 3602.47 | E21: =C21 -> 3602.47 | F21: =C21 -> 3602.47
B22: - сбытовая надбавка ГП | C22: =C17 -> 75.85 | D22: =C22 -> 75.85 | E22: =C22 -> 75.85 | F22: =C22 -> 75.85
B23: - плата за услуги по управлению изменением режима потребления электрической энергии | C23: 1.07 | D23: 1.07 | E23: 1.07 | F23: 1.07
B24: - инфраструктурные платежи | C24: =C19 -> 5.35 | D24: =C24 -> 5.35 | E24: =C24 -> 5.35 | F24: =C24 -> 5.35
A27: 2. | B27: Средневзвешенная нерегулируемая цена на электрическую энергию (мощность), используемая для расчета предельного уровня нерегулируемых цен для первой ценовой категории, без НДС, руб./МВт∙ч | E27: 3602.47
A28: 3. | B28: Составляющие расчета средневзвешенной нерегулируемой цены на электрическую энергию (мощность), используемой для расчета предельного уровня нерегулируемых цен для первой ценовой категории:
A29: а) | B29: средневзвешенная нерегулируемая цена на электрическую энергию на оптовом рынке, руб./МВт∙ч | E29: 2324,93
A30: б) | B30: средневзвешенная нерегулируемая цена на мощность на оптовом рынке, руб./МВт | E30: 937404,45
A31: в) | B31: коэффициент оплаты мощности потребителями (покупателями), осуществляющими расчеты по первой ценовой категории, 1/час | E31: 0.0013628526
A32: г) | B32: объем фактического пикового потребления гарантирующего поставщика на оптовом рынке, МВт | E32: 12653.047
A33: д) | B33: величина мощности, соответствующей покупке электрической энергии гарантирующим поставщиком у производителей электрической энергии (мощности) на розничных рынках, МВт | E33: 8.244
A34: е) | B34: сумма величин мощности, оплачиваемой на розничном рынке потребителями (покупателями), осуществляющими расчеты по второй - шестой ценовым категориям, МВт | E34: 5425.2309
B35: в том числе:
B36: – по второй ценовой категории, МВт | E36: 31.37
B37: – по третьей ценовой категории, МВт | E37: 3055.548
B38: – по четвертой ценовой категории, МВт | E38: 1954.9029
B39: – по пятой ценовой категории, МВт | E39: 24.143838
B40: – по шестой ценовой категории, МВт | E40: 359.26613
A41: ж) | B41: объем потребления мощности населением и приравненными к нему категориями потребителей, МВт | E41: 3942.223
A42: з) | B42: объем потребления электрической энергии потребителями (покупателями), осуществляющими расчеты по второй ценовой категории, МВт∙ч | E42: 13059.656
B43: в том числе:
B44: для трех зон суток, МВт∙ч | E44: 10179.74
B45: – по ночной зоне суток, МВт∙ч | E45: 3314.096
B46: – по полупиковой зоне суток, МВт∙ч | E46: 4121.4071
B47: – по пиковой зоне суток, МВт∙ч | E47: 2744.2369
B48: для двух зон суток, МВт∙ч | E48: 2879.9156
B49: – по ночной зоне суток, МВт∙ч | E49: 1178.6676
B50: – по пиковой зоне суток, МВт∙ч | E50: 1701.248
A51: и) | B51: фактический объем потребления электрической энергии гарантирующим поставщиком на оптовом рынке, МВт∙ч | E51: 7890017.1
A52: к) | B52: совокупный объем покупки электрической энергии гарантирующим поставщиком у производителей электрической энергии (мощности) на розничных рынках, МВт∙ч | E52: 4273.582
B53: объем покупки электрической энергии гарантирующим поставщиком у собственников и иных законных владельцев объектов микрогенерации, МВт∙ч * | E53: 44.239
A54: л) | B54: сумма объемов потребления электрической энергии потребителями (покупателями), осуществляющими расчеты по второй - шестой ценовым категориям, МВт∙ч | E54: 3379781.4
B55: в том числе:
B56: – по второй ценовой категории, МВт∙ч | E56: 13059.656
B57: – по третьей ценовой категории, МВт∙ч | E57: 1705602.8
B58: – по четвертой ценовой категории, МВт∙ч | E58: 1375077.5
B59: – по пятой ценовой категории, МВт∙ч | E59: 11664.351
B60: – по шестой ценовой категории, МВт∙ч | E60: 274377.05
A61: м) | B61: объем потребления электрической энергии населением и приравненными к нему категориями потребителей, МВт∙ч | E61: 2097639.6
A62: н) | B62: величина изменения средневзвешенной нерегулируемой цены на электрическую энергию (мощность), связанная с учетом данных за предыдущие расчетные периоды **, руб./МВт∙ч | E62: 0
A63: 44409
A64: 2. | B64: средневзвешенная нерегулируемая цена на электрическую энергию (мощность) за предыдущий расчетный период (август 2021 г.), определяемая с учетом данных, известных в расчетный период (июль 2025 г.), без НДС, руб./МВт∙ч | E64: 2790.14
A65: 3. | B65: Составляющие расчета средневзвешенной нерегулируемой цены на электрическую энергию (мощность), используемой для расчета предельного уровня нерегулируемых цен для первой ценовой категории:
A66: а) | B66: средневзвешенная нерегулируемая цена на электрическую энергию на оптовом рынке, руб./МВт∙ч | E66: 1694.92
A67: б) | B67: средневзвешенная нерегулируемая цена на мощность на оптовом рынке, руб./МВт | E67: 806602,09
A68: в) | B68: коэффициент оплаты мощности потребителями (покупателями), осуществляющими расчеты по первой ценовой категории, 1/час | E68: 0.0013553174
A69: г) | B69: объем фактического пикового потребления гарантирующего поставщика на оптовом рынке, МВт | E69: 10612.696
A70: д) | B70: величина мощности, соответствующей покупке электрической энергии гарантирующим поставщиком у производителей электрической энергии (мощности) на розничных рынках, МВт | E70: 4.476
A71: е) | B71: сумма величин мощности, оплачиваемой на розничном рынке потребителями (покупателями), осуществляющими расчеты по второй - шестой ценовым категориям, МВт | E71: 4485.8591
B72: в том числе:
B73: – по второй ценовой категории, МВт | E73: 34.433
B74: – по третьей ценовой категории, МВт | E74: 2569.4251
B75: – по четвертой ценовой категории, МВт | E75: 1560.442
B76: – по пятой ценовой категории, МВт | E76: 25.231
B77: – по шестой ценовой категории, МВт | E77: 296.328
A78: ж) | B78: объем потребления мощности населением и приравненными к нему категориями потребителей, МВт | E78: 3438.978
A79: з) | B79: объем потребления электрической энергии потребителями (покупателями), осуществляющими расчеты по второй ценовой категории, МВт∙ч | E79: 15426.098
B80: в том числе:
B81: для трех зон суток, МВт∙ч | E81: 13167.436
B82: – по ночной зоне суток, МВт∙ч | E82: 4664.081
B83: – по полупиковой зоне суток, МВт∙ч | E83: 4980.798
B84: – по пиковой зоне суток, МВт∙ч | E84: 3522.557
B85: для двух зон суток, МВт∙ч | E85: 2258.662
B86: – по ночной зоне суток, МВт∙ч | E86: 815.592
B87: – по пиковой зоне суток, МВт∙ч | E87: 1443.07
A88: и) | B88: фактический объем потребления электрической энергии гарантирующим поставщиком на оптовом рынке, МВт∙ч | E88: 6622343.5
A89: к) | B89: объем покупки электрической энергии гарантирующим поставщиком у производителей электрической энергии (мощности) на розничных рынках, МВт∙ч | E89: 2580.69
B90: в том числе: – объем покупки электрической энергии у собственников и иных законных владельцев объектов микрогенерации | E90: 0.19
A91: л) | B91: сумма объемов потребления электрической энергии потребителями (покупателями), осуществляющими расчеты по второй - шестой ценовым категориям, МВт∙ч | E91: 2797831.4
B92: в том числе:
B93: – по второй ценовой категории, МВт∙ч | E93: 15426.098
B94: – по третьей ценовой категории, МВт∙ч | E94: 1498035
B95: – по четвертой ценовой категории, МВт∙ч | E95: 1052136.8
B96: – по пятой ценовой категории, МВт∙ч | E96: 14445.146
B97: – по шестой ценовой категории, МВт∙ч | E97: 217788.4
A98: м) | B98: объем потребления электрической энергии населением и приравненными к нему категориями потребителей, МВт∙ч | E98: 1840595.2
A99: 44927
A100: 2. | B100: средневзвешенная нерегулируемая цена на электрическую энергию (мощность) за предыдущий расчетный период (январь 2023 г.), определяемая с учетом данных, известных в расчетный период (июль 2025 г.), без НДС, руб./МВт∙ч | E100: 2735.71
A101: 3. | B101: Составляющие расчета средневзвешенной нерегулируемой цены на электрическую энергию (мощность), используемой для расчета предельного уровня нерегулируемых цен для первой ценовой категории:
A102: а) | B102: средневзвешенная нерегулируемая цена на электрическую энергию на оптовом рынке, руб./МВт∙ч | E102: 1583,59
A103: б) | B103: средневзвешенная нерегулируемая цена на мощность на оптовом рынке, руб./МВт | E103: 854060,08
A104: в) | B104: коэффициент оплаты мощности потребителями (покупателями), осуществляющими расчеты по первой ценовой категории, 1/час | E104: 0.0013489874
A105: г) | B105: объем фактического пикового потребления гарантирующего поставщика на оптовом рынке, МВт | E105: 14776.262
A106: д) | B106: величина мощности, соответствующей покупке электрической энергии гарантирующим поставщиком у производителей электрической энергии (мощности) на розничных рынках, МВт | E106: 8.943
...

Sheet М_июль 2 цк
A2: ='М_июль 1 цк'!A2 -> Предельные уровни нерегулируемых цен на электрическую энергию (мощность), поставляемую АО "Мосэнергосбыт" потребителям
A3: ='М_июль 1 цк'!A3 -> с максимальной мощностью энергопринимающих устройств не менее 10 МВт
A4: ='М_июль 1 цк'!A4 -> г. Москва
A5: ='М_июль 1 цк'!A5 -> Июль 2025 г.
A7: II. Вторая ценовая категория для объемов покупки электрической энергии (мощности), учет которых осуществляется по зонам суток расчетного периода
A9: 1. Предельный уровень нерегулируемых цен для трех зон суток, руб./МВт∙ч без НДС
A11: № п/п | B11: Группа потребителей | C11: Уровень напряжения
C12: ВН | D12: СН I | E12: СН II | F12: НН
A13: 1.1. | B13: Прочие потребители
A14: 1.1.1. | B14: Иные прочие потребители
A15: 1.1.1.1. | B15: ночная зона | C15: =C16+C17+C18+C20+C19 -> 2571.64 | D15: =D16+D17+D18+D20+D19 -> 3361.57 | E15: =E16+E17+E18+E20+E19 -> 4013.58 | F15: =F16+F17+F18+F20+F19 -> 5689.74
B16: - средневзв. стоимость э/э (м) | C16: 1205.71 | D16: =C16 -> 1205.71 | E16: =C16 -> 1205.71 | F16: =C16 -> 1205.71
B17: - услуги по передаче | C17: 1283.66 | D17: 2073.59 | E17: 2725.6 | F17: 4401.76
B18: - сбытовая надбавка ГП | C18: 75.85 | D18: =C18 -> 75.85 | E18: =C18 -> 75.85 | F18: =C18 -> 75.85
B19: - плата за услуги по управлению изменением режима потребления электрической энергии | C19: 1.07 | D19: 1.07 | E19: 1.07 | F19: 1.07
B20: - инфраструктурные платежи | C20: 5.35 | D20: =C20 -> 5.35 | E20: =C20 -> 5.35 | F20: =C20 -> 5.35
A21: 1.1.1.2. | B21: полупиковая зона | C21: =C22+C23+C24+C26+C25 -> 5487.87 | D21: =D22+D23+D24+D26+D25 -> 6277.8 | E21: =E22+E23+E24+E26+E25 -> 6929.81 | F21: =F22+F23+F24+F26+F25 -> 8605.97
B22: - средневзв. стоимость э/э (м) | C22: 4121.94 | D22: =C22 -> 4121.94 | E22: =C22 -> 4121.94 | F22: =C22 -> 4121.94
B23: - услуги по передаче | C23: =C17 -> 1283.66 | D23: =D17 -> 2073.59 | E23: =E17 -> 2725.6 | F23: =F17 -> 4401.76
B24: - сбытовая надбавка ГП | C24: 75.85 | D24: =C24 -> 75.85 | E24: =C24 -> 75.85 | F24: =C24 -> 75.85
B25: - плата за услуги по управлению изменением режима потребления электрической энергии | C25: 1.07 | D25: 1.07 | E25: 1.07 | F25: 1.07
B26: - инфраструктурные платежи | C26: =C20 -> 5.35 | D26: =C26 -> 5.35 | E26: =C26 -> 5.35 | F26: =C26 -> 5.35
A27: 1.1.1.3. | B27: пиковая зона | C27: =C28+C29+C30+C32+C31 -> 10653.27 | D27: =D28+D29+D30+D32+D31 -> 11443.2 | E27: =E28+E29+E30+E32+E31 -> 12095.21 | F27: =F28+F29+F30+F32+F31 -> 13771.37
B28: - средневзв. стоимость э/э (м) | C28: 9287.34 | D28: =C28 -> 9287.34 | E28: =C28 -> 9287.34 | F28: =C28 -> 9287.34
B29: - услуги по передаче | C29: =C17 -> 1283.66 | D29: =D17 -> 2073.59 | E29: =E17 -> 2725.6 | F29: =F17 -> 4401.76
B30: - сбытовая надбавка ГП | C30: 75.85 | D30: =C30 -> 75.85 | E30: =C30 -> 75.85 | F30: =C30 -> 75.85
B31: - плата за услуги по управлению изменением режима потребления электрической энергии | C31: 1.07 | D31: 1.07 | E31: 1.07 | F31: 1.07
B32: - инфраструктурные платежи | C32: =C20 -> 5.35 | D32: =C32 -> 5.35 | E32: =C32 -> 5.35 | F32: =C32 -> 5.35
A33: 1.1.2. | B33: Потребители, рассчитывающиеся по договорам купли-продажи
A34: 1.1.2.1. | B34: ночная зона | C34: =C35+C36+C38+C37 -> 1287.98 | D34: =D35+D36+D38+D37 -> 1287.98 | E34: =E35+E36+E38+E37 -> 1287.98 | F34: =F35+F36+F38+F37 -> 1287.98
B35: - средневзв. стоимость э/э (м) | C35: =C16 -> 1205.71 | D35: =C35 -> 1205.71 | E35: =C35 -> 1205.71 | F35: =C35 -> 1205.71
B36: - сбытовая надбавка ГП | C36: =C18 -> 75.85 | D36: =C36 -> 75.85 | E36: =C36 -> 75.85 | F36: =C36 -> 75.85
B37: - плата за услуги по управлению изменением режима потребления электрической энергии | C37: 1.07 | D37: 1.07 | E37: 1.07 | F37: 1.07
B38: - инфраструктурные платежи | C38: =C20 -> 5.35 | D38: =C38 -> 5.35 | E38: =C38 -> 5.35 | F38: =C38 -> 5.35
A39: 1.1.2.2. | B39: полупиковая зона | C39: =C40+C41+C43+C42 -> 4204.21 | D39: =D40+D41+D43+D42 -> 4204.21 | E39: =E40+E41+E43+E42 -> 4204.21 | F39: =F40+F41+F43+F42 -> 4204.21
B40: - средневзв. стоимость э/э (м) | C40: =C22 -> 4121.94 | D40: =C40 -> 4121.94 | E40: =C40 -> 4121.94 | F40: =C40 -> 4121.94
B41: - сбытовая надбавка ГП | C41: =C24 -> 75.85 | D41: =C41 -> 75.85 | E41: =C41 -> 75.85 | F41: =C41 -> 75.85
B42: - плата за услуги по управлению изменением режима потребления электрической энергии | C42: 1.07 | D42: 1.07 | E42: 1.07 | F42: 1.07
B43: - инфраструктурные платежи | C43: =C38 -> 5.35 | D43: =C43 -> 5.35 | E43: =C43 -> 5.35 | F43: =C43 -> 5.35
A44: 1.1.2.3. | B44: пиковая зона | C44: =C45+C46+C48+C47 -> 9369.61 | D44: =D45+D46+D48+D47 -> 9369.61 | E44: =E45+E46+E48+E47 -> 9369.61 | F44: =F45+F46+F48+F47 -> 9369.61
B45: - средневзв. стоимость э/э (м) | C45: =C28 -> 9287.34 | D45: =C45 -> 9287.34 | E45: =C45 -> 9287.34 | F45: =C45 -> 9287.34
B46: - сбытовая надбавка ГП | C46: =C30 -> 75.85 | D46: =C46 -> 75.85 | E46: =C46 -> 75.85 | F46: =C46 -> 75.85
B47: - плата за услуги по управлению изменением режима потребления электрической энергии | C47: 1.07 | D47: 1.07 | E47: 1.07 | F47: 1.07
B48: - инфраструктурные платежи | C48: =C38 -> 5.35 | D48: =C48 -> 5.35 | E48: =C48 -> 5.35 | F48: =C48 -> 5.35
A50: 2. Предельный уровень нерегулируемых цен для двух зон суток, руб./МВт∙ч без НДС
A52: № п/п | B52: Группа потребителей | C52: Уровень напряжения
C53: ВН | D53: СН I | E53: СН II | F53: НН
A54: 2.1. | B54: Прочие потребители
A55: 2.1.1. | B55: Иные прочие потребители
A56: 2.1.1.1. | B56: ночная зона | C56: =C57+C58+C59+C60+C61 -> 2571.64 | D56: =D57+D58+D59+D60+D61 -> 3361.57 | E56: =E57+E58+E59+E60+E61 -> 4013.58 | F56: =F57+F58+F59+F60+F61 -> 5689.74
B57: - средневзв. стоимость э/э (м) | C57: 1205.71 | D57: =C57 -> 1205.71 | E57: =C57 -> 1205.71 | F57: =C57 -> 1205.71
B58: - услуги по передаче | C58: =C17 -> 1283.66 | D58: =D17 -> 2073.59 | E58: =E17 -> 2725.6 | F58: =F17 -> 4401.76
B59: - сбытовая надбавка ГП | C59: 75.85 | D59: =C59 -> 75.85 | E59: =C59 -> 75.85 | F59: =C59 -> 75.85
B60: - плата за услуги по управлению изменением режима потребления электрической энергии | C60: 1.07 | D60: 1.07 | E60: 1.07 | F60: 1.07
B61: - инфраструктурные платежи | C61: =C20 -> 5.35 | D61: =C61 -> 5.35 | E61: =C61 -> 5.35 | F61: =C61 -> 5.35
A62: 2.1.1.2. | B62: дневная зона | C62: =C63+C64+C65+C67+C66 -> 7656.99 | D62: =D63+D64+D65+D67+D66 -> 8446.92 | E62: =E63+E64+E65+E67+E66 -> 9098.93 | F62: =F63+F64+F65+F67+F66 -> 10775.09
B63: - средневзв. стоимость э/э (м) | C63: 6291.06 | D63: =C63 -> 6291.06 | E63: =C63 -> 6291.06 | F63: =C63 -> 6291.06
B64: - услуги по передаче | C64: =C17 -> 1283.66 | D64: =D17 -> 2073.59 | E64: =E17 -> 2725.6 | F64: =F17 -> 4401.76
B65: - сбытовая надбавка ГП | C65: 75.85 | D65: =C65 -> 75.85 | E65: =C65 -> 75.85 | F65: =C65 -> 75.85
B66: - плата за услуги по управлению изменением режима потребления электрической энергии | C66: 1.07 | D66: 1.07 | E66: 1.07 | F66: 1.07
B67: - инфраструктурные платежи | C67: =C20 -> 5.35 | D67: =C67 -> 5.35 | E67: =C67 -> 5.35 | F67: =C67 -> 5.35
A68: 2.1.2. | B68: Потребители, рассчитывающиеся по договорам купли-продажи
A69: 2.1.2.1. | B69: ночная зона | C69: =C70+C71+C73+C72 -> 1287.98 | D69: =D70+D71+D73+D72 -> 1287.98 | E69: =E70+E71+E73+E72 -> 1287.98 | F69: =F70+F71+F73+F72 -> 1287.98
B70: - средневзв. стоимость э/э (м) | C70: 1205.71 | D70: =C70 -> 1205.71 | E70: =C70 -> 1205.71 | F70: =C70 -> 1205.71
B71: - сбытовая надбавка ГП | C71: 75.85 | D71: =C71 -> 75.85 | E71: =C71 -> 75.85 | F71: =C71 -> 75.85
B72: - плата за услуги по управлению изменением режима потребления электрической энергии | C72: 1.07 | D72: 1.07 | E72: 1.07 | F72: 1.07
B73: - инфраструктурные платежи | C73: 5.35 | D73: =C73 -> 5.35 | E73: =C73 -> 5.35 | F73: =C73 -> 5.35
A74: 2.1.2.2. | B74: дневная зона | C74: =C75+C76+C78+C77 -> 6373.33 | D74: =D75+D76+D78+D77 -> 6373.33 | E74: =E75+E76+E78+E77 -> 6373.33 | F74: =F75+F76+F78+F77 -> 6373.33
B75: - средневзв. стоимость э/э (м) | C75: 6291.06 | D75: =C75 -> 6291.06 | E75: =C75 -> 6291.06 | F75: =C75 -> 6291.06
B76: - сбытовая надбавка ГП | C76: 75.85 | D76: =C76 -> 75.85 | E76: =C76 -> 75.85 | F76: =C76 -> 75.85
B77: - плата за услуги по управлению изменением режима потребления электрической энергии | C77: 1.07 | D77: 1.07 | E77: 1.07 | F77: 1.07
B78: - инфраструктурные платежи | C78: =C73 -> 5.35 | D78: =C78 -> 5.35 | E78: =C78 -> 5.35 | F78: =C78 -> 5.35
E388: 1729.54 | F388: 1729.54
E392: 0.0012544537 | F392: 0.0012544537
E393: 9340.696 | F393: 9340.696
E394: 8.034 | F394: 8.034
E395: 4296.763 | F395: 4296.763
E397: 69.124 | F397: 69.124
E398: 2870.597 | F398: 2870.597
E399: 1223.284 | F399: 1223.284
E400: 0 | F400: 0
E401: 133.758 | F401: 133.758
E402: 3168.964 | F402: 3168.964
E403: 26692.86 | F403: 26692.86
... E1331: 1710048.9 | F1331: 1710048.9

Sheet М_июль 3 цк
A2: ='М_июль 1 цк'!A2 -> Предельные уровни нерегулируемых цен на электрическую энергию (мощность), поставляемую АО "Мосэнергосбыт" потребителям
A3: ='М_июль 1 цк'!A3 -> с максимальной мощностью энергопринимающих устройств не менее 10 МВт
A4: ='М_июль 1 цк'!A4 -> г. Москва
A5: ='М_июль 1 цк'!A5 -> Июль 2025 г.
A7: III. Третья ценовая категория для объемов покупки электрической энергии (мощности), в отношении которых за расчетный период осуществляется почасовой учет, но не осуществляется почасовое планирование, а стоимость услуг по передаче электрической энергии определяется по тарифу на услуги по передаче электрической энергии в одноставочном выражении
A9: 1.1. Ставка за электрическую энергию предельного уровня нерегулируемых цен для абонентов группы "Иные прочие потребители", рублей/МВт∙ч без НДС
A11: Дата | B11: Ставка для фактических почасовых объемов покупки электрической энергии, отпущенных на уровне напряжения ВН
B12: 0:00-1:00 | C12: 1:00-2:00 | D12: 2:00-3:00 | E12: 3:00-4:00 | F12: 4:00-5:00 | G12: 5:00-6:00 | H12: 6:00-7:00 | I12: 7:00-8:00 | J12: 8:00-9:00 | K12: 9:00-10:00 | L12: 10:00-11:00 | M12: 11:00-12:00 | N12: 12:00-13:00 | O12: 13:00-14:00 | P12: 14:00-15:00 | Q12: 15:00-16:00 | R12: 16:00-17:00 | S12: 17:00-18:00 | T12: 18:00-19:00 | U12: 19:00-20:00 | V12: 20:00-21:00 | W12: 21:00-22:00 | X12: 22:00-23:00 | Y12: 23:00-0:00
A13: 1 | B13: =B14+B15+B16+B17 -> 3008.49 | C13: =C14+C15+C16+C17 -> 2739.95 | D13: =D14+D15+D16+D17 -> 2624.87 | E13: =E14+E15+E16+E17 -> 2524.07 | F13: =F14+F15+F16+F17 -> 2546.14 | G13: =G14+G15+G16+G17 -> 2831.43 | H13: =H14+H15+H16+H17 -> 2956.66 | I13: =I14+I15+I16+I17 -> 3408.52 | ... Y13: =Y14+Y15+Y16+Y17 -> 3430.63
A14: - средневзв. стоимость э/э (м) | B14: 1643.63 | C14: 1375.09 | D14: 1260.01 | E14: 1159.21 | F14: 1181.28 | G14: 1466.57 | H14: 1591.8 | I14: 2043.66 | J14: 2544.33 | K14: 2682.61 | L14: 2744.97 | M14: 2743.85 | N14: 2729.42 | O14: 2739.69 | P14: 2768.75 | Q14: 2783.49 | R14: 2762.56 | S14: 2768.68 | T14: 2746.78 | U14: 2697.44 | V14: 2663.63 | W14: 2636.06 | X14: 2326.79 | Y14: 2065.77
A15: - услуги по передаче | B15: 1283.66 | C15: =$B15 -> 1283.66 | D15: =$B15 -> 1283.66 | E15: =$B15 -> 1283.66 | F15: =$B15 -> 1283.66 | G15: =$B15 -> 1283.66 | H15: =$B15 -> 1283.66 | I15: =$B15 -> 1283.66 | J15: =$B15 -> 1283.66 | ... Y15: =$B15 -> 1283.66
A16: - сбытовая надбавка ГП | B16: 75.85 | C16: 75.85 | D16: 75.85 | E16: 75.85 | F16: 75.85 | G16: 75.85 | H16: 75.85 | I16: 75.85 | J16: 75.85 | K16: 75.85 | L16: 75.85 | M16: 75.85 | N16: 75.85 | O16: 75.85 | P16: 75.85 | Q16: 75.85 | R16: 75.85 | S16: 75.85 | T16: 75.85 | U16: 75.85 | V16: 75.85 | W16: 75.85 | X16: 75.85 | Y16: 75.85
A17: - инфраструктурные платежи | B17: 5.35 | C17: =$B17 -> 5.35 | D17: =$B17 -> 5.35 | E17: =$B17 -> 5.35 | F17: =$B17 -> 5.35 | G17: =$B17 -> 5.35 | H17: =$B17 -> 5.35 | I17: =$B17 -> 5.35 | J17: =$B17 -> 5.35 | ... Y17: =$B17 -> 5.35
A18: 2 | B18: =B19+B20+B21+B22 -> 3053.84 | C18: =C19+C20+C21+C22 -> 2893.86 | D18: =D19+D20+D21+D22 -> 2810.21 | E18: =E19+E20+E21+E22 -> 2594.71 | F18: =F19+F20+F21+F22 -> 2689.02 | G18: =G19+G20+G21+G22 -> 2890.07 | H18: =H19+H20+H21+H22 -> 2972.17 | I18: =I19+I20+I21+I22 -> 3459.2 | ... Y18: =Y19+Y20+Y21+Y22 -> 3365.24
A19: - средневзв. стоимость э/э (м) | B19: 1688.98 | C19: 1529 | D19: 1445.35 | E19: 1229.85 | F19: 1324.16 | G19: 1525.21 | H19: 1607.31 | I19: 2094.34 | J19: 2706.96 | K19: 2804.21 | L19: 2837.46 | M19: 2828.28 | N19: 2843.1 | O19: 2873.1 | P19: 2874.34 | Q19: 2863.78 | R19: 2837.34 | S19: 2817.79 | T19: 2806.9 | U19: 2778.96 | V19: 2748.46 | W19: 2727.03 | X19: 2445.18 | Y19: 2000.38
A20: - услуги по передаче | B20: =$B$15 -> 1283.66 | C20: =$B20 -> 1283.66 | D20: =$B20 -> 1283.66 | E20: =$B20 -> 1283.66 | F20: =$B20 -> 1283.66 | G20: =$B20 -> 1283.66 | H20: =$B20 -> 1283.66 | I20: =$B20 -> 1283.66 | J20: =$B20 -> 1283.66 | ... Y20: =$B20 -> 1283.66
A21: - сбытовая надбавка ГП | B21: 75.85 | C21: 75.85 | D21: 75.85 | E21: 75.85 | F21: 75.85 | G21: 75.85 | H21: 75.85 | I21: 75.85 | J21: 75.85 | K21: 75.85 | L21: 75.85 | M21: 75.85 | N21: 75.85 | O21: 75.85 | P21: 75.85 | Q21: 75.85 | R21: 75.85 | S21: 75.85 | T21: 75.85 | U21: 75.85 | V21: 75.85 | W21: 75.85 | X21: 75.85 | Y21: 75.85
A22: - инфраструктурные платежи | B22: =$B$17 -> 5.35 | C22: =$B22 -> 5.35 | D22: =$B22 -> 5.35 | E22: =$B22 -> 5.35 | F22: =$B22 -> 5.35 | G22: =$B22 -> 5.35 | H22: =$B22 -> 5.35 | I22: =$B22 -> 5.35 | J22: =$B22 -> 5.35 | ... Y22: =$B22 -> 5.35
A23: 3 | B23: =B24+B25+B26+B27 -> 2935.76 | C23: =C24+C25+C26+C27 -> 2777.57 | D23: =D24+D25+D26+D27 -> 2654.38 | E23: =E24+E25+E26+E27 -> 2538.68 | F23: =F24+F25+F26+F27 -> 2550.29 | G23: =G24+G25+G26+G27 -> 2775.75 | H23: =H24+H25+H26+H27 -> 2919.71 | I23: =I24+I25+I26+I27 -> 3373.9 | ... Y23: =Y24+Y25+Y26+Y27 -> 3353.52
A24: - средневзв. стоимость э/э (м) | B24: 1570.9 | C24: 1412.71 | D24: 1289.52 | E24: 1173.82 | F24: 1185.43 | G24: 1410.89 | H24: 1554.85 | I24: 2009.04 | J24: 2559.55 | K24: 2598.88 | L24: 2641.18 | M24: 2673.9 | N24: 2667.07 | O24: 2651.63 | P24: 2872.93 | Q24: 2941.52 | R24: 2884.71 | S24: 2688.33 | T24: 2757.86 | U24: 2651.34 | V24: 2696.89 | W24: 2677.99 | X24: 2417.66 | Y24: 1988.66
A25: - услуги по передаче | B25: =$B$15 -> 1283.66 | C25: =$B25 -> 1283.66 | D25: =$B25 -> 1283.66 | E25: =$B25 -> 1283.66 | F25: =$B25 -> 1283.66 | G25: =$B25 -> 1283.66 | H25: =$B25 -> 1283.66 | I25: =$B25 -> 1283.66 | J25: =$B25 -> 1283.66 | ... Y25: =$B25 -> 1283.66
A26: - сбытовая надбавка ГП | B26: 75.85 | C26: 75.85 | D26: 75.85 | E26: 75.85 | F26: 75.85 | G26: 75.85 | H26: 75.85 | I26: 75.85 | J26: 75.85 | K26: 75.85 | L26: 75.85 | M26: 75.85 | N26: 75.85 | O26: 75.85 | P26: 75.85 | Q26: 75.85 | R26: 75.85 | S26: 75.85 | T26: 75.85 | U26: 75.85 | V26: 75.85 | W26: 75.85 | X26: 75.85 | Y26: 75.85
A27: - инфраструктурные платежи | B27: =$B$17 -> 5.35 | C27: =$B27 -> 5.35 | D27: =$B27 -> 5.35 | E27: =$B27 -> 5.35 | F27: =$B27 -> 5.35 | G27: =$B27 -> 5.35 | H27: =$B27 -> 5.35 | I27: =$B27 -> 5.35 | J27: =$B27 -> 5.35 | ... Y27: =$B27 -> 5.35
A28: 4 | B28: =B29+B30+B31+B32 -> 3026.38 | C28: =C29+C30+C31+C32 -> 2806.35 | D28: =D29+D30+D31+D32 -> 2660.9 | E28: =E29+E30+E31+E32 -> 2531.62 | F28: =F29+F30+F31+F32 -> 2548.11 | G28: =G29+G30+G31+G32 -> 2780.66 | H28: =H29+H30+H31+H32 -> 2932.74 | I28: =I29+I30+I31+I32 -> 3395.36 | ... Y28: =Y29+Y30+Y31+Y32 -> 3410.36
A29: - средневзв. стоимость э/э (м) | B29: 1661.52 | C29: 1441.49 | D29: 1296.04 | E29: 1166.76 | F29: 1183.25 | G29: 1415.8 | H29: 1567.88 | I29: 2030.5 | J29: 2568.65 | K29: 2687.94 | L29: 2641.38 | M29: 2639.93 | N29: 2707.75 | O29: 2639.25 | P29: 2784.72 | Q29: 2836.9 | R29: 2818.07 | S29: 2794.9 | T29: 2781.67 | U29: 2648.88 | V29: 2631.45 | W29: 2708.37 | X29: 2511.35 | Y29: 2045.5
A30: - услуги по передаче | B30: =$B$15 -> 1283.66 | C30: =$B30 -> 1283.66 | D30: =$B30 -> 1283.66 | E30: =$B30 -> 1283.66 | F30: =$B30 -> 1283.66 | G30: =$B30 -> 1283.66 | H30: =$B30 -> 1283.66 | I30: =$B30 -> 1283.66 | J30: =$B30 -> 1283.66 | ... Y30: =$B30 -> 1283.66
A31: - сбытовая надбавка ГП | B31: 75.85 | C31: 75.85 | D31: 75.85 | E31: 75.85 | F31: 75.85 | G31: 75.85 | H31: 75.85 | I31: 75.85 | J31: 75.85 | K31: 75.85 | L31: 75.85 | M31: 75.85 | N31: 75.85 | O31: 75.85 | P31: 75.85 | Q31: 75.85 | R31: 75.85 | S31: 75.85 | T31: 75.85 | U31: 75.85 | V31: 75.85 | W31: 75.85 | X31: 75.85 | Y31: 75.85
A32: - инфраструктурные платежи | B32: =$B$17 -> 5.35 | C32: =$B32 -> 5.35 | D32: =$B32 -> 5.35 | E32: =$B32 -> 5.35 | F32: =$B32 -> 5.35 | G32: =$B32 -> 5.35 | H32: =$B32 -> 5.35 | I32: =$B32 -> 5.35 | J32: =$B32 -> 5.35 | ... Y32: =$B32 -> 5.35
A33: 5 | B33: =B34+B35+B36+B37 -> 3118.22 | C33: =C34+C35+C36+C37 -> 2883.99 | D33: =D34+D35+D36+D37 -> 2776.94 | E33: =E34+E35+E36+E37 -> 2633.8 | F33: =F34+F35+F36+F37 -> 2575.51 | G33: =G34+G35+G36+G37 -> 2566.56 | H33: =H34+H35+H36+H37 -> 2669.72 | I33: =I34+I35+I36+I37 -> 3033.88 | ... Y33: =Y34+Y35+Y36+Y37 -> 3346.02
A34: - средневзв. стоимость э/э (м) | B34: 1753.36 | C34: 1519.13 | D34: 1412.08 | E34: 1268.94 | F34: 1210.65 | G34: 1201.7 | H34: 1304.86 | I34: 1669.02 | J34: 2134.91 | K34: 2370.79 | L34: 2439.61 | M34: 2468.97 | N34: 2464.34 | O34: 2468.42 | P34: 2464.8 | Q34: 2527.1 | R34: 2535.38 | S34: 2500.69 | T34: 2480.64 | U34: 2452.58 | V34: 2450.49 | W34: 2467.58 | X34: 2169.48 | Y34: 1981.16
A35: - услуги по передаче | B35: =$B$15 -> 1283.66 | C35: =$B35 -> 1283.66 | D35: =$B35 -> 1283.66 | E35: =$B35 -> 1283.66 | F35: =$B35 -> 1283.66 | G35: =$B35 -> 1283.66 | H35: =$B35 -> 1283.66 | I35: =$B35 -> 1283.66 | J35: =$B35 -> 1283.66 | ... Y35: =$B35 -> 1283.66
A36: - сбытовая надбавка ГП | B36: 75.85 | C36: 75.85 | D36: 75.85 | E36: 75.85 | F36: 75.85 | G36: 75.85 | H36: 75.85 | I36: 75.85 | J36: 75.85 | K36: 75.85 | L36: 75.85 | M36: 75.85 | N36: 75.85 | O36: 75.85 | P36: 75.85 | Q36: 75.85 | R36: 75.85 | S36: 75.85 | T36: 75.85 | U36: 75.85 | V36: 75.85 | W36: 75.85 | X36: 75.85 | Y36: 75.85
A37: - инфраструктурные платежи | B37: =$B$17 -> 5.35 | C37: =$B37 -> 5.35 | D37: =$B37 -> 5.35 | E37: =$B37 -> 5.35 | F37: =$B37 -> 5.35 | G37: =$B37 -> 5.35 | H37: =$B37 -> 5.35 | I37: =$B37 -> 5.35 | J37: =$B37 -> 5.35 | ... Y37: =$B37 -> 5.35
A38: 6 | B38: =B39+B40+B41+B42 -> 3126.51 | C38: =C39+C40+C41+C42 -> 2872.44 | D38: =D39+D40+D41+D42 -> 2751.46 | E38: =E39+E40+E41+E42 -> 2565.83 | F38: =F39+F40+F41+F42 -> 2508.34 | G38: =G39+G40+G41+G42 -> 2507.27 | H38: =H39+H40+H41+H42 -> 2452.02 | I38: =I39+I40+I41+I42 -> 2880.87 | ... Y38: =Y39+Y40+Y41+Y42 -> 3207.4
A39: - средневзв. стоимость э/э (м) | B39: 1761.65 | C39: 1507.58 | D39: 1386.6 | E39: 1200.97 | F39: 1143.48 | G39: 1142.41 | H39: 1087.16 | I39: 1516.01 | J39: 1920.92 | K39: 2258.81 | L39: 2395.9 | M39: 2395.86 | N39: 2398.62 | O39: 2405.7 | P39: 2410.55 | Q39: 2412.36 | R39: 2465.57 | S39: 2451.43 | T39: 2449.76 | U39: 2433.67 | V39: 2433.2 | W39: 2429.4 | X39: 2185.02 | Y39: 1842.54
A40: - услуги по передаче | B40: =$B$15 -> 1283.66 | C40: =$B40 -> 1283.66 | D40: =$B40 -> 1283.66 | E40: =$B40 -> 1283.66 | F40: =$B40 -> 1283.66 | G40: =$B40 -> 1283.66 | H40: =$B40 -> 1283.66 | I40: =$B40 -> 1283.66 | J40: =$B40 -> 1283.66 | ... Y40: =$B40 -> 1283.66
A41: - сбытовая надбавка ГП | B41: 75.85 | C41: 75.85 | D41: 75.85 | E41: 75.85 | F41: 75.85 | G41: 75.85 | H41: 75.85 | I41: 75.85 | J41: 75.85 | K41: 75.85 | L41: 75.85 | M41: 75.85 | N41: 75.85 | O41: 75.85 | P41: 75.85 | Q41: 75.85 | R41: 75.85 | S41: 75.85 | T41: 75.85 | U41: 75.85 | V41: 75.85 | W41: 75.85 | X41: 75.85 | Y41: 75.85
A42: - инфраструктурные платежи | B42: =$B$17 -> 5.35 | C42: =$B42 -> 5.35 | D42: =$B42 -> 5.35 | E42: =$B42 -> 5.35 | F42: =$B42 -> 5.35 | G42: =$B42 -> 5.35 | H42: =$B42 -> 5.35 | I42: =$B42 -> 5.35 | J42: =$B42 -> 5.35 | ... Y42: =$B42 -> 5.35
A43: 7 | B43: =B44+B45+B46+B47 -> 3050.77 | C43: =C44+C45+C46+C47 -> 2882.24 | D43: =D44+D45+D46+D47 -> 2681.61 | E43: =E44+E45+E46+E47 -> 2536.88 | F43: =F44+F45+F46+F47 -> 2505.68 | G43: =G44+G45+G46+G47 -> 2595.26 | H43: =H44+H45+H46+H47 -> 2901.4 | I43: =I44+I45+I46+I47 -> 3342.63 | ... Y43: =Y44+Y45+Y46+Y47 -> 3234.94
A44: - средневзв. стоимость э/э (м) | B44: 1685.91 | C44: 1517.38 | D44: 1316.75 | E44: 1172.02 | F44: 1140.82 | G44: 1230.4 | H44: 1536.54 | I44: 1977.77 | J44: 2516.42 | K44: 2642.82 | L44: 2703.04 | M44: 2743.84 | N44: 2728.5 | O44: 2752.78 | P44: 2737.88 | Q44: 2771.21 | R44: 2719.3 | S44: 2834.06 | T44: 2733.83 | U44: 2697.7 | V44: 2643.26 | W44: 2659.85 | X44: 2219.27 | Y44: 1870.08
A45: - услуги по передаче | B45: =$B$15 -> 1283.66 | C45: =$B45 -> 1283.66 | D45: =$B45 -> 1283.66 | E45: =$B45 -> 1283.66 | F45: =$B45 -> 1283.66 | G45: =$B45 -> 1283.66 | H45: =$B45 -> 1283.66 | I45: =$B45 -> 1283.66 | J45: =$B45 -> 1283.66 | ... Y45: =$B45 -> 1283.66
A46: - сбытовая надбавка ГП | B46: 75.85 | C46: 75.85 | D46: 75.85 | E46: 75.85 | F46: 75.85 | G46: 75.85 | H46: 75.85 | I46: 75.85 | J46: 75.85 | K46: 75.85 | L46: 75.85 | M46: 75.85 | N46: 75.85 | O46: 75.85 | P46: 75.85 | Q46: 75.85 | R46: 75.85 | S46: 75.85 | T46: 75.85 | U46: 75.85 | V46: 75.85 | W46: 75.85 | X46: 75.85 | Y46: 75.85
A47: - инфраструктурные платежи | B47: =$B$17 -> 5.35 | C47: =$B47 -> 5.35 | D47: =$B47 -> 5.35 | E47: =$B47 -> 5.35 | F47: =$B47 -> 5.35 | G47: =$B47 -> 5.35 | H47: =$B47 -> 5.35 | I47: =$B47 -> 5.35 | J47: =$B47 -> 5.35 | ... Y47: =$B47 -> 5.35
A48: 8 | B48: =B49+B50+B51+B52 -> 2883.99 | C48: =C49+C50+C51+C52 -> 2609.88 | D48: =D49+D50+D51+D52 -> 2446.88 | E48: =E49+E50+E51+E52 -> 1555.01 | F48: =F49+F50+F51+F52 -> 1513.44 | G48: =G49+G50+G51+G52 -> 1528.65 | H48: =H49+H50+H51+H52 -> 2586.86 | I48: =I49+I50+I51+I52 -> 3182.43 | ... Y48: =Y49+Y50+Y51+Y52 -> 3220.4
A49: - средневзв. стоимость э/э (м) | B49: 1519.13 | C49: 1245.02 | D49: 1082.02 | E49: 190.15 | F49: 148.58 | G49: 163.79 | H49: 1222 | I49: 1817.57 | J49: 2386.8 | K49: 2620.89 | L49: 2753.89 | M49: 2766.53 | N49: 2750.06 | O49: 2752.45 | P49: 3081.15 | Q49: 2829.37 | R49: 2852.62 | S49: 2826.79 | T49: 2731.55 | U49: 2624.77 | V49: 2604.67 | W49: 2544.9 | X49: 2150.53 | Y49: 1855.54
A50: - услуги по передаче | B50: =$B$15 -> 1283.66 | C50: =$B50 -> 1283.66 | D50: =$B50 -> 1283.66 | E50: =$B50 -> 1283.66 | F50: =$B50 -> 1283.66 | G50: =$B50 -> 1283.66 | H50: =$B50 -> 1283.66 | I50: =$B50 -> 1283.66 | J50: =$B50 -> 1283.66 | ... Y50: =$B50 -> 1283.66
A51: - сбытовая надбавка ГП | B51: 75.85 | C51: 75.85 | D51: 75.85 | E51: 75.85 | F51: 75.85 | G51: 75.85 | H51: 75.85 | I51: 75.85 | J51: 75.85 | K51: 75.85 | L51: 75.85 | M51: 75.85 | N51: 75.85 | O51: 75.85 | P51: 75.85 | Q51: 75.85 | R51: 75.85 | S51: 75.85 | T51: 75.85 | U51: 75.85 | V51: 75.85 | W51: 75.85 | X51: 75.85 | Y51: 75.85
A52: - инфраструктурные платежи | B52: =$B$17 -> 5.35 | C52: =$B52 -> 5.35 | D52: =$B52 -> 5.35 | E52: =$B52 -> 5.35 | F52: =$B52 -> 5.35 | G52: =$B52 -> 5.35 | H52: =$B52 -> 5.35 | I52: =$B52 -> 5.35 | J52: =$B52 -> 5.35 | ... Y52: =$B52 -> 5.35
A53: 9 | B53: =B54+B55+B56+B57 -> 3057.49 | C53: =C54+C55+C56+C57 -> 2491.02 | D53: =D54+D55+D56+D57 -> 1521.92 | E53: =E54+E55+E56+E57 -> 1517.7 | F53: =F54+F55+F56+F57 -> 1515.23 | G53: =G54+G55+G56+G57 -> 1528.52 | H53: =H54+H55+H56+H57 -> 2494.43 | I53: =I54+I55+I56+I57 -> 3196.93 | ... Y53: =Y54+Y55+Y56+Y57 -> 2955.01
A54: - средневзв. стоимость э/э (м) | B54: 1692.63 | C54: 1126.16 | D54: 157.06 | E54: 152.84 | F54: 150.37 | G54: 163.66 | H54: 1129.57 | I54: 1832.07 | J54: 2133.88 | K54: 2497.34 | L54: 2693.5 | M54: 2757.98 | N54: 2756.02 | O54: 3052.55 | P54: 3209.79 | Q54: 3223.31 | R54: 3167.97 | S54: 3140.22 | T54: 2786.8 | U54: 2570.26 | V54: 2515.07 | W54: 2497.39 | X54: 2056.21 | Y54: 1590.15
A55: - услуги по передаче | B55: =$B$15 -> 1283.66 | C55: =$B55 -> 1283.66 | D55: =$B55 -> 1283.66 | E55: =$B55 -> 1283.66 | F55: =$B55 -> 1283.66 | G55: =$B55 -> 1283.66 | H55: =$B55 -> 1283.66 | I55: =$B55 -> 1283.66 | J55: =$B55 -> 1283.66 | ... Y55: =$B55 -> 1283.66
A56: - сбытовая надбавка ГП | B56: 75.85 | C56: 75.85 | D56: 75.85 | E56: 75.85 | F56: 75.85 | G56: 75.85 | H56: 75.85 | I56: 75.85 | J56: 75.85 | K56: 75.85 | L56: 75.85 | M56: 75.85 | N56: 75.85 | O56: 75.85 | P56: 75.85 | Q56: 75.85 | R56: 75.85 | S56: 75.85 | T56: 75.85 | U56: 75.85 | V56: 75.85 | W56: 75.85 | X56: 75.85 | Y56: 75.85
A57: - инфраструктурные платежи | B57: =$B$17 -> 5.35 | C57: =$B57 -> 5.35 | D57: =$B57 -> 5.35 | E57: =$B57 -> 5.35 | F57: =$B57 -> 5.35 | G57: =$B57 -> 5.35 | H57: =$B57 -> 5.35 | I57: =$B57 -> 5.35 | J57: =$B57 -> 5.35 | ... Y57: =$B57 -> 5.35
A58: 10 | B58: =B59+B60+B61+B62 -> 2709.62 | C58: =C59+C60+C61+C62 -> 2440.75 | D58: =D59+D60+D61+D62 -> 1507.76 | E58: =E59+E60+E61+E62 -> 1484.93 | F58: =F59+F60+F61+F62 -> 1492.01 | G58: =G59+G60+G61+G62 -> 1512.11 | H58: =H59+H60+H61+H62 -> 2073.67 | I58: =I59+I60+I61+I62 -> 2985.36 | ... Y58: =Y59+Y60+Y61+Y62 -> 3174.61
A59: - средневзв. стоимость э/э (м) | B59: 1344.76 | C59: 1075.89 | D59: 142.9 | E59: 120.07 | F59: 127.15 | G59: 147.25 | H59: 708.81 | I59: 1620.5 | J59: 2220.31 | K59: 2731.02 | L59: 3037.45 | M59: 3178.14 | N59: 2657.09 | O59: 3029.52 | P59: 3237.11 | Q59: 3082.44 | R59: 3084.05 | S59: 3007.53 | T59: 2862.95 | U59: 2840.64 | V59: 2729.6 | W59: 2671.87 | X59: 2185.28 | Y59: 1809.75
A60: - услуги по передаче | B60: =$B$15 -> 1283.66 | C60: =$B60 -> 1283.66 | D60: =$B60 -> 1283.66 | E60: =$B60 -> 1283.66 | F60: =$B60 -> 1283.66 | G60: =$B60 -> 1283.66 | H60: =$B60 -> 1283.66 | I60: =$B60 -> 1283.66 | J60: =$B60 -> 1283.66 | ... Y60: =$B60 -> 1283.66
A61: - сбытовая надбавка ГП | B61: 75.85 | C61: 75.85 | D61: 75.85 | E61: 75.85 | F61: 75.85 | G61: 75.85 | H61: 75.85 | I61: 75.85 | J61: 75.85 | K61: 75.85 | L61: 75.85 | M61: 75.85 | N61: 75.85 | O61: 75.85 | P61: 75.85 | Q61: 75.85 | R61: 75.85 | S61: 75.85 | T61: 75.85 | U61: 75.85 | V61: 75.85 | W61: 75.85 | X61: 75.85 | Y61: 75.85
A62: - инфраструктурные платежи | B62: =$B$17 -> 5.35 | C62: =$B62 -> 5.35 | D62: =$B62 -> 5.35 | E62: =$B62 -> 5.35 | F62: =$B62 -> 5.35 | G62: =$B62 -> 5.35 | H62: =$B62 -> 5.35 | I62: =$B62 -> 5.35 | J62: =$B62 -> 5.35 | ... Y62: =$B62 -> 5.35
A63: 11 | B63: =B64+B65+B66+B67 -> 2828.38 | C63: =C64+C65+C66+C67 -> 2604.06 | D63: =D64+D65+D66+D67 -> 1522.44 | E63: =E64+E65+E66+E67 -> 1516.47 | F63: =F64+F65+F66+F67 -> 1517.06 | G63: =G64+G65+G66+G67 -> 1519.73 | H63: =H64+H65+H66+H67 -> 2710.68 | I63: =I64+I65+I66+I67 -> 3143.19 | ... Y63: =Y64+Y65+Y66+Y67 -> 3424.82
A64: - средневзв. стоимость э/э (м) | B64: 1463.52 | C64: 1239.2 | D64: 157.58 | E64: 151.61 | F64: 152.2 | G64: 154.87 | H64: 1345.82 | I64: 1778.33 | J64: 2517.19 | K64: 2779.58 | L64: 2799.71 | M64: 2902.42 | N64: 2914.86 | O64: 2982.36 | P64: 2754.11 | Q64: 3061.37 | R64: 3061.84 | S64: 3348.84 | T64: 2924.97 | U64: 2837.1 | V64: 2959.58 | W64: 2832.44 | X64: 2367.04 | Y64: 2059.96
A65: - услуги по передаче | B65: =$B$15 -> 1283.66 | C65: =$B65 -> 1283.66 | D65: =$B65 -> 1283.66 | E65: =$B65 -> 1283.66 | F65: =$B65 -> 1283.66 | G65: =$B65 -> 1283.66 | H65: =$B65 -> 1283.66 | I65: =$B65 -> 1283.66 | J65: =$B65 -> 1283.66 | ... Y65: =$B65 -> 1283.66
A66: - сбытовая надбавка ГП | B66: 75.85 | C66: 75.85 | D66: 75.85 | E66: 75.85 | F66: 75.85 | G66: 75.85 | H66: 75.85 | I66: 75.85 | J66: 75.85 | K66: 75.85 | L66: 75.85 | M66: 75.85 | N66: 75.85 | O66: 75.85 | P66: 75.85 | Q66: 75.85 | R66: 75.85 | S66: 75.85 | T66: 75.85 | U66: 75.85 | V66: 75.85 | W66: 75.85 | X66: 75.85 | Y66: 75.85
A67: - инфраструктурные платежи | B67: =$B$17 -> 5.35 | C67: =$B67 -> 5.35 | D67: =$B67 -> 5.35 | E67: =$B67 -> 5.35 | F67: =$B67 -> 5.35 | G67: =$B67 -> 5.35 | H67: =$B67 -> 5.35 | I67: =$B67 -> 5.35 | J67: =$B67 -> 5.35 | ... Y67: =$B67 -> 5.35
A68: 12 | B68: =B69+B70+B71+B72 -> 3139.52 | C68: =C69+C70+C71+C72 -> 2813.1 | D68: =D69+D70+D71+D72 -> 2647.73 | E68: =E69+E70+E71+E72 -> 1726.85 | F68: =F69+F70+F71+F72 -> 1542.61 | G68: =G69+G70+G71+G72 -> 1539.74 | H68: =H69+H70+H71+H72 -> 2479.94 | I68: =I69+I70+I71+I72 -> 2995.37 | ... Y68: =Y69+Y70+Y71+Y72 -> 3515.92
A69: - средневзв. стоимость э/э (м) | B69: 1774.66 | C69: 1448.24 | D69: 1282.87 | E69: 361.99 | F69: 177.75 | G69: 174.88 | H69: 1115.08 | I69: 1630.51 | J69: 2215.05 | K69: 2564.66 | L69: 2743.61 | M69: 2757.38 | N69: 2751.08 | O69: 2846.09 | P69: 2860.77 | Q69: 2799.77 | R69: 3214.08 | S69: 3164.24 | T69: 2779.49 | U69: 2679.46 | V69: 2779.53 | W69: 2846.71 | X69: 2556.08 | Y69: 2151.06
A70: - услуги по передаче | B70: =$B$15 -> 1283.66 | C70: =$B70 -> 1283.66 | D70: =$B70 -> 1283.66 | E70: =$B70 -> 1283.66 | F70: =$B70 -> 1283.66 | G70: =$B70 -> 1283.66 | H70: =$B70 -> 1283.66 | I70: =$B70 -> 1283.66 | J70: =$B70 -> 1283.66 | ... Y70: =$B70 -> 1283.66
A71: - сбытовая надбавка ГП | B71: 75.85 | C71: 75.85 | D71: 75.85 | E71: 75.85 | F71: 75.85 | G71: 75.85 | H71: 75.85 | I71: 75.85 | J71: 75.85 | K71: 75.85 | L71: 75.85 | M71: 75.85 | N71: 75.85 | O71: 75.85 | P71: 75.85 | Q71: 75.85 | R71: 75.85 | S71: 75.85 | T71: 75.85 | U71: 75.85 | V71: 75.85 | W71: 75.85 | X71: 75.85 | Y71: 75.85
A72: - инфраструктурные платежи | B72: =$B$17 -> 5.35 | C72: =$B72 -> 5.35 | D72: =$B72 -> 5.35 | E72: =$B72 -> 5.35 | F72: =$B72 -> 5.35 | G72: =$B72 -> 5.35 | H72: =$B72 -> 5.35 | I72: =$B72 -> 5.35 | J72: =$B72 -> 5.35 | ... Y72: =$B72 -> 5.35
A73: 13 | B73: =B74+B75+B76+B77 -> 3063.24 | C73: =C74+C75+C76+C77 -> 2850.52 | D73: =D74+D75+D76+D77 -> 2681.86 | E73: =E74+E75+E76+E77 -> 1567.49 | F73: =F74+F75+F76+F77 -> 1532.3 | G73: =G74+G75+G76+G77 -> 1529.03 | H73: =H74+H75+H76+H77 -> 2336.61 | I73: =I74+I75+I76+I77 -> 2799.45 | ... Y73: =Y74+Y75+Y76+Y77 -> 3375.27
A74: - средневзв. стоимость э/э (м) | B74: 1698.38 | C74: 1485.66 | D74: 1317 | E74: 202.63 | F74: 167.44 | G74: 164.17 | H74: 971.75 | I74: 1434.59 | J74: 1978.25 | K74: 2469.39 | L74: 2591.3 | M74: 2585.28 | N74: 2770.57 | O74: 2728.68 | P74: 2791.8 | Q74: 2808.61 | R74: 2785.21 | S74: 2911.59 | T74: 2831.65 | U74: 2752.88 | V74: 2732.52 | W74: 2727.08 | X74: 2460.78 | Y74: 2010.41
A75: - услуги по передаче | B75: =$B$15 -> 1283.66 | C75: =$B75 -> 1283.66 | D75: =$B75 -> 1283.66 | E75: =$B75 -> 1283.66 | F75: =$B75 -> 1283.66 | G75: =$B75 -> 1283.66 | H75: =$B75 -> 1283.66 | I75: =$B75 -> 1283.66 | J75: =$B75 -> 1283.66 | ... Y75: =$B75 -> 1283.66
A76: - сбытовая надбавка ГП | B76: 75.85 | C76: 75.85 | D76: 75.85 | E76: 75.85 | F76: 75.85 | G76: 75.85 | H76: 75.85 | I76: 75.85 | J76: 75.85 | K76: 75.85 | L76: 75.85 | M76: 75.85 | N76: 75.85 | O76: 75.85 | P76: 75.85 | Q76: 75.85 | R76: 75.85 | S76: 75.85 | T76: 75.85 | U76: 75.85 | V76: 75.85 | W76: 75.85 | X76: 75.85 | Y76: 75.85
A77: - инфраструктурные платежи | B77: =$B$17 -> 5.35 | C77: =$B77 -> 5.35 | D77: =$B77 -> 5.35 | E77: =$B77 -> 5.35 | F77: =$B77 -> 5.35 | G77: =$B77 -> 5.35 | H77: =$B77 -> 5.35 | I77: =$B77 -> 5.35 | J77: =$B77 -> 5.35 | ... Y77: =$B77 -> 5.35
A78: 14 | B78: =B79+B80+B81+B82 -> 2936.02 | C78: =C79+C80+C81+C82 -> 2739.39 | D78: =D79+D80+D81+D82 -> 1634.58 | E78: =E79+E80+E81+E82 -> 1541.89 | F78: =F79+F80+F81+F82 -> 1537.61 | G78: =G79+G80+G81+G82 -> 1541.91 | H78: =H79+H80+H81+H82 -> 2556.08 | I78: =I79+I80+I81+I82 -> 3210.04 | ... Y78: =Y79+Y80+Y81+Y82 -> 3181.64
A79: - средневзв. стоимость э/э (м) | B79: 1571.16 | C79: 1374.53 | D79: 269.72 | E79: 177.03 | F79: 172.75 | G79: 177.05 | H79: 1191.22 | I79: 1845.18 | J79: 2619.18 | K79: 2871.52 | L79: 2895.84 | M79: 2902.83 | N79: 2894.62 | O79: 2900.41 | P79: 2894.5 | Q79: 2960.06 | R79: 2939.75 | S79: 2926.91 | T79: 2877.18 | U79: 2797.16 | V79: 2785.27 | W79: 2752.19 | X79: 2228.96 | Y79: 1816.78
A80: - услуги по передаче | B80: =$B$15 -> 1283.66 | C80: =$B80 -> 1283.66 | D80: =$B80 -> 1283.66 | E80: =$B80 -> 1283.66 | F80: =$B80 -> 1283.66 | G80: =$B80 -> 1283.66 | H80: =$B80 -> 1283.66 | I80: =$B80 -> 1283.66 | J80: =$B80 -> 1283.66 | ... Y80: =$B80 -> 1283.66
A81: - сбытовая надбавка ГП | B81: 75.85 | C81: 75.85 | D81: 75.85 | E81: 75.85 | F81: 75.85 | G81: 75.85 | H81: 75.85 | I81: 75.85 | J81: 75.85 | K81: 75.85 | L81: 75.85 | M81: 75.85 | N81: 75.85 | O81: 75.85 | P81: 75.85 | Q81: 75.85 | R81: 75.85 | S81: 75.85 | T81: 75.85 | U81: 75.85 | V81: 75.85 | W81: 75.85 | X81: 75.85 | Y81: 75.85
A82: - инфраструктурные платежи | B82: =$B$17 -> 5.35 | C82: =$B82 -> 5.35 | D82: =$B82 -> 5.35 | E82: =$B82 -> 5.35 | F82: =$B82 -> 5.35 | G82: =$B82 -> 5.35 | H82: =$B82 -> 5.35 | I82: =$B82 -> 5.35 | J82: =$B82 -> 5.35 | ... Y82: =$B82 -> 5.35
A83: 15 | B83: =B84+B85+B86+B87 -> 2782.2 | C83: =C84+C85+C86+C87 -> 2592.67 | D83: =D84+D85+D86+D87 -> 2433.07 | E83: =E84+E85+E86+E87 -> 1473.98 | F83: =F84+F85+F86+F87 -> 1396.43 | G83: =G84+G85+G86+G87 -> 1472.6 | H83: =H84+H85+H86+H87 -> 2388.35 | I83: =I84+I85+I86+I87 -> 3210.3 | ... Y83: =Y84+Y85+Y86+Y87 -> 3285.86
A84: - средневзв. стоимость э/э (м) | B84: 1417.34 | C84: 1227.81 | D84: 1068.21 | E84: 109.12 | F84: 31.57 | G84: 107.74 | H84: 1023.49 | I84: 1845.44 | J84: 2433.4 | K84: 2892.37 | L84: 2879.59 | M84: 2948.78 | N84: 2950.12 | O84: 2969.15 | P84: 2956.29 | Q84: 2978.09 | R84: 3013.06 | S84: 3049.74 | T84: 2962.02 | U84: 2846.26 | V84: 2745.91 | W84: 2742.16 | X84: 2196.13 | Y84: 1921
A85: - услуги по передаче | B85: =$B$15 -> 1283.66 | C85: =$B85 -> 1283.66 | D85: =$B85 -> 1283.66 | E85: =$B85 -> 1283.66 | F85: =$B85 -> 1283.66 | G85: =$B85 -> 1283.66 | H85: =$B85 -> 1283.66 | I85: =$B85 -> 1283.66 | J85: =$B85 -> 1283.66 | ... Y85: =$B85 -> 1283.66
A86: - сбытовая надбавка ГП | B86: 75.85 | C86: 75.85 | D86: 75.85 | E86: 75.85 | F86: 75.85 | G86: 75.85 | H86: 75.85 | I86: 75.85 | J86: 75.85 | K86: 75.85 | L86: 75.85 | M86: 75.85 | N86: 75.85 | O86: 75.85 | P86: 75.85 | Q86: 75.85 | R86: 75.85 | S86: 75.85 | T86: 75.85 | U86: 75.85 | V86: 75.85 | W86: 75.85 | X86: 75.85 | Y86: 75.85
A87: - инфраструктурные платежи | B87: =$B$17 -> 5.35 | C87: =$B87 -> 5.35 | D87: =$B87 -> 5.35 | E87: =$B87 -> 5.35 | F87: =$B87 -> 5.35 | G87: =$B87 -> 5.35 | H87: =$B87 -> 5.35 | I87: =$B87 -> 5.35 | J87: =$B87 -> 5.35 | ... Y87: =$B87 -> 5.35
A88: 16 | B88: =B89+B90+B91+B92 -> 2821.79 | C88: =C89+C90+C91+C92 -> 2644.79 | D88: =D89+D90+D91+D92 -> 2465.83 | E88: =E89+E90+E91+E92 -> 2214.47 | F88: =F89+F90+F91+F92 -> 1624.99 | G88: =G89+G90+G91+G92 -> 2408.34 | H88: =H89+H90+H91+H92 -> 2487.98 | I88: =I89+I90+I91+I92 -> 2947.43 | ... Y88: =Y89+Y90+Y91+Y92 -> 3180.87
A89: - средневзв. стоимость э/э (м) | B89: 1456.93 | C89: 1279.93 | D89: 1100.97 | E89: 849.61 | F89: 260.13 | G89: 1043.48 | H89: 1123.12 | I89: 1582.57 | J89: 2368.26 | K89: 2855.03 | L89: 2928.17 | M89: 3033.92 | N89: 3154.17 | O89: 3179.94 | P89: 3175.14 | Q89: 3092.33 | R89: 3119.37 | S89: 2923.4 | T89: 2854.64 | U89: 2738.07 | V89: 2709.8 | W89: 2690.09 | X89: 2442.61 | Y89: 1816.01
A90: - услуги по передаче | B90: =$B$15 -> 1283.66 | C90: =$B90 -> 1283.66 | D90: =$B90 -> 1283.66 | E90: =$B90 -> 1283.66 | F90: =$B90 -> 1283.66 | G90: =$B90 -> 1283.66 | H90: =$B90 -> 1283.66 | I90: =$B90 -> 1283.66 | J90: =$B90 -> 1283.66 | ... Y90: =$B90 -> 1283.66
A91: - сбытовая надбавка ГП | B91: 75.85 | C91: 75.85 | D91: 75.85 | E91: 75.85 | F91: 75.85 | G91: 75.85 | H91: 75.85 | I91: 75.85 | J91: 75.85 | K91: 75.85 | L91: 75.85 | M91: 75.85 | N91: 75.85 | O91: 75.85 | P91: 75.85 | Q91: 75.85 | R91: 75.85 | S91: 75.85 | T91: 75.85 | U91: 75.85 | V91: 75.85 | W91: 75.85 | X91: 75.85 | Y91: 75.85
A92: - инфраструктурные платежи | B92: =$B$17 -> 5.35 | C92: =$B92 -> 5.35 | D92: =$B92 -> 5.35 | E92: =$B92 -> 5.35 | F92: =$B92 -> 5.35 | G92: =$B92 -> 5.35 | H92: =$B92 -> 5.35 | I92: =$B92 -> 5.35 | J92: =$B92 -> 5.35 | ... Y92: =$B92 -> 5.35
A93: 17 | B93: =B94+B95+B96+B97 -> 2953.52 | C93: =C94+C95+C96+C97 -> 2681.85 | D93: =D94+D95+D96+D97 -> 2471.35 | E93: =E94+E95+E96+E97 -> 2210.12 | F93: =F94+F95+F96+F97 -> 2183.69 | G93: =G94+G95+G96+G97 -> 2421.47 | H93: =H94+H95+H96+H97 -> 2682.84 | I93: =I94+I95+I96+I97 -> 3277.73 | ... Y93: =Y94+Y95+Y96+Y97 -> 3334.32
A94: - средневзв. стоимость э/э (м) | B94: 1588.66 | C94: 1316.99 | D94: 1106.49 | E94: 845.26 | F94: 818.83 | G94: 1056.61 | H94: 1317.98 | I94: 1912.87 | J94: 2629.25 | K94: 2893.84 | L94: 2895.72 | M94: 3002.23 | N94: 3003.68 | O94: 3027.52 | P94: 3026.25 | Q94: 3013.19 | R94: 3018.06 | S94: 2971.67 | T94: 2908.04 | U94: 2847.78 | V94: 2823.95 | W94: 2807.31 | X94: 2613.24 | Y94: 1969.46
A95: - услуги по передаче | B95: =$B$15 -> 1283.66 | C95: =$B95 -> 1283.66 | D95: =$B95 -> 1283.66 | E95: =$B95 -> 1283.66 | F95: =$B95 -> 1283.66 | G95: =$B95 -> 1283.66 | H95: =$B95 -> 1283.66 | I95: =$B95 -> 1283.66 | J95: =$B95 -> 1283.66 | ... Y95: =$B95 -> 1283.66
A96: - сбытовая надбавка ГП | B96: 75.85 | C96: 75.85 | D96: 75.85 | E96: 75.85 | F96: 75.85 | G96: 75.85 | H96: 75.85 | I96: 75.85 | J96: 75.85 | K96: 75.85 | L96: 75.85 | M96: 75.85 | N96: 75.85 | O96: 75.85 | P96: 75.85 | Q96: 75.85 | R96: 75.85 | S96: 75.85 | T96: 75.85 | U96: 75.85 | V96: 75.85 | W96: 75.85 | X96: 75.85 | Y96: 75.85
A97: - инфраструктурные платежи | B97: =$B$17 -> 5.35 | C97: =$B97 -> 5.35 | D97: =$B97 -> 5.35 | E97: =$B97 -> 5.35 | F97: =$B97 -> 5.35 | G97: =$B97 -> 5.35 | H97: =$B97 -> 5.35 | I97: =$B97 -> 5.35 | J97: =$B97 -> 5.35 | ... Y97: =$B97 -> 5.35
A98: 18 | B98: =B99+B100+B101+B102 -> 2975.83 | C98: =C99+C100+C101+C102 -> 2767.23 | D98: =D99+D100+D101+D102 -> 2569.89 | E98: =E99+E100+E101+E102 -> 2434.05 | F98: =F99+F100+F101+F102 -> 2198.24 | G98: =G99+G100+G101+G102 -> 2344.84 | H98: =H99+H100+H101+H102 -> 2792.23 | I98: =I99+I100+I101+I102 -> 3278.54 | ... Y98: =Y99+Y100+Y101+Y102 -> 3613.19
A99: - средневзв. стоимость э/э (м) | B99: 1610.97 | C99: 1402.37 | D99: 1205.03 | E99: 1069.19 | F99: 833.38 | G99: 979.98 | H99: 1427.37 | I99: 1913.68 | J99: 2874.94 | K99: 3004.59 | L99: 3101.21 | M99: 3322.11 | N99: 3309.94 | O99: 3447.48 | P99: 3469.43 | Q99: 3441.94 | R99: 3275.18 | S99: 3157.78 | T99: 3096.69 | U99: 3014.76 | V99: 2925.04 | W99: 3004.37 | X99: 2715.84 | Y99: 2248.33
A100: - услуги по передаче | B100: =$B$15 -> 1283.66 | C100: =$B100 -> 1283.66 | D100: =$B100 -> 1283.66 | E100: =$B100 -> 1283.66 | F100: =$B100 -> 1283.66 | G100: =$B100 -> 1283.66 | H100: =$B100 -> 1283.66 | I100: =$B100 -> 1283.66 | J100: =$B100 -> 1283.66 | ... Y100: =$B100 -> 1283.66
A101: - сбытовая надбавка ГП | B101: 75.85 | C101: 75.85 | D101: 75.85 | E101: 75.85 | F101: 75.85 | G101: 75.85 | H101: 75.85 | I101: 75.85 | J101: 75.85 | K101: 75.85 | L101: 75.85 | M101: 75.85 | N101: 75.85 | O101: 75.85 | P101: 75.85 | Q101: 75.85 | R101: 75.85 | S101: 75.85 | T101: 75.85 | U101: 75.85 | V101: 75.85 | W101: 75.85 | X101: 75.85 | Y101: 75.85
A102: - инфраструктурные платежи | B102: =$B$17 -> 5.35 | C102: =$B102 -> 5.35 | D102: =$B102 -> 5.35 | E102: =$B102 -> 5.35 | F102: =$B102 -> 5.35 | G102: =$B102 -> 5.35 | H102: =$B102 -> 5.35 | I102: =$B102 -> 5.35 | J102: =$B102 -> 5.35 | ... Y102: =$B102 -> 5.35
A103: 19 | B103: =B104+B105+B106+B107 -> 3201.61 | C103: =C104+C105+C106+C107 -> 2946.17 | D103: =D104+D105+D106+D107 -> 2794.52 | E103: =E104+E105+E106+E107 -> 2586.74 | F103: =F104+F105+F106+F107 -> 2510.25 | G103: =G104+G105+G106+G107 -> 2597.22 | H103: =H104+H105+H106+H107 -> 2607.73 | I103: =I104+I105+I106+I107 -> 2840.01 | ... Y103: =Y104+Y105+Y106+Y107 -> 3546.86
A104: - средневзв. стоимость э/э (м) | B104: 1836.75 | C104: 1581.31 | D104: 1429.66 | E104: 1221.88 | F104: 1145.39 | G104: 1232.36 | H104: 1242.87 | I104: 1475.15 | J104: 2322.34 | K104: 2778.06 | L104: 2855.51 | M104: 2867.19 | N104: 2907.61 | O104: 2915.85 | P104: 2923.28 | Q104: 2914.06 | R104: 2934.88 | S104: 2901.65 | T104: 2878.85 | U104: 2849.21 | V104: 2835.47 | W104: 2815.49 | X104: 2659.81 | Y104: 2182
...

Sheet М_июль 4 цк
A2: ='М_июль 1 цк'!A2 -> Предельные уровни нерегулируемых цен на электрическую энергию (мощность), поставляемую АО "Мосэнергосбыт" потребителям
A3: ='М_июль 1 цк'!A3 -> с максимальной мощностью энергопринимающих устройств не менее 10 МВт
A4: ='М_июль 1 цк'!A4 -> г. Москва
A5: ='М_июль 1 цк'!A5 -> Июль 2025 г.
A7: IV. Четвертая ценовая категория для объемов покупки электрической энергии (мощности), в отношении которых за расчетный период осуществляется почасовой учет, но не осуществляется почасовое планирование, а стоимость услуг по передаче электрической энергии определяется по тарифу на услуги по передаче электрической энергии в двухставочном выражении
A9: 1.1. Ставка за электрическую энергию предельного уровня нерегулируемых цен для абонентов группы "Иные прочие потребители", рублей/МВт∙ч без НДС
A11: Дата | B11: Ставка для фактических почасовых объемов покупки электрической энергии, отпущенных на уровне напряжения ВН
B12: 0:00-1:00 | C12: 1:00-2:00 | D12: 2:00-3:00 | E12: 3:00-4:00 | F12: 4:00-5:00 | G12: 5:00-6:00 | H12: 6:00-7:00 | I12: 7:00-8:00 | J12: 8:00-9:00 | K12: 9:00-10:00 | L12: 10:00-11:00 | M12: 11:00-12:00 | N12: 12:00-13:00 | O12: 13:00-14:00 | P12: 14:00-15:00 | Q12: 15:00-16:00 | R12: 16:00-17:00 | S12: 17:00-18:00 | T12: 18:00-19:00 | U12: 19:00-20:00 | V12: 20:00-21:00 | W12: 21:00-22:00 | X12: 22:00-23:00 | Y12: 23:00-0:00
A13: 1 | B13: =B14+B15+B16+B17 -> 1805.41 | C13: =C14+C15+C16+C17 -> 1536.87 | D13: =D14+D15+D16+D17 -> 1421.79 | E13: =E14+E15+E16+E17 -> 1320.99 | F13: =F14+F15+F16+F17 -> 1343.06 | G13: =G14+G15+G16+G17 -> 1628.35 | H13: =H14+H15+H16+H17 -> 1753.58 | I13: =I14+I15+I16+I17 -> 2205.44 | ... Y13: =Y14+Y15+Y16+Y17 -> 2227.55
A14: - средневзв. стоимость э/э (м) | B14: 1643.63 | C14: 1375.09 | D14: 1260.01 | E14: 1159.21 | F14: 1181.28 | G14: 1466.57 | H14: 1591.8 | I14: 2043.66 | J14: 2544.33 | K14: 2682.61 | L14: 2744.97 | M14: 2743.85 | N14: 2729.42 | O14: 2739.69 | P14: 2768.75 | Q14: 2783.49 | R14: 2762.56 | S14: 2768.68 | T14: 2746.78 | U14: 2697.44 | V14: 2663.63 | W14: 2636.06 | X14: 2326.79 | Y14: 2065.77
A15: - услуги по передаче | B15: 80.58 | C15: =$B15 -> 80.58 | D15: =$B15 -> 80.58 | E15: =$B15 -> 80.58 | F15: =$B15 -> 80.58 | G15: =$B15 -> 80.58 | H15: =$B15 -> 80.58 | I15: =$B15 -> 80.58 | J15: =$B15 -> 80.58 | ... Y15: =$B15 -> 80.58
A16: - сбытовая надбавка ГП | B16: 75.85 | C16: 75.85 | D16: 75.85 | E16: 75.85 | F16: 75.85 | G16: 75.85 | H16: 75.85 | I16: 75.85 | J16: 75.85 | K16: 75.85 | L16: 75.85 | M16: 75.85 | N16: 75.85 | O16: 75.85 | P16: 75.85 | Q16: 75.85 | R16: 75.85 | S16: 75.85 | T16: 75.85 | U16: 75.85 | V16: 75.85 | W16: 75.85 | X16: 75.85 | Y16: 75.85
A17: - инфраструктурные платежи | B17: 5.35 | C17: =$B17 -> 5.35 | D17: =$B17 -> 5.35 | E17: =$B17 -> 5.35 | F17: =$B17 -> 5.35 | G17: =$B17 -> 5.35 | H17: =$B17 -> 5.35 | I17: =$B17 -> 5.35 | J17: =$B17 -> 5.35 | ... Y17: =$B17 -> 5.35
A18: 2 | B18: =B19+B20+B21+B22 -> 1850.76 | C18: =C19+C20+C21+C22 -> 1690.78 | D18: =D19+D20+D21+D22 -> 1607.13 | E18: =E19+E20+E21+E22 -> 1391.63 | F18: =F19+F20+F21+F22 -> 1485.94 | G18: =G19+G20+G21+G22 -> 1686.99 | H18: =H19+H20+H21+H22 -> 1769.09 | I18: =I19+I20+I21+I22 -> 2256.12 | ... Y18: =Y19+Y20+Y21+Y22 -> 2162.16
A19: - средневзв. стоимость э/э (м) | B19: 1688.98 | C19: 1529 | D19: 1445.35 | E19: 1229.85 | F19: 1324.16 | G19: 1525.21 | H19: 1607.31 | I19: 2094.34 | J19: 2706.96 | K19: 2804.21 | L19: 2837.46 | M19: 2828.28 | N19: 2843.1 | O19: 2873.1 | P19: 2874.34 | Q19: 2863.78 | R19: 2837.34 | S19: 2817.79 | T19: 2806.9 | U19: 2778.96 | V19: 2748.46 | W19: 2727.03 | X19: 2445.18 | Y19: 2000.38
A20: - услуги по передаче | B20: =$B$15 -> 80.58 | C20: =$B20 -> 80.58 | D20: =$B20 -> 80.58 | E20: =$B20 -> 80.58 | F20: =$B20 -> 80.58 | G20: =$B20 -> 80.58 | H20: =$B20 -> 80.58 | I20: =$B20 -> 80.58 | J20: =$B20 -> 80.58 | ... Y20: =$B20 -> 80.58
A21: - сбытовая надбавка ГП | B21: 75.85 | C21: 75.85 | D21: 75.85 | E21: 75.85 | F21: 75.85 | G21: 75.85 | H21: 75.85 | I21: 75.85 | J21: 75.85 | K21: 75.85 | L21: 75.85 | M21: 75.85 | N21: 75.85 | O21: 75.85 | P21: 75.85 | Q21: 75.85 | R21: 75.85 | S21: 75.85 | T21: 75.85 | U21: 75.85 | V21: 75.85 | W21: 75.85 | X21: 75.85 | Y21: 75.85
A22: - инфраструктурные платежи | B22: =$B$17 -> 5.35 | C22: =$B22 -> 5.35 | D22: =$B22 -> 5.35 | E22: =$B22 -> 5.35 | F22: =$B22 -> 5.35 | G22: =$B22 -> 5.35 | H22: =$B22 -> 5.35 | I22: =$B22 -> 5.35 | J22: =$B22 -> 5.35 | ... Y22: =$B22 -> 5.35
A23: 3 | B23: =B24+B25+B26+B27 -> 1732.68 | C23: =C24+C25+C26+C27 -> 1574.49 | D23: =D24+D25+D26+D27 -> 1451.3 | E23: =E24+E25+E26+E27 -> 1335.6 | F23: =F24+F25+F26+F27 -> 1347.21 | G23: =G24+G25+G26+G27 -> 1572.67 | H23: =H24+H25+H26+H27 -> 1716.63 | I23: =I24+I25+I26+I27 -> 2170.82 | ... Y23: =Y24+Y25+Y26+Y27 -> 2150.44
A24: - средневзв. стоимость э/э (м) | B24: 1570.9 | C24: 1412.71 | D24: 1289.52 | E24: 1173.82 | F24: 1185.43 | G24: 1410.89 | H24: 1554.85 | I24: 2009.04 | J24: 2559.55 | K24: 2598.88 | L24: 2641.18 | M24: 2673.9 | N24: 2667.07 | O24: 2651.63 | P24: 2872.93 | Q24: 2941.52 | R24: 2884.71 | S24: 2688.33 | T24: 2757.86 | U24: 2651.34 | V24: 2696.89 | W24: 2677.99 | X24: 2417.66 | Y24: 1988.66
A25: - услуги по передаче | B25: =$B$15 -> 80.58 | C25: =$B25 -> 80.58 | D25: =$B25 -> 80.58 | E25: =$B25 -> 80.58 | F25: =$B25 -> 80.58 | G25: =$B25 -> 80.58 | H25: =$B25 -> 80.58 | I25: =$B25 -> 80.58 | J25: =$B25 -> 80.58 | ... Y25: =$B25 -> 80.58
A26: - сбытовая надбавка ГП | B26: 75.85 | C26: 75.85 | D26: 75.85 | E26: 75.85 | F26: 75.85 | G26: 75.85 | H26: 75.85 | I26: 75.85 | J26: 75.85 | K26: 75.85 | L26: 75.85 | M26: 75.85 | N26: 75.85 | O26: 75.85 | P26: 75.85 | Q26: 75.85 | R26: 75.85 | S26: 75.85 | T26: 75.85 | U26: 75.85 | V26: 75.85 | W26: 75.85 | X26: 75.85 | Y26: 75.85
A27: - инфраструктурные платежи | B27: =$B$17 -> 5.35 | C27: =$B27 -> 5.35 | D27: =$B27 -> 5.35 | E27: =$B27 -> 5.35 | F27: =$B27 -> 5.35 | G27: =$B27 -> 5.35 | H27: =$B27 -> 5.35 | I27: =$B27 -> 5.35 | J27: =$B27 -> 5.35 | ... Y27: =$B27 -> 5.35
A28: 4 | B28: =B29+B30+B31+B32 -> 1823.3 | C28: =C29+C30+C31+C32 -> 1603.27 | D28: =D29+D30+D31+D32 -> 1457.82 | E28: =E29+E30+E31+E32 -> 1328.54 | F28: =F29+F30+F31+F32 -> 1345.03 | G28: =G29+G30+G31+G32 -> 1577.58 | H28: =H29+H30+H31+H32 -> 1729.66 | I28: =I29+I30+I31+I32 -> 2192.28 | ... Y28: =Y29+Y30+Y31+Y32 -> 2207.28
A29: - средневзв. стоимость э/э (м) | B29: 1661.52 | C29: 1441.49 | D29: 1296.04 | E29: 1166.76 | F29: 1183.25 | G29: 1415.8 | H29: 1567.88 | I29: 2030.5 | J29: 2568.65 | K29: 2687.94 | L29: 2641.38 | M29: 2639.93 | N29: 2707.75 | O29: 2639.25 | P29: 2784.72 | Q29: 2836.9 | R29: 2818.07 | S29: 2794.9 | T29: 2781.67 | U29: 2648.88 | V29: 2631.45 | W29: 2708.37 | X29: 2511.35 | Y29: 2045.5
A30: - услуги по передаче | B30: =$B$15 -> 80.58 | C30: =$B30 -> 80.58 | D30: =$B30 -> 80.58 | E30: =$B30 -> 80.58 | F30: =$B30 -> 80.58 | G30: =$B30 -> 80.58 | H30: =$B30 -> 80.58 | I30: =$B30 -> 80.58 | J30: =$B30 -> 80.58 | ... Y30: =$B30 -> 80.58
A31: - сбытовая надбавка ГП | B31: 75.85 | C31: 75.85 | D31: 75.85 | E31: 75.85 | F31: 75.85 | G31: 75.85 | H31: 75.85 | I31: 75.85 | J31: 75.85 | K31: 75.85 | L31: 75.85 | M31: 75.85 | N31: 75.85 | O31: 75.85 | P31: 75.85 | Q31: 75.85 | R31: 75.85 | S31: 75.85 | T31: 75.85 | U31: 75.85 | V31: 75.85 | W31: 75.85 | X31: 75.85 | Y31: 75.85
A32: - инфраструктурные платежи | B32: =$B$17 -> 5.35 | C32: =$B32 -> 5.35 | D32: =$B32 -> 5.35 | E32: =$B32 -> 5.35 | F32: =$B32 -> 5.35 | G32: =$B32 -> 5.35 | H32: =$B32 -> 5.35 | I32: =$B32 -> 5.35 | J32: =$B32 -> 5.35 | ... Y32: =$B32 -> 5.35
A33: 5 | B33: =B34+B35+B36+B37 -> 1915.14 | C33: =C34+C35+C36+C37 -> 1680.91 | D33: =D34+D35+D36+D37 -> 1573.86 | E33: =E34+E35+E36+E37 -> 1430.72 | F33: =F34+F35+F36+F37 -> 1372.43 | G33: =G34+G35+G36+G37 -> 1363.48 | H33: =H34+H35+H36+H37 -> 1466.64 | I33: =I34+I35+I36+I37 -> 1830.8 | ... Y33: =Y34+Y35+Y36+Y37 -> 2142.94
A34: - средневзв. стоимость э/э (м) | B34: 1753.36 | C34: 1519.13 | D34: 1412.08 | E34: 1268.94 | F34: 1210.65 | G34: 1201.7 | H34: 1304.86 | I34: 1669.02 | J34: 2134.91 | K34: 2370.79 | L34: 2439.61 | M34: 2468.97 | N34: 2464.34 | O34: 2468.42 | P34: 2464.8 | Q34: 2527.1 | R34: 2535.38 | S34: 2500.69 | T34: 2480.64 | U34: 2452.58 | V34: 2450.49 | W34: 2467.58 | X34: 2169.48 | Y34: 1981.16
A35: - услуги по передаче | B35: =$B$15 -> 80.58 | C35: =$B35 -> 80.58 | D35: =$B35 -> 80.58 | E35: =$B35 -> 80.58 | F35: =$B35 -> 80.58 | G35: =$B35 -> 80.58 | H35: =$B35 -> 80.58 | I35: =$B35 -> 80.58 | J35: =$B35 -> 80.58 | ... Y35: =$B35 -> 80.58
A36: - сбытовая надбавка ГП | B36: 75.85 | C36: 75.85 | D36: 75.85 | E36: 75.85 | F36: 75.85 | G36: 75.85 | H36: 75.85 | I36: 75.85 | J36: 75.85 | K36: 75.85 | L36: 75.85 | M36: 75.85 | N36: 75.85 | O36: 75.85 | P36: 75.85 | Q36: 75.85 | R36: 75.85 | S36: 75.85 | T36: 75.85 | U36: 75.85 | V36: 75.85 | W36: 75.85 | X36: 75.85 | Y36: 75.85
A37: - инфраструктурные платежи | B37: =$B$17 -> 5.35 | C37: =$B37 -> 5.35 | D37: =$B37 -> 5.35 | E37: =$B37 -> 5.35 | F37: =$B37 -> 5.35 | G37: =$B37 -> 5.35 | H37: =$B37 -> 5.35 | I37: =$B37 -> 5.35 | J37: =$B37 -> 5.35 | ... Y37: =$B37 -> 5.35
A38: 6 | B38: =B39+B40+B41+B42 -> 1923.43 | C38: =C39+C40+C41+C42 -> 1669.36 | D38: =D39+D40+D41+D42 -> 1548.38 | E38: =E39+E40+E41+E42 -> 1362.75 | F38: =F39+F40+F41+F42 -> 1305.26 | G38: =G39+G40+G41+G42 -> 1304.19 | H38: =H39+H40+H41+H42 -> 1248.94 | I38: =I39+I40+I41+I42 -> 1677.79 | ... Y38: =Y39+Y40+Y41+Y42 -> 2004.32
A39: - средневзв. стоимость э/э (м) | B39: 1761.65 | C39: 1507.58 | D39: 1386.6 | E39: 1200.97 | F39: 1143.48 | G39: 1142.41 | H39: 1087.16 | I39: 1516.01 | J39: 1920.92 | K39: 2258.81 | L39: 2395.9 | M39: 2395.86 | N39: 2398.62 | O39: 2405.7 | P39: 2410.55 | Q39: 2412.36 | R39: 2465.57 | S39: 2451.43 | T39: 2449.76 | U39: 2433.67 | V39: 2433.2 | W39: 2429.4 | X39: 2185.02 | Y39: 1842.54
A40: - услуги по передаче | B40: =$B$15 -> 80.58 | C40: =$B40 -> 80.58 | D40: =$B40 -> 80.58 | E40: =$B40 -> 80.58 | F40: =$B40 -> 80.58 | G40: =$B40 -> 80.58 | H40: =$B40 -> 80.58 | I40: =$B40 -> 80.58 | J40: =$B40 -> 80.58 | ... Y40: =$B40 -> 80.58
A41: - сбытовая надбавка ГП | B41: 75.85 | C41: 75.85 | D41: 75.85 | E41: 75.85 | F41: 75.85 | G41: 75.85 | H41: 75.85 | I41: 75.85 | J41: 75.85 | K41: 75.85 | L41: 75.85 | M41: 75.85 | N41: 75.85 | O41: 75.85 | P41: 75.85 | Q41: 75.85 | R41: 75.85 | S41: 75.85 | T41: 75.85 | U41: 75.85 | V41: 75.85 | W41: 75.85 | X41: 75.85 | Y41: 75.85
A42: - инфраструктурные платежи | B42: =$B$17 -> 5.35 | C42: =$B42 -> 5.35 | D42: =$B42 -> 5.35 | E42: =$B42 -> 5.35 | F42: =$B42 -> 5.35 | G42: =$B42 -> 5.35 | H42: =$B42 -> 5.35 | I42: =$B42 -> 5.35 | J42: =$B42 -> 5.35 | ... Y42: =$B42 -> 5.35
A43: 7 | B43: =B44+B45+B46+B47 -> 1847.69 | C43: =C44+C45+C46+C47 -> 1679.16 | D43: =D44+D45+D46+D47 -> 1478.53 | E43: =E44+E45+E46+E47 -> 1333.8 | F43: =F44+F45+F46+F47 -> 1302.6 | G43: =G44+G45+G46+G47 -> 1392.18 | H43: =H44+H45+H46+H47 -> 1698.32 | I43: =I44+I45+I46+I47 -> 2139.55 | ... Y43: =Y44+Y45+Y46+Y47 -> 2031.86
A44: - средневзв. стоимость э/э (м) | B44: 1685.91 | C44: 1517.38 | D44: 1316.75 | E44: 1172.02 | F44: 1140.82 | G44: 1230.4 | H44: 1536.54 | I44: 1977.77 | J44: 2516.42 | K44: 2642.82 | L44: 2703.04 | M44: 2743.84 | N44: 2728.5 | O44: 2752.78 | P44: 2737.88 | Q44: 2771.21 | R44: 2719.3 | S44: 2834.06 | T44: 2733.83 | U44: 2697.7 | V44: 2643.26 | W44: 2659.85 | X44: 2219.27 | Y44: 1870.08
A45: - услуги по передаче | B45: =$B$15 -> 80.58 | C45: =$B45 -> 80.58 | D45: =$B45 -> 80.58 | E45: =$B45 -> 80.58 | F45: =$B45 -> 80.58 | G45: =$B45 -> 80.58 | H45: =$B45 -> 80.58 | I45: =$B45 -> 80.58 | J45: =$B45 -> 80.58 | ... Y45: =$B45 -> 80.58
A46: - сбытовая надбавка ГП | B46: 75.85 | C46: 75.85 | D46: 75.85 | E46: 75.85 | F46: 75.85 | G46: 75.85 | H46: 75.85 | I46: 75.85 | J46: 75.85 | K46: 75.85 | L46: 75.85 | M46: 75.85 | N46: 75.85 | O46: 75.85 | P46: 75.85 | Q46: 75.85 | R46: 75.85 | S46: 75.85 | T46: 75.85 | U46: 75.85 | V46: 75.85 | W46: 75.85 | X46: 75.85 | Y46: 75.85
A47: - инфраструктурные платежи | B47: =$B$17 -> 5.35 | C47: =$B47 -> 5.35 | D47: =$B47 -> 5.35 | E47: =$B47 -> 5.35 | F47: =$B47 -> 5.35 | G47: =$B47 -> 5.35 | H47: =$B47 -> 5.35 | I47: =$B47 -> 5.35 | J47: =$B47 -> 5.35 | ... Y47: =$B47 -> 5.35
A48: 8 | B48: =B49+B50+B51+B52 -> 1680.91 | C48: =C49+C50+C51+C52 -> 1406.8 | D48: =D49+D50+D51+D52 -> 1243.8 | E48: =E49+E50+E51+E52 -> 351.93 | F48: =F49+F50+F51+F52 -> 310.36 | G48: =G49+G50+G51+G52 -> 325.57 | H48: =H49+H50+H51+H52 -> 1383.78 | I48: =I49+I50+I51+I52 -> 1979.35 | ... Y48: =Y49+Y50+Y51+Y52 -> 2017.32
A49: - средневзв. стоимость э/э (м) | B49: 1519.13 | C49: 1245.02 | D49: 1082.02 | E49: 190.15 | F49: 148.58 | G49: 163.79 | H49: 1222 | I49: 1817.57 | J49: 2386.8 | K49: 2620.89 | L49: 2753.89 | M49: 2766.53 | N49: 2750.06 | O49: 2752.45 | P49: 3081.15 | Q49: 2829.37 | R49: 2852.62 | S49: 2826.79 | T49: 2731.55 | U49: 2624.77 | V49: 2604.67 | W49: 2544.9 | X49: 2150.53 | Y49: 1855.54
A50: - услуги по передаче | B50: =$B$15 -> 80.58 | C50: =$B50 -> 80.58 | D50: =$B50 -> 80.58 | E50: =$B50 -> 80.58 | F50: =$B50 -> 80.58 | G50: =$B50 -> 80.58 | H50: =$B50 -> 80.58 | I50: =$B50 -> 80.58 | J50: =$B50 -> 80.58 | ... Y50: =$B50 -> 80.58
A51: - сбытовая надбавка ГП | B51: 75.85 | C51: 75.85 | D51: 75.85 | E51: 75.85 | F51: 75.85 | G51: 75.85 | H51: 75.85 | I51: 75.85 | J51: 75.85 | K51: 75.85 | L51: 75.85 | M51: 75.85 | N51: 75.85 | O51: 75.85 | P51: 75.85 | Q51: 75.85 | R51: 75.85 | S51: 75.85 | T51: 75.85 | U51: 75.85 | V51: 75.85 | W51: 75.85 | X51: 75.85 | Y51: 75.85
A52: - инфраструктурные платежи | B52: =$B$17 -> 5.35 | C52: =$B52 -> 5.35 | D52: =$B52 -> 5.35 | E52: =$B52 -> 5.35 | F52: =$B52 -> 5.35 | G52: =$B52 -> 5.35 | H52: =$B52 -> 5.35 | I52: =$B52 -> 5.35 | J52: =$B52 -> 5.35 | ... Y52: =$B52 -> 5.35
A53: 9 | B53: =B54+B55+B56+B57 -> 1854.41 | C53: =C54+C55+C56+C57 -> 1287.94 | D53: =D54+D55+D56+D57 -> 318.84 | E53: =E54+E55+E56+E57 -> 314.62 | F53: =F54+F55+F56+F57 -> 312.15 | G53: =G54+G55+G56+G57 -> 325.44 | H53: =H54+H55+H56+H57 -> 1291.35 | I53: =I54+I55+I56+I57 -> 1993.85 | ... Y53: =Y54+Y55+Y56+Y57 -> 1751.93
A54: - средневзв. стоимость э/э (м) | B54: 1692.63 | C54: 1126.16 | D54: 157.06 | E54: 152.84 | F54: 150.37 | G54: 163.66 | H54: 1129.57 | I54: 1832.07 | J54: 2133.88 | K54: 2497.34 | L54: 2693.5 | M54: 2757.98 | N54: 2756.02 | O54: 3052.55 | P54: 3209.79 | Q54: 3223.31 | R54: 3167.97 | S54: 3140.22 | T54: 2786.8 | U54: 2570.26 | V54: 2515.07 | W54: 2497.39 | X54: 2056.21 | Y54: 1590.15
A55: - услуги по передаче | B55: =$B$15 -> 80.58 | C55: =$B55 -> 80.58 | D55: =$B55 -> 80.58 | E55: =$B55 -> 80.58 | F55: =$B55 -> 80.58 | G55: =$B55 -> 80.58 | H55: =$B55 -> 80.58 | I55: =$B55 -> 80.58 | J55: =$B55 -> 80.58 | ... Y55: =$B55 -> 80.58
A56: - сбытовая надбавка ГП | B56: 75.85 | C56: 75.85 | D56: 75.85 | E56: 75.85 | F56: 75.85 | G56: 75.85 | H56: 75.85 | I56: 75.85 | J56: 75.85 | K56: 75.85 | L56: 75.85 | M56: 75.85 | N56: 75.85 | O56: 75.85 | P56: 75.85 | Q56: 75.85 | R56: 75.85 | S56: 75.85 | T56: 75.85 | U56: 75.85 | V56: 75.85 | W56: 75.85 | X56: 75.85 | Y56: 75.85
A57: - инфраструктурные платежи | B57: =$B$17 -> 5.35 | C57: =$B57 -> 5.35 | D57: =$B57 -> 5.35 | E57: =$B57 -> 5.35 | F57: =$B57 -> 5.35 | G57: =$B57 -> 5.35 | H57: =$B57 -> 5.35 | I57: =$B57 -> 5.35 | J57: =$B57 -> 5.35 | ... Y57: =$B57 -> 5.35
A58: 10 | B58: =B59+B60+B61+B62 -> 1506.54 | C58: =C59+C60+C61+C62 -> 1237.67 | D58: =D59+D60+D61+D62 -> 304.68 | E58: =E59+E60+E61+E62 -> 281.85 | F58: =F59+F60+F61+F62 -> 288.93 | G58: =G59+G60+G61+G62 -> 309.03 | H58: =H59+H60+H61+H62 -> 870.59 | I58: =I59+I60+I61+I62 -> 1782.28 | ... Y58: =Y59+Y60+Y61+Y62 -> 1971.53
A59: - средневзв. стоимость э/э (м) | B59: 1344.76 | C59: 1075.89 | D59: 142.9 | E59: 120.07 | F59: 127.15 | G59: 147.25 | H59: 708.81 | I59: 1620.5 | J59: 2220.31 | K59: 2731.02 | L59: 3037.45 | M59: 3178.14 | N59: 2657.09 | O59: 3029.52 | P59: 3237.11 | Q59: 3082.44 | R59: 3084.05 | S59: 3007.53 | T59: 2862.95 | U59: 2840.64 | V59: 2729.6 | W59: 2671.87 | X59: 2185.28 | Y59: 1809.75
A60: - услуги по передаче | B60: =$B$15 -> 80.58 | C60: =$B60 -> 80.58 | D60: =$B60 -> 80.58 | E60: =$B60 -> 80.58 | F60: =$B60 -> 80.58 | G60: =$B60 -> 80.58 | H60: =$B60 -> 80.58 | I60: =$B60 -> 80.58 | J60: =$B60 -> 80.58 | ... Y60: =$B60 -> 80.58
A61: - сбытовая надбавка ГП | B61: 75.85 | C61: 75.85 | D61: 75.85 | E61: 75.85 | F61: 75.85 | G61: 75.85 | H61: 75.85 | I61: 75.85 | J61: 75.85 | K61: 75.85 | L61: 75.85 | M61: 75.85 | N61: 75.85 | O61: 75.85 | P61: 75.85 | Q61: 75.85 | R61: 75.85 | S61: 75.85 | T61: 75.85 | U61: 75.85 | V61: 75.85 | W61: 75.85 | X61: 75.85 | Y61: 75.85
A62: - инфраструктурные платежи | B62: =$B$17 -> 5.35 | C62: =$B62 -> 5.35 | D62: =$B62 -> 5.35 | E62: =$B62 -> 5.35 | F62: =$B62 -> 5.35 | G62: =$B62 -> 5.35 | H62: =$B62 -> 5.35 | I62: =$B62 -> 5.35 | J62: =$B62 -> 5.35 | ... Y62: =$B62 -> 5.35
A63: 11 | B63: =B64+B65+B66+B67 -> 1625.3 | C63: =C64+C65+C66+C67 -> 1400.98 | D63: =D64+D65+D66+D67 -> 319.36 | E63: =E64+E65+E66+E67 -> 313.39 | F63: =F64+F65+F66+F67 -> 313.98 | G63: =G64+G65+G66+G67 -> 316.65 | H63: =H64+H65+H66+H67 -> 1507.6 | I63: =I64+I65+I66+I67 -> 1940.11 | ... Y63: =Y64+Y65+Y66+Y67 -> 2221.74
A64: - средневзв. стоимость э/э (м) | B64: 1463.52 | C64: 1239.2 | D64: 157.58 | E64: 151.61 | F64: 152.2 | G64: 154.87 | H64: 1345.82 | I64: 1778.33 | J64: 2517.19 | K64: 2779.58 | L64: 2799.71 | M64: 2902.42 | N64: 2914.86 | O64: 2982.36 | P64: 2754.11 | Q64: 3061.37 | R64: 3061.84 | S64: 3348.84 | T64: 2924.97 | U64: 2837.1 | V64: 2959.58 | W64: 2832.44 | X64: 2367.04 | Y64: 2059.96
A65: - услуги по передаче | B65: =$B$15 -> 80.58 | C65: =$B65 -> 80.58 | D65: =$B65 -> 80.58 | E65: =$B65 -> 80.58 | F65: =$B65 -> 80.58 | G65: =$B65 -> 80.58 | H65: =$B65 -> 80.58 | I65: =$B65 -> 80.58 | J65: =$B65 -> 80.58 | ... Y65: =$B65 -> 80.58
A66: - сбытовая надбавка ГП | B66: 75.85 | C66: 75.85 | D66: 75.85 | E66: 75.85 | F66: 75.85 | G66: 75.85 | H66: 75.85 | I66: 75.85 | J66: 75.85 | K66: 75.85 | L66: 75.85 | M66: 75.85 | N66: 75.85 | O66: 75.85 | P66: 75.85 | Q66: 75.85 | R66: 75.85 | S66: 75.85 | T66: 75.85 | U66: 75.85 | V66: 75.85 | W66: 75.85 | X66: 75.85 | Y66: 75.85
A67: - инфраструктурные платежи | B67: =$B$17 -> 5.35 | C67: =$B67 -> 5.35 | D67: =$B67 -> 5.35 | E67: =$B67 -> 5.35 | F67: =$B67 -> 5.35 | G67: =$B67 -> 5.35 | H67: =$B67 -> 5.35 | I67: =$B67 -> 5.35 | J67: =$B67 -> 5.35 | ... Y67: =$B67 -> 5.35
A68: 12 | B68: =B69+B70+B71+B72 -> 1936.44 | C68: =C69+C70+C71+C72 -> 1610.02 | D68: =D69+D70+D71+D72 -> 1444.65 | E68: =E69+E70+E71+E72 -> 523.77 | F68: =F69+F70+F71+F72 -> 339.53 | G68: =G69+G70+G71+G72 -> 336.66 | H68: =H69+H70+H71+H72 -> 1276.86 | I68: =I69+I70+I71+I72 -> 1792.29 | ... Y68: =Y69+Y70+Y71+Y72 -> 2312.84
A69: - средневзв. стоимость э/э (м) | B69: 1774.66 | C69: 1448.24 | D69: 1282.87 | E69: 361.99 | F69: 177.75 | G69: 174.88 | H69: 1115.08 | I69: 1630.51 | J69: 2215.05 | K69: 2564.66 | L69: 2743.61 | M69: 2757.38 | N69: 2751.08 | O69: 2846.09 | P69: 2860.77 | Q69: 2799.77 | R69: 3214.08 | S69: 3164.24 | T69: 2779.49 | U69: 2679.46 | V69: 2779.53 | W69: 2846.71 | X69: 2556.08 | Y69: 2151.06
A70: - услуги по передаче | B70: =$B$15 -> 80.58 | C70: =$B70 -> 80.58 | D70: =$B70 -> 80.58 | E70: =$B70 -> 80.58 | F70: =$B70 -> 80.58 | G70: =$B70 -> 80.58 | H70: =$B70 -> 80.58 | I70: =$B70 -> 80.58 | J70: =$B70 -> 80.58 | ... Y70: =$B70 -> 80.58
A71: - сбытовая надбавка ГП | B71: 75.85 | C71: 75.85 | D71: 75.85 | E71: 75.85 | F71: 75.85 | G71: 75.85 | H71: 75.85 | I71: 75.85 | J71: 75.85 | K71: 75.85 | L71: 75.85 | M71: 75.85 | N71: 75.85 | O71: 75.85 | P71: 75.85 | Q71: 75.85 | R71: 75.85 | S71: 75.85 | T71: 75.85 | U71: 75.85 | V71: 75.85 | W71: 75.85 | X71: 75.85 | Y71: 75.85
A72: - инфраструктурные платежи | B72: =$B$17 -> 5.35 | C72: =$B72 -> 5.35 | D72: =$B72 -> 5.35 | E72: =$B72 -> 5.35 | F72: =$B72 -> 5.35 | G72: =$B72 -> 5.35 | H72: =$B72 -> 5.35 | I72: =$B72 -> 5.35 | J72: =$B72 -> 5.35 | ... Y72: =$B72 -> 5.35
A73: 13 | B73: =B74+B75+B76+B77 -> 1860.16 | C73: =C74+C75+C76+C77 -> 1647.44 | D73: =D74+D75+D76+D77 -> 1478.78 | E73: =E74+E75+E76+E77 -> 364.41 | F73: =F74+F75+F76+F77 -> 329.22 | G73: =G74+G75+G76+G77 -> 325.95 | H73: =H74+H75+H76+H77 -> 1133.53 | I73: =I74+I75+I76+I77 -> 1596.37 | ... Y73: =Y74+Y75+Y76+Y77 -> 2172.19
A74: - средневзв. стоимость э/э (м) | B74: 1698.38 | C74: 1485.66 | D74: 1317 | E74: 202.63 | F74: 167.44 | G74: 164.17 | H74: 971.75 | I74: 1434.59 | J74: 1978.25 | K74: 2469.39 | L74: 2591.3 | M74: 2585.28 | N74: 2770.57 | O74: 2728.68 | P74: 2791.8 | Q74: 2808.61 | R74: 2785.21 | S74: 2911.59 | T74: 2831.65 | U74: 2752.88 | V74: 2732.52 | W74: 2727.08 | X74: 2460.78 | Y74: 2010.41
A75: - услуги по передаче | B75: =$B$15 -> 80.58 | C75: =$B75 -> 80.58 | D75: =$B75 -> 80.58 | E75: =$B75 -> 80.58 | F75: =$B75 -> 80.58 | G75: =$B75 -> 80.58 | H75: =$B75 -> 80.58 | I75: =$B75 -> 80.58 | J75: =$B75 -> 80.58 | ... Y75: =$B75 -> 80.58
A76: - сбытовая надбавка ГП | B76: 75.85 | C76: 75.85 | D76: 75.85 | E76: 75.85 | F76: 75.85 | G76: 75.85 | H76: 75.85 | I76: 75.85 | J76: 75.85 | K76: 75.85 | L76: 75.85 | M76: 75.85 | N76: 75.85 | O76: 75.85 | P76: 75.85 | Q76: 75.85 | R76: 75.85 | S76: 75.85 | T76: 75.85 | U76: 75.85 | V76: 75.85 | W76: 75.85 | X76: 75.85 | Y76: 75.85
A77: - инфраструктурные платежи | B77: =$B$17 -> 5.35 | C77: =$B77 -> 5.35 | D77: =$B77 -> 5.35 | E77: =$B77 -> 5.35 | F77: =$B77 -> 5.35 | G77: =$B77 -> 5.35 | H77: =$B77 -> 5.35 | I77: =$B77 -> 5.35 | J77: =$B77 -> 5.35 | ... Y77: =$B77 -> 5.35
A78: 14 | B78: =B79+B80+B81+B82 -> 1732.94 | C78: =C79+C80+C81+C82 -> 1536.31 | D78: =D79+D80+D81+D82 -> 431.5 | E78: =E79+E80+E81+E82 -> 338.81 | F78: =F79+F80+F81+F82 -> 334.53 | G78: =G79+G80+G81+G82 -> 338.83 | H78: =H79+H80+H81+H82 -> 1353 | I78: =I79+I80+I81+I82 -> 2006.96 | ... Y78: =Y79+Y80+Y81+Y82 -> 1978.56
A79: - средневзв. стоимость э/э (м) | B79: 1571.16 | C79: 1374.53 | D79: 269.72 | E79: 177.03 | F79: 172.75 | G79: 177.05 | H79: 1191.22 | I79: 1845.18 | J79: 2619.18 | K79: 2871.52 | L79: 2895.84 | M79: 2902.83 | N79: 2894.62 | O79: 2900.41 | P79: 2894.5 | Q79: 2960.06 | R79: 2939.75 | S79: 2926.91 | T79: 2877.18 | U79: 2797.16 | V79: 2785.27 | W79: 2752.19 | X79: 2228.96 | Y79: 1816.78
A80: - услуги по передаче | B80: =$B$15 -> 80.58 | C80: =$B80 -> 80.58 | D80: =$B80 -> 80.58 | E80: =$B80 -> 80.58 | F80: =$B80 -> 80.58 | G80: =$B80 -> 80.58 | H80: =$B80 -> 80.58 | I80: =$B80 -> 80.58 | J80: =$B80 -> 80.58 | ... Y80: =$B80 -> 80.58
A81: - сбытовая надбавка ГП | B81: 75.85 | C81: 75.85 | D81: 75.85 | E81: 75.85 | F81: 75.85 | G81: 75.85 | H81: 75.85 | I81: 75.85 | J81: 75.85 | K81: 75.85 | L81: 75.85 | M81: 75.85 | N81: 75.85 | O81: 75.85 | P81: 75.85 | Q81: 75.85 | R81: 75.85 | S81: 75.85 | T81: 75.85 | U81: 75.85 | V81: 75.85 | W81: 75.85 | X81: 75.85 | Y81: 75.85
A82: - инфраструктурные платежи | B82: =$B$17 -> 5.35 | C82: =$B82 -> 5.35 | D82: =$B82 -> 5.35 | E82: =$B82 -> 5.35 | F82: =$B82 -> 5.35 | G82: =$B82 -> 5.35 | H82: =$B82 -> 5.35 | I82: =$B82 -> 5.35 | J82: =$B82 -> 5.35 | ... Y82: =$B82 -> 5.35
A83: 15 | B83: =B84+B85+B86+B87 -> 1579.12 | C83: =C84+C85+C86+C87 -> 1389.59 | D83: =D84+D85+D86+D87 -> 1229.99 | E83: =E84+E85+E86+E87 -> 270.9 | F83: =F84+F85+F86+F87 -> 193.35 | G83: =G84+G85+G86+G87 -> 269.52 | H83: =H84+H85+H86+H87 -> 1185.27 | I83: =I84+I85+I86+I87 -> 2007.22 | ... Y83: =Y84+Y85+Y86+Y87 -> 2082.78
A84: - средневзв. стоимость э/э (м) | B84: 1417.34 | C84: 1227.81 | D84: 1068.21 | E84: 109.12 | F84: 31.57 | G84: 107.74 | H84: 1023.49 | I84: 1845.44 | J84: 2433.4 | K84: 2892.37 | L84: 2879.59 | M84: 2948.78 | N84: 2950.12 | O84: 2969.15 | P84: 2956.29 | Q84: 2978.09 | R84: 3013.06 | S84: 3049.74 | T84: 2962.02 | U84: 2846.26 | V84: 2745.91 | W84: 2742.16 | X84: 2196.13 | Y84: 1921
A85: - услуги по передаче | B85: =$B$15 -> 80.58 | C85: =$B85 -> 80.58 | D85: =$B85 -> 80.58 | E85: =$B85 -> 80.58 | F85: =$B85 -> 80.58 | G85: =$B85 -> 80.58 | H85: =$B85 -> 80.58 | I85: =$B85 -> 80.58 | J85: =$B85 -> 80.58 | ... Y85: =$B85 -> 80.58
A86: - сбытовая надбавка ГП | B86: 75.85 | C86: 75.85 | D86: 75.85 | E86: 75.85 | F86: 75.85 | G86: 75.85 | H86: 75.85 | I86: 75.85 | J86: 75.85 | K86: 75.85 | L86: 75.85 | M86: 75.85 | N86: 75.85 | O86: 75.85 | P86: 75.85 | Q86: 75.85 | R86: 75.85 | S86: 75.85 | T86: 75.85 | U86: 75.85 | V86: 75.85 | W86: 75.85 | X86: 75.85 | Y86: 75.85
A87: - инфраструктурные платежи | B87: =$B$17 -> 5.35 | C87: =$B87 -> 5.35 | D87: =$B87 -> 5.35 | E87: =$B87 -> 5.35 | F87: =$B87 -> 5.35 | G87: =$B87 -> 5.35 | H87: =$B87 -> 5.35 | I87: =$B87 -> 5.35 | J87: =$B87 -> 5.35 | ... Y87: =$B87 -> 5.35
A88: 16 | B88: =B89+B90+B91+B92 -> 1618.71 | C88: =C89+C90+C91+C92 -> 1441.71 | D88: =D89+D90+D91+D92 -> 1262.75 | E88: =E89+E90+E91+E92 -> 1011.39 | F88: =F89+F90+F91+F92 -> 421.91 | G88: =G89+G90+G91+G92 -> 1205.26 | H88: =H89+H90+H91+H92 -> 1284.9 | I88: =I89+I90+I91+I92 -> 1744.35 | ... Y88: =Y89+Y90+Y91+Y92 -> 1977.79
A89: - средневзв. стоимость э/э (м) | B89: 1456.93 | C89: 1279.93 | D89: 1100.97 | E89: 849.61 | F89: 260.13 | G89: 1043.48 | H89: 1123.12 | I89: 1582.57 | J89: 2368.26 | K89: 2855.03 | L89: 2928.17 | M89: 3033.92 | N89: 3154.17 | O89: 3179.94 | P89: 3175.14 | Q89: 3092.33 | R89: 3119.37 | S89: 2923.4 | T89: 2854.64 | U89: 2738.07 | V89: 2709.8 | W89: 2690.09 | X89: 2442.61 | Y89: 1816.01
A90: - услуги по передаче | B90: =$B$15 -> 80.58 | C90: =$B90 -> 80.58 | D90: =$B90 -> 80.58 | E90: =$B90 -> 80.58 | F90: =$B90 -> 80.58 | G90: =$B90 -> 80.58 | H90: =$B90 -> 80.58 | I90: =$B90 -> 80.58 | J90: =$B90 -> 80.58 | ... Y90: =$B90 -> 80.58
A91: - сбытовая надбавка ГП | B91: 75.85 | C91: 75.85 | D91: 75.85 | E91: 75.85 | F91: 75.85 | G91: 75.85 | H91: 75.85 | I91: 75.85 | J91: 75.85 | K91: 75.85 | L91: 75.85 | M91: 75.85 | N91: 75.85 | O91: 75.85 | P91: 75.85 | Q91: 75.85 | R91: 75.85 | S91: 75.85 | T91: 75.85 | U91: 75.85 | V91: 75.85 | W91: 75.85 | X91: 75.85 | Y91: 75.85
A92: - инфраструктурные платежи | B92: =$B$17 -> 5.35 | C92: =$B92 -> 5.35 | D92: =$B92 -> 5.35 | E92: =$B92 -> 5.35 | F92: =$B92 -> 5.35 | G92: =$B92 -> 5.35 | H92: =$B92 -> 5.35 | I92: =$B92 -> 5.35 | J92: =$B92 -> 5.35 | ... Y92: =$B92 -> 5.35
A93: 17 | B93: =B94+B95+B96+B97 -> 1750.44 | C93: =C94+C95+C96+C97 -> 1478.77 | D93: =D94+D95+D96+D97 -> 1268.27 | E93: =E94+E95+E96+E97 -> 1007.04 | F93: =F94+F95+F96+F97 -> 980.61 | G93: =G94+G95+G96+G97 -> 1218.39 | H93: =H94+H95+H96+H97 -> 1479.76 | I93: =I94+I95+I96+I97 -> 2074.65 | ... Y93: =Y94+Y95+Y96+Y97 -> 2131.24
A94: - средневзв. стоимость э/э (м) | B94: 1588.66 | C94: 1316.99 | D94: 1106.49 | E94: 845.26 | F94: 818.83 | G94: 1056.61 | H94: 1317.98 | I94: 1912.87 | J94: 2629.25 | K94: 2893.84 | L94: 2895.72 | M94: 3002.23 | N94: 3003.68 | O94: 3027.52 | P94: 3026.25 | Q94: 3013.19 | R94: 3018.06 | S94: 2971.67 | T94: 2908.04 | U94: 2847.78 | V94: 2823.95 | W94: 2807.31 | X94: 2613.24 | Y94: 1969.46
A95: - услуги по передаче | B95: =$B$15 -> 80.58 | C95: =$B95 -> 80.58 | D95: =$B95 -> 80.58 | E95: =$B95 -> 80.58 | F95: =$B95 -> 80.58 | G95: =$B95 -> 80.58 | H95: =$B95 -> 80.58 | I95: =$B95 -> 80.58 | J95: =$B95 -> 80.58 | ... Y95: =$B95 -> 80.58
A96: - сбытовая надбавка ГП | B96: 75.85 | C96: 75.85 | D96: 75.85 | E96: 75.85 | F96: 75.85 | G96: 75.85 | H96: 75.85 | I96: 75.85 | J96: 75.85 | K96: 75.85 | L96: 75.85 | M96: 75.85 | N96: 75.85 | O96: 75.85 | P96: 75.85 | Q96: 75.85 | R96: 75.85 | S96: 75.85 | T96: 75.85 | U96: 75.85 | V96: 75.85 | W96: 75.85 | X96: 75.85 | Y96: 75.85
A97: - инфраструктурные платежи | B97: =$B$17 -> 5.35 | C97: =$B97 -> 5.35 | D97: =$B97 -> 5.35 | E97: =$B97 -> 5.35 | F97: =$B97 -> 5.35 | G97: =$B97 -> 5.35 | H97: =$B97 -> 5.35 | I97: =$B97 -> 5.35 | J97: =$B97 -> 5.35 | ... Y97: =$B97 -> 5.35
A98: 18 | B98: =B99+B100+B101+B102 -> 1772.75 | C98: =C99+C100+C101+C102 -> 1564.15 | D98: =D99+D100+D101+D102 -> 1366.81 | E98: =E99+E100+E101+E102 -> 1230.97 | F98: =F99+F100+F101+F102 -> 995.16 | G98: =G99+G100+G101+G102 -> 1141.76 | H98: =H99+H100+H101+H102 -> 1589.15 | I98: =I99+I100+I101+I102 -> 2075.46 | ... Y98: =Y99+Y100+Y101+Y102 -> 2410.11
A99: - средневзв. стоимость э/э (м) | B99: 1610.97 | C99: 1402.37 | D99: 1205.03 | E99: 1069.19 | F99: 833.38 | G99: 979.98 | H99: 1427.37 | I99: 1913.68 | J99: 2874.94 | K99: 3004.59 | L99: 3101.21 | M99: 3322.11 | N99: 3309.94 | O99: 3447.48 | P99: 3469.43 | Q99: 3441.94 | R99: 3275.18 | S99: 3157.78 | T99: 3096.69 | U99: 3014.76 | V99: 2925.04 | W99: 3004.37 | X99: 2715.84 | Y99: 2248.33
A100: - услуги по передаче | B100: =$B$15 -> 80.58 | C100: =$B100 -> 80.58 | D100: =$B100 -> 80.58 | E100: =$B100 -> 80.58 | F100: =$B100 -> 80.58 | G100: =$B100 -> 80.58 | H100: =$B100 -> 80.58 | I100: =$B100 -> 80.58 | J100: =$B100 -> 80.58 | ... Y100: =$B100 -> 80.58
A101: - сбытовая надбавка ГП | B101: 75.85 | C101: 75.85 | D101: 75.85 | E101: 75.85 | F101: 75.85 | G101: 75.85 | H101: 75.85 | I101: 75.85 | J101: 75.85 | K101: 75.85 | L101: 75.85 | M101: 75.85 | N101: 75.85 | O101: 75.85 | P101: 75.85 | Q101: 75.85 | R101: 75.85 | S101: 75.85 | T101: 75.85 | U101: 75.85 | V101: 75.85 | W101: 75.85 | X101: 75.85 | Y101: 75.85
A102: - инфраструктурные платежи | B102: =$B$17 -> 5.35 | C102: =$B102 -> 5.35 | D102: =$B102 -> 5.35 | E102: =$B102 -> 5.35 | F102: =$B102 -> 5.35 | G102: =$B102 -> 5.35 | H102: =$B102 -> 5.35 | I102: =$B102 -> 5.35 | J102: =$B102 -> 5.35 | ... Y102: =$B102 -> 5.35
A103: 19 | B103: =B104+B105+B106+B107 -> 1998.53 | C103: =C104+C105+C106+C107 -> 1743.09 | D103: =D104+D105+D106+D107 -> 1591.44 | E103: =E104+E105+E106+E107 -> 1383.66 | F103: =F104+F105+F106+F107 -> 1307.17 | G103: =G104+G105+G106+G107 -> 1394.14 | H103: =H104+H105+H106+H107 -> 1404.65 | I103: =I104+I105+I106+I107 -> 1636.93 | ... Y103: =Y104+Y105+Y106+Y107 -> 2343.78
A104: - средневзв. стоимость э/э (м) | B104: 1836.75 | C104: 1581.31 | D104: 1429.66 | E104: 1221.88 | F104: 1145.39 | G104: 1232.36 | H104: 1242.87 | I104: 1475.15 | J104: 2322.34 | K104: 2778.06 | L104: 2855.51 | M104: 2867.19 | N104: 2907.61 | O104: 2915.85 | P104: 2923.28 | Q104: 2914.06 | R104: 2934.88 | S104: 2901.65 | T104: 2878.85 | U104: 2849.21 | V104: 2835.47 | W104: 2815.49 | X104: 2659.81 | Y104: 2182
...

Sheet М_июль 5 цк
A2: ='М_июль 1 цк'!A2 -> Предельные уровни нерегулируемых цен на электрическую энергию (мощность), поставляемую АО "Мосэнергосбыт" потребителям
A3: ='М_июль 1 цк'!A3 -> с максимальной мощностью энергопринимающих устройств не менее 10 МВт
A4: ='М_июль 1 цк'!A4 -> г. Москва
A5: ='М_июль 1 цк'!A5 -> Июль 2025 г.
A7: V. Пятая ценовая категория для объемов покупки электрической энергии (мощности), в отношении которых за расчетный период осуществляются почасовое планирование и учет, а стоимость услуг по передаче электрической энергии определяется по тарифу на услуги по передаче электрической энергии в одноставочном выражении
A9: 1.1. Ставка за электрическую энергию предельного уровня нерегулируемых цен для абонентов группы "Иные прочие потребители", рублей/МВт∙ч без НДС
A11: Дата | B11: Ставка для фактических почасовых объемов покупки электрической энергии, отпущенных на уровне напряжения ВН
B12: 0:00-1:00 | C12: 1:00-2:00 | D12: 2:00-3:00 | E12: 3:00-4:00 | F12: 4:00-5:00 | G12: 5:00-6:00 | H12: 6:00-7:00 | I12: 7:00-8:00 | J12: 8:00-9:00 | K12: 9:00-10:00 | L12: 10:00-11:00 | M12: 11:00-12:00 | N12: 12:00-13:00 | O12: 13:00-14:00 | P12: 14:00-15:00 | Q12: 15:00-16:00 | R12: 16:00-17:00 | S12: 17:00-18:00 | T12: 18:00-19:00 | U12: 19:00-20:00 | V12: 20:00-21:00 | W12: 21:00-22:00 | X12: 22:00-23:00 | Y12: 23:00-0:00
A13: 1 | B13: =B14+B15+B16+B17 -> 2993.72 | C13: =C14+C15+C16+C17 -> 2725.18 | D13: =D14+D15+D16+D17 -> 2610.1 | E13: =E14+E15+E16+E17 -> 2509.3 | F13: =F14+F15+F16+F17 -> 2531.37 | G13: =G14+G15+G16+G17 -> 2816.66 | H13: =H14+H15+H16+H17 -> 2941.89 | I13: =I14+I15+I16+I17 -> 3393.75 | ... Y13: =Y14+Y15+Y16+Y17 -> 3415.86
A14: - средневзв. стоимость э/э (м) | B14: 1628.86 | C14: 1360.32 | D14: 1245.24 | E14: 1144.44 | F14: 1166.51 | G14: 1451.8 | H14: 1577.03 | I14: 2028.89 | J14: 2529.56 | K14: 2667.84 | L14: 2730.2 | M14: 2729.08 | N14: 2714.65 | O14: 2724.92 | P14: 2753.98 | Q14: 2768.72 | R14: 2747.79 | S14: 2753.91 | T14: 2732.01 | U14: 2682.67 | V14: 2648.86 | W14: 2621.29 | X14: 2312.02 | Y14: 2051
A15: - услуги по передаче | B15: 1283.66 | C15: =$B15 -> 1283.66 | D15: =$B15 -> 1283.66 | E15: =$B15 -> 1283.66 | F15: =$B15 -> 1283.66 | G15: =$B15 -> 1283.66 | H15: =$B15 -> 1283.66 | I15: =$B15 -> 1283.66 | J15: =$B15 -> 1283.66 | ... Y15: =$B15 -> 1283.66
A16: - сбытовая надбавка ГП | B16: 75.85 | C16: 75.85 | D16: 75.85 | E16: 75.85 | F16: 75.85 | G16: 75.85 | H16: 75.85 | I16: 75.85 | J16: 75.85 | K16: 75.85 | L16: 75.85 | M16: 75.85 | N16: 75.85 | O16: 75.85 | P16: 75.85 | Q16: 75.85 | R16: 75.85 | S16: 75.85 | T16: 75.85 | U16: 75.85 | V16: 75.85 | W16: 75.85 | X16: 75.85 | Y16: 75.85
A17: - инфраструктурные платежи | B17: 5.35 | C17: =$B17 -> 5.35 | D17: =$B17 -> 5.35 | E17: =$B17 -> 5.35 | F17: =$B17 -> 5.35 | G17: =$B17 -> 5.35 | H17: =$B17 -> 5.35 | I17: =$B17 -> 5.35 | J17: =$B17 -> 5.35 | ... Y17: =$B17 -> 5.35
A18: 2 | B18: =B19+B20+B21+B22 -> 3039.07 | C18: =C19+C20+C21+C22 -> 2879.09 | D18: =D19+D20+D21+D22 -> 2795.44 | E18: =E19+E20+E21+E22 -> 2579.94 | F18: =F19+F20+F21+F22 -> 2674.25 | G18: =G19+G20+G21+G22 -> 2875.3 | H18: =H19+H20+H21+H22 -> 2957.4 | I18: =I19+I20+I21+I22 -> 3444.43 | ... Y18: =Y19+Y20+Y21+Y22 -> 3350.47
A19: - средневзв. стоимость э/э (м) | B19: 1674.21 | C19: 1514.23 | D19: 1430.58 | E19: 1215.08 | F19: 1309.39 | G19: 1510.44 | H19: 1592.54 | I19: 2079.57 | J19: 2692.19 | K19: 2789.44 | L19: 2822.69 | M19: 2813.51 | N19: 2828.33 | O19: 2858.33 | P19: 2859.57 | Q19: 2849.01 | R19: 2822.57 | S19: 2803.02 | T19: 2792.13 | U19: 2764.19 | V19: 2733.69 | W19: 2712.26 | X19: 2430.41 | Y19: 1985.61
A20: - услуги по передаче | B20: =$B$15 -> 1283.66 | C20: =$B20 -> 1283.66 | D20: =$B20 -> 1283.66 | E20: =$B20 -> 1283.66 | F20: =$B20 -> 1283.66 | G20: =$B20 -> 1283.66 | H20: =$B20 -> 1283.66 | I20: =$B20 -> 1283.66 | J20: =$B20 -> 1283.66 | ... Y20: =$B20 -> 1283.66
A21: - сбытовая надбавка ГП | B21: 75.85 | C21: 75.85 | D21: 75.85 | E21: 75.85 | F21: 75.85 | G21: 75.85 | H21: 75.85 | I21: 75.85 | J21: 75.85 | K21: 75.85 | L21: 75.85 | M21: 75.85 | N21: 75.85 | O21: 75.85 | P21: 75.85 | Q21: 75.85 | R21: 75.85 | S21: 75.85 | T21: 75.85 | U21: 75.85 | V21: 75.85 | W21: 75.85 | X21: 75.85 | Y21: 75.85
A22: - инфраструктурные платежи | B22: =$B$17 -> 5.35 | C22: =$B22 -> 5.35 | D22: =$B22 -> 5.35 | E22: =$B22 -> 5.35 | F22: =$B22 -> 5.35 | G22: =$B22 -> 5.35 | H22: =$B22 -> 5.35 | I22: =$B22 -> 5.35 | J22: =$B22 -> 5.35 | ... Y22: =$B22 -> 5.35
A23: 3 | B23: =B24+B25+B26+B27 -> 2920.99 | C23: =C24+C25+C26+C27 -> 2762.8 | D23: =D24+D25+D26+D27 -> 2639.61 | E23: =E24+E25+E26+E27 -> 2523.91 | F23: =F24+F25+F26+F27 -> 2535.52 | G23: =G24+G25+G26+G27 -> 2760.98 | H23: =H24+H25+H26+H27 -> 2904.94 | I23: =I24+I25+I26+I27 -> 3359.13 | ... Y23: =Y24+Y25+Y26+Y27 -> 3338.75
A24: - средневзв. стоимость э/э (м) | B24: 1556.13 | C24: 1397.94 | D24: 1274.75 | E24: 1159.05 | F24: 1170.66 | G24: 1396.12 | H24: 1540.08 | I24: 1994.27 | J24: 2544.78 | K24: 2584.11 | L24: 2626.41 | M24: 2659.13 | N24: 2652.3 | O24: 2636.86 | P24: 2858.16 | Q24: 2926.75 | R24: 2869.94 | S24: 2673.56 | T24: 2743.09 | U24: 2636.57 | V24: 2682.12 | W24: 2663.22 | X24: 2402.89 | Y24: 1973.89
A25: - услуги по передаче | B25: =$B$15 -> 1283.66 | C25: =$B25 -> 1283.66 | D25: =$B25 -> 1283.66 | E25: =$B25 -> 1283.66 | F25: =$B25 -> 1283.66 | G25: =$B25 -> 1283.66 | H25: =$B25 -> 1283.66 | I25: =$B25 -> 1283.66 | J25: =$B25 -> 1283.66 | ... Y25: =$B25 -> 1283.66
A26: - сбытовая надбавка ГП | B26: 75.85 | C26: 75.85 | D26: 75.85 | E26: 75.85 | F26: 75.85 | G26: 75.85 | H26: 75.85 | I26: 75.85 | J26: 75.85 | K26: 75.85 | L26: 75.85 | M26: 75.85 | N26: 75.85 | O26: 75.85 | P26: 75.85 | Q26: 75.85 | R26: 75.85 | S26: 75.85 | T26: 75.85 | U26: 75.85 | V26: 75.85 | W26: 75.85 | X26: 75.85 | Y26: 75.85
A27: - инфраструктурные платежи | B27: =$B$17 -> 5.35 | C27: =$B27 -> 5.35 | D27: =$B27 -> 5.35 | E27: =$B27 -> 5.35 | F27: =$B27 -> 5.35 | G27: =$B27 -> 5.35 | H27: =$B27 -> 5.35 | I27: =$B27 -> 5.35 | J27: =$B27 -> 5.35 | ... Y27: =$B27 -> 5.35
A28: 4 | B28: =B29+B30+B31+B32 -> 3011.61 | C28: =C29+C30+C31+C32 -> 2791.58 | D28: =D29+D30+D31+D32 -> 2646.13 | E28: =E29+E30+E31+E32 -> 2516.85 | F28: =F29+F30+F31+F32 -> 2533.34 | G28: =G29+G30+G31+G32 -> 2765.89 | H28: =H29+H30+H31+H32 -> 2917.97 | I28: =I29+I30+I31+I32 -> 3380.59 | ... Y28: =Y29+Y30+Y31+Y32 -> 3395.59
A29: - средневзв. стоимость э/э (м) | B29: 1646.75 | C29: 1426.72 | D29: 1281.27 | E29: 1151.99 | F29: 1168.48 | G29: 1401.03 | H29: 1553.11 | I29: 2015.73 | J29: 2553.88 | K29: 2673.17 | L29: 2626.61 | M29: 2625.16 | N29: 2692.98 | O29: 2624.48 | P29: 2769.95 | Q29: 2822.13 | R29: 2803.3 | S29: 2780.13 | T29: 2766.9 | U29: 2634.11 | V29: 2616.68 | W29: 2693.6 | X29: 2496.58 | Y29: 2030.73
A30: - услуги по передаче | B30: =$B$15 -> 1283.66 | C30: =$B30 -> 1283.66 | D30: =$B30 -> 1283.66 | E30: =$B30 -> 1283.66 | F30: =$B30 -> 1283.66 | G30: =$B30 -> 1283.66 | H30: =$B30 -> 1283.66 | I30: =$B30 -> 1283.66 | J30: =$B30 -> 1283.66 | ... Y30: =$B30 -> 1283.66
A31: - сбытовая надбавка ГП | B31: 75.85 | C31: 75.85 | D31: 75.85 | E31: 75.85 | F31: 75.85 | G31: 75.85 | H31: 75.85 | I31: 75.85 | J31: 75.85 | K31: 75.85 | L31: 75.85 | M31: 75.85 | N31: 75.85 | O31: 75.85 | P31: 75.85 | Q31: 75.85 | R31: 75.85 | S31: 75.85 | T31: 75.85 | U31: 75.85 | V31: 75.85 | W31: 75.85 | X31: 75.85 | Y31: 75.85
A32: - инфраструктурные платежи | B32: =$B$17 -> 5.35 | C32: =$B32 -> 5.35 | D32: =$B32 -> 5.35 | E32: =$B32 -> 5.35 | F32: =$B32 -> 5.35 | G32: =$B32 -> 5.35 | H32: =$B32 -> 5.35 | I32: =$B32 -> 5.35 | J32: =$B32 -> 5.35 | ... Y32: =$B32 -> 5.35
A33: 5 | B33: =B34+B35+B36+B37 -> 3103.45 | C33: =C34+C35+C36+C37 -> 2869.22 | D33: =D34+D35+D36+D37 -> 2762.17 | E33: =E34+E35+E36+E37 -> 2619.03 | F33: =F34+F35+F36+F37 -> 2560.74 | G33: =G34+G35+G36+G37 -> 2551.79 | H33: =H34+H35+H36+H37 -> 2654.95 | I33: =I34+I35+I36+I37 -> 3019.11 | ... Y33: =Y34+Y35+Y36+Y37 -> 3331.25
A34: - средневзв. стоимость э/э (м) | B34: 1738.59 | C34: 1504.36 | D34: 1397.31 | E34: 1254.17 | F34: 1195.88 | G34: 1186.93 | H34: 1290.09 | I34: 1654.25 | J34: 2120.14 | K34: 2356.02 | L34: 2424.84 | M34: 2454.2 | N34: 2449.57 | O34: 2453.65 | P34: 2450.03 | Q34: 2512.33 | R34: 2520.61 | S34: 2485.92 | T34: 2465.87 | U34: 2437.81 | V34: 2435.72 | W34: 2452.81 | X34: 2154.71 | Y34: 1966.39
A35: - услуги по передаче | B35: =$B$15 -> 1283.66 | C35: =$B35 -> 1283.66 | D35: =$B35 -> 1283.66 | E35: =$B35 -> 1283.66 | F35: =$B35 -> 1283.66 | G35: =$B35 -> 1283.66 | H35: =$B35 -> 1283.66 | I35: =$B35 -> 1283.66 | J35: =$B35 -> 1283.66 | ... Y35: =$B35 -> 1283.66
A36: - сбытовая надбавка ГП | B36: 75.85 | C36: 75.85 | D36: 75.85 | E36: 75.85 | F36: 75.85 | G36: 75.85 | H36: 75.85 | I36: 75.85 | J36: 75.85 | K36: 75.85 | L36: 75.85 | M36: 75.85 | N36: 75.85 | O36: 75.85 | P36: 75.85 | Q36: 75.85 | R36: 75.85 | S36: 75.85 | T36: 75.85 | U36: 75.85 | V36: 75.85 | W36: 75.85 | X36: 75.85 | Y36: 75.85
A37: - инфраструктурные платежи | B37: =$B$17 -> 5.35 | C37: =$B37 -> 5.35 | D37: =$B37 -> 5.35 | E37: =$B37 -> 5.35 | F37: =$B37 -> 5.35 | G37: =$B37 -> 5.35 | H37: =$B37 -> 5.35 | I37: =$B37 -> 5.35 | J37: =$B37 -> 5.35 | ... Y37: =$B37 -> 5.35
A38: 6 | B38: =B39+B40+B41+B42 -> 3111.74 | C38: =C39+C40+C41+C42 -> 2857.67 | D38: =D39+D40+D41+D42 -> 2736.69 | E38: =E39+E40+E41+E42 -> 2551.06 | F38: =F39+F40+F41+F42 -> 2493.57 | G38: =G39+G40+G41+G42 -> 2492.5 | H38: =H39+H40+H41+H42 -> 2437.25 | I38: =I39+I40+I41+I42 -> 2866.1 | ... Y38: =Y39+Y40+Y41+Y42 -> 3192.63
A39: - средневзв. стоимость э/э (м) | B39: 1746.88 | C39: 1492.81 | D39: 1371.83 | E39: 1186.2 | F39: 1128.71 | G39: 1127.64 | H39: 1072.39 | I39: 1501.24 | J39: 1906.15 | K39: 2244.04 | L39: 2381.13 | M39: 2381.09 | N39: 2383.85 | O39: 2390.93 | P39: 2395.78 | Q39: 2397.59 | R39: 2450.8 | S39: 2436.66 | T39: 2434.99 | U39: 2418.9 | V39: 2418.43 | W39: 2414.63 | X39: 2170.25 | Y39: 1827.77
A40: - услуги по передаче | B40: =$B$15 -> 1283.66 | C40: =$B40 -> 1283.66 | D40: =$B40 -> 1283.66 | E40: =$B40 -> 1283.66 | F40: =$B40 -> 1283.66 | G40: =$B40 -> 1283.66 | H40: =$B40 -> 1283.66 | I40: =$B40 -> 1283.66 | J40: =$B40 -> 1283.66 | ... Y40: =$B40 -> 1283.66
A41: - сбытовая надбавка ГП | B41: 75.85 | C41: 75.85 | D41: 75.85 | E41: 75.85 | F41: 75.85 | G41: 75.85 | H41: 75.85 | I41: 75.85 | J41: 75.85 | K41: 75.85 | L41: 75.85 | M41: 75.85 | N41: 75.85 | O41: 75.85 | P41: 75.85 | Q41: 75.85 | R41: 75.85 | S41: 75.85 | T41: 75.85 | U41: 75.85 | V41: 75.85 | W41: 75.85 | X41: 75.85 | Y41: 75.85
A42: - инфраструктурные платежи | B42: =$B$17 -> 5.35 | C42: =$B42 -> 5.35 | D42: =$B42 -> 5.35 | E42: =$B42 -> 5.35 | F42: =$B42 -> 5.35 | G42: =$B42 -> 5.35 | H42: =$B42 -> 5.35 | I42: =$B42 -> 5.35 | J42: =$B42 -> 5.35 | ... Y42: =$B42 -> 5.35
A43: 7 | B43: =B44+B45+B46+B47 -> 3036 | C43: =C44+C45+C46+C47 -> 2867.47 | D43: =D44+D45+D46+D47 -> 2666.84 | E43: =E44+E45+E46+E47 -> 2522.11 | F43: =F44+F45+F46+F47 -> 2490.91 | G43: =G44+G45+G46+G47 -> 2580.49 | H43: =H44+H45+H46+H47 -> 2886.63 | I43: =I44+I45+I46+I47 -> 3327.86 | ... Y43: =Y44+Y45+Y46+Y47 -> 3220.17
A44: - средневзв. стоимость э/э (м) | B44: 1671.14 | C44: 1502.61 | D44: 1301.98 | E44: 1157.25 | F44: 1126.05 | G44: 1215.63 | H44: 1521.77 | I44: 1963 | J44: 2501.65 | K44: 2628.05 | L44: 2688.27 | M44: 2729.07 | N44: 2713.73 | O44: 2738.01 | P44: 2723.11 | Q44: 2756.44 | R44: 2704.53 | S44: 2819.29 | T44: 2719.06 | U44: 2682.93 | V44: 2628.49 | W44: 2645.08 | X44: 2204.5 | Y44: 1855.31
A45: - услуги по передаче | B45: =$B$15 -> 1283.66 | C45: =$B45 -> 1283.66 | D45: =$B45 -> 1283.66 | E45: =$B45 -> 1283.66 | F45: =$B45 -> 1283.66 | G45: =$B45 -> 1283.66 | H45: =$B45 -> 1283.66 | I45: =$B45 -> 1283.66 | J45: =$B45 -> 1283.66 | ... Y45: =$B45 -> 1283.66
A46: - сбытовая надбавка ГП | B46: 75.85 | C46: 75.85 | D46: 75.85 | E46: 75.85 | F46: 75.85 | G46: 75.85 | H46: 75.85 | I46: 75.85 | J46: 75.85 | K46: 75.85 | L46: 75.85 | M46: 75.85 | N46: 75.85 | O46: 75.85 | P46: 75.85 | Q46: 75.85 | R46: 75.85 | S46: 75.85 | T46: 75.85 | U46: 75.85 | V46: 75.85 | W46: 75.85 | X46: 75.85 | Y46: 75.85
A47: - инфраструктурные платежи | B47: =$B$17 -> 5.35 | C47: =$B47 -> 5.35 | D47: =$B47 -> 5.35 | E47: =$B47 -> 5.35 | F47: =$B47 -> 5.35 | G47: =$B47 -> 5.35 | H47: =$B47 -> 5.35 | I47: =$B47 -> 5.35 | J47: =$B47 -> 5.35 | ... Y47: =$B47 -> 5.35
A48: 8 | B48: =B49+B50+B51+B52 -> 2869.22 | C48: =C49+C50+C51+C52 -> 2595.11 | D48: =D49+D50+D51+D52 -> 2432.11 | E48: =E49+E50+E51+E52 -> 1540.24 | F48: =F49+F50+F51+F52 -> 1498.67 | G48: =G49+G50+G51+G52 -> 1513.88 | H48: =H49+H50+H51+H52 -> 2572.09 | I48: =I49+I50+I51+I52 -> 3167.66 | ... Y48: =Y49+Y50+Y51+Y52 -> 3205.63
A49: - средневзв. стоимость э/э (м) | B49: 1504.36 | C49: 1230.25 | D49: 1067.25 | E49: 175.38 | F49: 133.81 | G49: 149.02 | H49: 1207.23 | I49: 1802.8 | J49: 2372.03 | K49: 2606.12 | L49: 2739.12 | M49: 2751.76 | N49: 2735.29 | O49: 2737.68 | P49: 3066.38 | Q49: 2814.6 | R49: 2837.85 | S49: 2812.02 | T49: 2716.78 | U49: 2610 | V49: 2589.9 | W49: 2530.13 | X49: 2135.76 | Y49: 1840.77
A50: - услуги по передаче | B50: =$B$15 -> 1283.66 | C50: =$B50 -> 1283.66 | D50: =$B50 -> 1283.66 | E50: =$B50 -> 1283.66 | F50: =$B50 -> 1283.66 | G50: =$B50 -> 1283.66 | H50: =$B50 -> 1283.66 | I50: =$B50 -> 1283.66 | J50: =$B50 -> 1283.66 | ... Y50: =$B50 -> 1283.66
A51: - сбытовая надбавка ГП | B51: 75.85 | C51: 75.85 | D51: 75.85 | E51: 75.85 | F51: 75.85 | G51: 75.85 | H51: 75.85 | I51: 75.85 | J51: 75.85 | K51: 75.85 | L51: 75.85 | M51: 75.85 | N51: 75.85 | O51: 75.85 | P51: 75.85 | Q51: 75.85 | R51: 75.85 | S51: 75.85 | T51: 75.85 | U51: 75.85 | V51: 75.85 | W51: 75.85 | X51: 75.85 | Y51: 75.85
A52: - инфраструктурные платежи | B52: =$B$17 -> 5.35 | C52: =$B52 -> 5.35 | D52: =$B52 -> 5.35 | E52: =$B52 -> 5.35 | F52: =$B52 -> 5.35 | G52: =$B52 -> 5.35 | H52: =$B52 -> 5.35 | I52: =$B52 -> 5.35 | J52: =$B52 -> 5.35 | ... Y52: =$B52 -> 5.35
A53: 9 | B53: =B54+B55+B56+B57 -> 3042.72 | C53: =C54+C55+C56+C57 -> 2476.25 | D53: =D54+D55+D56+D57 -> 1507.15 | E53: =E54+E55+E56+E57 -> 1502.93 | F53: =F54+F55+F56+F57 -> 1500.46 | G53: =G54+G55+G56+G57 -> 1513.75 | H53: =H54+H55+H56+H57 -> 2479.66 | I53: =I54+I55+I56+I57 -> 3182.16 | ... Y53: =Y54+Y55+Y56+Y57 -> 2940.24
A54: - средневзв. стоимость э/э (м) | B54: 1677.86 | C54: 1111.39 | D54: 142.29 | E54: 138.07 | F54: 135.6 | G54: 148.89 | H54: 1114.8 | I54: 1817.3 | J54: 2119.11 | K54: 2482.57 | L54: 2678.73 | M54: 2743.21 | N54: 2741.25 | O54: 3037.78 | P54: 3195.02 | Q54: 3208.54 | R54: 3153.2 | S54: 3125.45 | T54: 2772.03 | U54: 2555.49 | V54: 2500.3 | W54: 2482.62 | X54: 2041.44 | Y54: 1575.38
A55: - услуги по передаче | B55: =$B$15 -> 1283.66 | C55: =$B55 -> 1283.66 | D55: =$B55 -> 1283.66 | E55: =$B55 -> 1283.66 | F55: =$B55 -> 1283.66 | G55: =$B55 -> 1283.66 | H55: =$B55 -> 1283.66 | I55: =$B55 -> 1283.66 | J55: =$B55 -> 1283.66 | ... Y55: =$B55 -> 1283.66
A56: - сбытовая надбавка ГП | B56: 75.85 | C56: 75.85 | D56: 75.85 | E56: 75.85 | F56: 75.85 | G56: 75.85 | H56: 75.85 | I56: 75.85 | J56: 75.85 | K56: 75.85 | L56: 75.85 | M56: 75.85 | N56: 75.85 | O56: 75.85 | P56: 75.85 | Q56: 75.85 | R56: 75.85 | S56: 75.85 | T56: 75.85 | U56: 75.85 | V56: 75.85 | W56: 75.85 | X56: 75.85 | Y56: 75.85
A57: - инфраструктурные платежи | B57: =$B$17 -> 5.35 | C57: =$B57 -> 5.35 | D57: =$B57 -> 5.35 | E57: =$B57 -> 5.35 | F57: =$B57 -> 5.35 | G57: =$B57 -> 5.35 | H57: =$B57 -> 5.35 | I57: =$B57 -> 5.35 | J57: =$B57 -> 5.35 | ... Y57: =$B57 -> 5.35
A58: 10 | B58: =B59+B60+B61+B62 -> 2694.85 | C58: =C59+C60+C61+C62 -> 2425.98 | D58: =D59+D60+D61+D62 -> 1492.99 | E58: =E59+E60+E61+E62 -> 1470.16 | F58: =F59+F60+F61+F62 -> 1477.24 | G58: =G59+G60+G61+G62 -> 1497.34 | H58: =H59+H60+H61+H62 -> 2058.9 | I58: =I59+I60+I61+I62 -> 2970.59 | ... Y58: =Y59+Y60+Y61+Y62 -> 3159.84
A59: - средневзв. стоимость э/э (м) | B59: 1329.99 | C59: 1061.12 | D59: 128.13 | E59: 105.3 | F59: 112.38 | G59: 132.48 | H59: 694.04 | I59: 1605.73 | J59: 2205.54 | K59: 2716.25 | L59: 3022.68 | M59: 3163.37 | N59: 2642.32 | O59: 3014.75 | P59: 3222.34 | Q59: 3067.67 | R59: 3069.28 | S59: 2992.76 | T59: 2848.18 | U59: 2825.87 | V59: 2714.83 | W59: 2657.1 | X59: 2170.51 | Y59: 1794.98
A60: - услуги по передаче | B60: =$B$15 -> 1283.66 | C60: =$B60 -> 1283.66 | D60: =$B60 -> 1283.66 | E60: =$B60 -> 1283.66 | F60: =$B60 -> 1283.66 | G60: =$B60 -> 1283.66 | H60: =$B60 -> 1283.66 | I60: =$B60 -> 1283.66 | J60: =$B60 -> 1283.66 | ... Y60: =$B60 -> 1283.66
A61: - сбытовая надбавка ГП | B61: 75.85 | C61: 75.85 | D61: 75.85 | E61: 75.85 | F61: 75.85 | G61: 75.85 | H61: 75.85 | I61: 75.85 | J61: 75.85 | K61: 75.85 | L61: 75.85 | M61: 75.85 | N61: 75.85 | O61: 75.85 | P61: 75.85 | Q61: 75.85 | R61: 75.85 | S61: 75.85 | T61: 75.85 | U61: 75.85 | V61: 75.85 | W61: 75.85 | X61: 75.85 | Y61: 75.85
A62: - инфраструктурные платежи | B62: =$B$17 -> 5.35 | C62: =$B62 -> 5.35 | D62: =$B62 -> 5.35 | E62: =$B62 -> 5.35 | F62: =$B62 -> 5.35 | G62: =$B62 -> 5.35 | H62: =$B62 -> 5.35 | I62: =$B62 -> 5.35 | J62: =$B62 -> 5.35 | ... Y62: =$B62 -> 5.35
A63: 11 | B63: =B64+B65+B66+B67 -> 2813.61 | C63: =C64+C65+C66+C67 -> 2589.29 | D63: =D64+D65+D66+D67 -> 1507.67 | E63: =E64+E65+E66+E67 -> 1501.7 | F63: =F64+F65+F66+F67 -> 1502.29 | G63: =G64+G65+G66+G67 -> 1504.96 | H63: =H64+H65+H66+H67 -> 2695.91 | I63: =I64+I65+I66+I67 -> 3128.42 | ... Y63: =Y64+Y65+Y66+Y67 -> 3410.05
A64: - средневзв. стоимость э/э (м) | B64: 1448.75 | C64: 1224.43 | D64: 142.81 | E64: 136.84 | F64: 137.43 | G64: 140.1 | H64: 1331.05 | I64: 1763.56 | J64: 2502.42 | K64: 2764.81 | L64: 2784.94 | M64: 2887.65 | N64: 2900.09 | O64: 2967.59 | P64: 2739.34 | Q64: 3046.6 | R64: 3047.07 | S64: 3334.07 | T64: 2910.2 | U64: 2822.33 | V64: 2944.81 | W64: 2817.67 | X64: 2352.27 | Y64: 2045.19
A65: - услуги по передаче | B65: =$B$15 -> 1283.66 | C65: =$B65 -> 1283.66 | D65: =$B65 -> 1283.66 | E65: =$B65 -> 1283.66 | F65: =$B65 -> 1283.66 | G65: =$B65 -> 1283.66 | H65: =$B65 -> 1283.66 | I65: =$B65 -> 1283.66 | J65: =$B65 -> 1283.66 | ... Y65: =$B65 -> 1283.66
A66: - сбытовая надбавка ГП | B66: 75.85 | C66: 75.85 | D66: 75.85 | E66: 75.85 | F66: 75.85 | G66: 75.85 | H66: 75.85 | I66: 75.85 | J66: 75.85 | K66: 75.85 | L66: 75.85 | M66: 75.85 | N66: 75.85 | O66: 75.85 | P66: 75.85 | Q66: 75.85 | R66: 75.85 | S66: 75.85 | T66: 75.85 | U66: 75.85 | V66: 75.85 | W66: 75.85 | X66: 75.85 | Y66: 75.85
A67: - инфраструктурные платежи | B67: =$B$17 -> 5.35 | C67: =$B67 -> 5.35 | D67: =$B67 -> 5.35 | E67: =$B67 -> 5.35 | F67: =$B67 -> 5.35 | G67: =$B67 -> 5.35 | H67: =$B67 -> 5.35 | I67: =$B67 -> 5.35 | J67: =$B67 -> 5.35 | ... Y67: =$B67 -> 5.35
A68: 12 | B68: =B69+B70+B71+B72 -> 3124.75 | C68: =C69+C70+C71+C72 -> 2798.33 | D68: =D69+D70+D71+D72 -> 2632.96 | E68: =E69+E70+E71+E72 -> 1712.08 | F68: =F69+F70+F71+F72 -> 1527.84 | G68: =G69+G70+G71+G72 -> 1524.97 | H68: =H69+H70+H71+H72 -> 2465.17 | I68: =I69+I70+I71+I72 -> 2980.6 | ... Y68: =Y69+Y70+Y71+Y72 -> 3501.15
A69: - средневзв. стоимость э/э (м) | B69: 1759.89 | C69: 1433.47 | D69: 1268.1 | E69: 347.22 | F69: 162.98 | G69: 160.11 | H69: 1100.31 | I69: 1615.74 | J69: 2200.28 | K69: 2549.89 | L69: 2728.84 | M69: 2742.61 | N69: 2736.31 | O69: 2831.32 | P69: 2846 | Q69: 2785 | R69: 3199.31 | S69: 3149.47 | T69: 2764.72 | U69: 2664.69 | V69: 2764.76 | W69: 2831.94 | X69: 2541.31 | Y69: 2136.29
A70: - услуги по передаче | B70: =$B$15 -> 1283.66 | C70: =$B70 -> 1283.66 | D70: =$B70 -> 1283.66 | E70: =$B70 -> 1283.66 | F70: =$B70 -> 1283.66 | G70: =$B70 -> 1283.66 | H70: =$B70 -> 1283.66 | I70: =$B70 -> 1283.66 | J70: =$B70 -> 1283.66 | ... Y70: =$B70 -> 1283.66
A71: - сбытовая надбавка ГП | B71: 75.85 | C71: 75.85 | D71: 75.85 | E71: 75.85 | F71: 75.85 | G71: 75.85 | H71: 75.85 | I71: 75.85 | J71: 75.85 | K71: 75.85 | L71: 75.85 | M71: 75.85 | N71: 75.85 | O71: 75.85 | P71: 75.85 | Q71: 75.85 | R71: 75.85 | S71: 75.85 | T71: 75.85 | U71: 75.85 | V71: 75.85 | W71: 75.85 | X71: 75.85 | Y71: 75.85
A72: - инфраструктурные платежи | B72: =$B$17 -> 5.35 | C72: =$B72 -> 5.35 | D72: =$B72 -> 5.35 | E72: =$B72 -> 5.35 | F72: =$B72 -> 5.35 | G72: =$B72 -> 5.35 | H72: =$B72 -> 5.35 | I72: =$B72 -> 5.35 | J72: =$B72 -> 5.35 | ... Y72: =$B72 -> 5.35
A73: 13 | B73: =B74+B75+B76+B77 -> 3048.47 | C73: =C74+C75+C76+C77 -> 2835.75 | D73: =D74+D75+D76+D77 -> 2667.09 | E73: =E74+E75+E76+E77 -> 1552.72 | F73: =F74+F75+F76+F77 -> 1517.53 | G73: =G74+G75+G76+G77 -> 1514.26 | H73: =H74+H75+H76+H77 -> 2321.84 | I73: =I74+I75+I76+I77 -> 2784.68 | ... Y73: =Y74+Y75+Y76+Y77 -> 3360.5
A74: - средневзв. стоимость э/э (м) | B74: 1683.61 | C74: 1470.89 | D74: 1302.23 | E74: 187.86 | F74: 152.67 | G74: 149.4 | H74: 956.98 | I74: 1419.82 | J74: 1963.48 | K74: 2454.62 | L74: 2576.53 | M74: 2570.51 | N74: 2755.8 | O74: 2713.91 | P74: 2777.03 | Q74: 2793.84 | R74: 2770.44 | S74: 2896.82 | T74: 2816.88 | U74: 2738.11 | V74: 2717.75 | W74: 2712.31 | X74: 2446.01 | Y74: 1995.64
A75: - услуги по передаче | B75: =$B$15 -> 1283.66 | C75: =$B75 -> 1283.66 | D75: =$B75 -> 1283.66 | E75: =$B75 -> 1283.66 | F75: =$B75 -> 1283.66 | G75: =$B75 -> 1283.66 | H75: =$B75 -> 1283.66 | I75: =$B75 -> 1283.66 | J75: =$B75 -> 1283.66 | ... Y75: =$B75 -> 1283.66
A76: - сбытовая надбавка ГП | B76: 75.85 | C76: 75.85 | D76: 75.85 | E76: 75.85 | F76: 75.85 | G76: 75.85 | H76: 75.85 | I76: 75.85 | J76: 75.85 | K76: 75.85 | L76: 75.85 | M76: 75.85 | N76: 75.85 | O76: 75.85 | P76: 75.85 | Q76: 75.85 | R76: 75.85 | S76: 75.85 | T76: 75.85 | U76: 75.85 | V76: 75.85 | W76: 75.85 | X76: 75.85 | Y76: 75.85
A77: - инфраструктурные платежи | B77: =$B$17 -> 5.35 | C77: =$B77 -> 5.35 | D77: =$B77 -> 5.35 | E77: =$B77 -> 5.35 | F77: =$B77 -> 5.35 | G77: =$B77 -> 5.35 | H77: =$B77 -> 5.35 | I77: =$B77 -> 5.35 | J77: =$B77 -> 5.35 | ... Y77: =$B77 -> 5.35
A78: 14 | B78: =B79+B80+B81+B82 -> 2921.25 | C78: =C79+C80+C81+C82 -> 2724.62 | D78: =D79+D80+D81+D82 -> 1619.81 | E78: =E79+E80+E81+E82 -> 1527.12 | F78: =F79+F80+F81+F82 -> 1522.84 | G78: =G79+G80+G81+G82 -> 1527.14 | H78: =H79+H80+H81+H82 -> 2541.31 | I78: =I79+I80+I81+I82 -> 3195.27 | ... Y78: =Y79+Y80+Y81+Y82 -> 3166.87
A79: - средневзв. стоимость э/э (м) | B79: 1556.39 | C79: 1359.76 | D79: 254.95 | E79: 162.26 | F79: 157.98 | G79: 162.28 | H79: 1176.45 | I79: 1830.41 | J79: 2604.41 | K79: 2856.75 | L79: 2881.07 | M79: 2888.06 | N79: 2879.85 | O79: 2885.64 | P79: 2879.73 | Q79: 2945.29 | R79: 2924.98 | S79: 2912.14 | T79: 2862.41 | U79: 2782.39 | V79: 2770.5 | W79: 2737.42 | X79: 2214.19 | Y79: 1802.01
A80: - услуги по передаче | B80: =$B$15 -> 1283.66 | C80: =$B80 -> 1283.66 | D80: =$B80 -> 1283.66 | E80: =$B80 -> 1283.66 | F80: =$B80 -> 1283.66 | G80: =$B80 -> 1283.66 | H80: =$B80 -> 1283.66 | I80: =$B80 -> 1283.66 | J80: =$B80 -> 1283.66 | ... Y80: =$B80 -> 1283.66
A81: - сбытовая надбавка ГП | B81: 75.85 | C81: 75.85 | D81: 75.85 | E81: 75.85 | F81: 75.85 | G81: 75.85 | H81: 75.85 | I81: 75.85 | J81: 75.85 | K81: 75.85 | L81: 75.85 | M81: 75.85 | N81: 75.85 | O81: 75.85 | P81: 75.85 | Q81: 75.85 | R81: 75.85 | S81: 75.85 | T81: 75.85 | U81: 75.85 | V81: 75.85 | W81: 75.85 | X81: 75.85 | Y81: 75.85
A82: - инфраструктурные платежи | B82: =$B$17 -> 5.35 | C82: =$B82 -> 5.35 | D82: =$B82 -> 5.35 | E82: =$B82 -> 5.35 | F82: =$B82 -> 5.35 | G82: =$B82 -> 5.35 | H82: =$B82 -> 5.35 | I82: =$B82 -> 5.35 | J82: =$B82 -> 5.35 | ... Y82: =$B82 -> 5.35
A83: 15 | B83: =B84+B85+B86+B87 -> 2767.43 | C83: =C84+C85+C86+C87 -> 2577.9 | D83: =D84+D85+D86+D87 -> 2418.3 | E83: =E84+E85+E86+E87 -> 1459.21 | F83: =F84+F85+F86+F87 -> 1381.66 | G83: =G84+G85+G86+G87 -> 1457.83 | H83: =H84+H85+H86+H87 -> 2373.58 | I83: =I84+I85+I86+I87 -> 3195.53 | ... Y83: =Y84+Y85+Y86+Y87 -> 3271.09
A84: - средневзв. стоимость э/э (м) | B84: 1402.57 | C84: 1213.04 | D84: 1053.44 | E84: 94.35 | F84: 16.8 | G84: 92.97 | H84: 1008.72 | I84: 1830.67 | J84: 2418.63 | K84: 2877.6 | L84: 2864.82 | M84: 2934.01 | N84: 2935.35 | O84: 2954.38 | P84: 2941.52 | Q84: 2963.32 | R84: 2998.29 | S84: 3034.97 | T84: 2947.25 | U84: 2831.49 | V84: 2731.14 | W84: 2727.39 | X84: 2181.36 | Y84: 1906.23
A85: - услуги по передаче | B85: =$B$15 -> 1283.66 | C85: =$B85 -> 1283.66 | D85: =$B85 -> 1283.66 | E85: =$B85 -> 1283.66 | F85: =$B85 -> 1283.66 | G85: =$B85 -> 1283.66 | H85: =$B85 -> 1283.66 | I85: =$B85 -> 1283.66 | J85: =$B85 -> 1283.66 | ... Y85: =$B85 -> 1283.66
A86: - сбытовая надбавка ГП | B86: 75.85 | C86: 75.85 | D86: 75.85 | E86: 75.85 | F86: 75.85 | G86: 75.85 | H86: 75.85 | I86: 75.85 | J86: 75.85 | K86: 75.85 | L86: 75.85 | M86: 75.85 | N86: 75.85 | O86: 75.85 | P86: 75.85 | Q86: 75.85 | R86: 75.85 | S86: 75.85 | T86: 75.85 | U86: 75.85 | V86: 75.85 | W86: 75.85 | X86: 75.85 | Y86: 75.85
A87: - инфраструктурные платежи | B87: =$B$17 -> 5.35 | C87: =$B87 -> 5.35 | D87: =$B87 -> 5.35 | E87: =$B87 -> 5.35 | F87: =$B87 -> 5.35 | G87: =$B87 -> 5.35 | H87: =$B87 -> 5.35 | I87: =$B87 -> 5.35 | J87: =$B87 -> 5.35 | ... Y87: =$B87 -> 5.35
A88: 16 | B88: =B89+B90+B91+B92 -> 2807.02 | C88: =C89+C90+C91+C92 -> 2630.02 | D88: =D89+D90+D91+D92 -> 2451.06 | E88: =E89+E90+E91+E92 -> 2199.7 | F88: =F89+F90+F91+F92 -> 1610.22 | G88: =G89+G90+G91+G92 -> 2393.57 | H88: =H89+H90+H91+H92 -> 2473.21 | I88: =I89+I90+I91+I92 -> 2932.66 | ... Y88: =Y89+Y90+Y91+Y92 -> 3166.1
A89: - средневзв. стоимость э/э (м) | B89: 1442.16 | C89: 1265.16 | D89: 1086.2 | E89: 834.84 | F89: 245.36 | G89: 1028.71 | H89: 1108.35 | I89: 1567.8 | J89: 2353.49 | K89: 2840.26 | L89: 2913.4 | M89: 3019.15 | N89: 3139.4 | O89: 3165.17 | P89: 3160.37 | Q89: 3077.56 | R89: 3104.6 | S89: 2908.63 | T89: 2839.87 | U89: 2723.3 | V89: 2695.03 | W89: 2675.32 | X89: 2427.84 | Y89: 1801.24
A90: - услуги по передаче | B90: =$B$15 -> 1283.66 | C90: =$B90 -> 1283.66 | D90: =$B90 -> 1283.66 | E90: =$B90 -> 1283.66 | F90: =$B90 -> 1283.66 | G90: =$B90 -> 1283.66 | H90: =$B90 -> 1283.66 | I90: =$B90 -> 1283.66 | J90: =$B90 -> 1283.66 | ... Y90: =$B90 -> 1283.66
A91: - сбытовая надбавка ГП | B91: 75.85 | C91: 75.85 | D91: 75.85 | E91: 75.85 | F91: 75.85 | G91: 75.85 | H91: 75.85 | I91: 75.85 | J91: 75.85 | K91: 75.85 | L91: 75.85 | M91: 75.85 | N91: 75.85 | O91: 75.85 | P91: 75.85 | Q91: 75.85 | R91: 75.85 | S91: 75.85 | T91: 75.85 | U91: 75.85 | V91: 75.85 | W91: 75.85 | X91: 75.85 | Y91: 75.85
A92: - инфраструктурные платежи | B92: =$B$17 -> 5.35 | C92: =$B92 -> 5.35 | D92: =$B92 -> 5.35 | E92: =$B92 -> 5.35 | F92: =$B92 -> 5.35 | G92: =$B92 -> 5.35 | H92: =$B92 -> 5.35 | I92: =$B92 -> 5.35 | J92: =$B92 -> 5.35 | ... Y92: =$B92 -> 5.35
A93: 17 | B93: =B94+B95+B96+B97 -> 2938.75 | C93: =C94+C95+C96+C97 -> 2667.08 | D93: =D94+D95+D96+D97 -> 2456.58 | E93: =E94+E95+E96+E97 -> 2195.35 | F93: =F94+F95+F96+F97 -> 2168.92 | G93: =G94+G95+G96+G97 -> 2406.7 | H93: =H94+H95+H96+H97 -> 2668.07 | I93: =I94+I95+I96+I97 -> 3262.96 | ... Y93: =Y94+Y95+Y96+Y97 -> 3319.55
A94: - средневзв. стоимость э/э (м) | B94: 1573.89 | C94: 1302.22 | D94: 1091.72 | E94: 830.49 | F94: 804.06 | G94: 1041.84 | H94: 1303.21 | I94: 1898.1 | J94: 2614.48 | K94: 2879.07 | L94: 2880.95 | M94: 2987.46 | N94: 2988.91 | O94: 3012.75 | P94: 3011.48 | Q94: 2998.42 | R94: 3003.29 | S94: 2956.9 | T94: 2893.27 | U94: 2833.01 | V94: 2809.18 | W94: 2792.54 | X94: 2598.47 | Y94: 1954.69
A95: - услуги по передаче | B95: =$B$15 -> 1283.66 | C95: =$B95 -> 1283.66 | D95: =$B95 -> 1283.66 | E95: =$B95 -> 1283.66 | F95: =$B95 -> 1283.66 | G95: =$B95 -> 1283.66 | H95: =$B95 -> 1283.66 | I95: =$B95 -> 1283.66 | J95: =$B95 -> 1283.66 | ... Y95: =$B95 -> 1283.66
A96: - сбытовая надбавка ГП | B96: 75.85 | C96: 75.85 | D96: 75.85 | E96: 75.85 | F96: 75.85 | G96: 75.85 | H96: 75.85 | I96: 75.85 | J96: 75.85 | K96: 75.85 | L96: 75.85 | M96: 75.85 | N96: 75.85 | O96: 75.85 | P96: 75.85 | Q96: 75.85 | R96: 75.85 | S96: 75.85 | T96: 75.85 | U96: 75.85 | V96: 75.85 | W96: 75.85 | X96: 75.85 | Y96: 75.85
A97: - инфраструктурные платежи | B97: =$B$17 -> 5.35 | C97: =$B97 -> 5.35 | D97: =$B97 -> 5.35 | E97: =$B97 -> 5.35 | F97: =$B97 -> 5.35 | G97: =$B97 -> 5.35 | H97: =$B97 -> 5.35 | I97: =$B97 -> 5.35 | J97: =$B97 -> 5.35 | ... Y97: =$B97 -> 5.35
A98: 18 | B98: =B99+B100+B101+B102 -> 2961.06 | C98: =C99+C100+C101+C102 -> 2752.46 | D98: =D99+D100+D101+D102 -> 2555.12 | E98: =E99+E100+E101+E102 -> 2419.28 | F98: =F99+F100+F101+F102 -> 2183.47 | G98: =G99+G100+G101+G102 -> 2330.07 | H98: =H99+H100+H101+H102 -> 2777.46 | I98: =I99+I100+I101+I102 -> 3263.77 | ... Y98: =Y99+Y100+Y101+Y102 -> 3598.42
A99: - средневзв. стоимость э/э (м) | B99: 1596.2 | C99: 1387.6 | D99: 1190.26 | E99: 1054.42 | F99: 818.61 | G99: 965.21 | H99: 1412.6 | I99: 1898.91 | J99: 2860.17 | K99: 2989.82 | L99: 3086.44 | M99: 3307.34 | N99: 3295.17 | O99: 3432.71 | P99: 3454.66 | Q99: 3427.17 | R99: 3260.41 | S99: 3143.01 | T99: 3081.92 | U99: 2999.99 | V99: 2910.27 | W99: 2989.6 | X99: 2701.07 | Y99: 2233.56
A100: - услуги по передаче | B100: =$B$15 -> 1283.66 | C100: =$B100 -> 1283.66 | D100: =$B100 -> 1283.66 | E100: =$B100 -> 1283.66 | F100: =$B100 -> 1283.66 | G100: =$B100 -> 1283.66 | H100: =$B100 -> 1283.66 | I100: =$B100 -> 1283.66 | J100: =$B100 -> 1283.66 | ... Y100: =$B100 -> 1283.66
A101: - сбытовая надбавка ГП | B101: 75.85 | C101: 75.85 | D101: 75.85 | E101: 75.85 | F101: 75.85 | G101: 75.85 | H101: 75.85 | I101: 75.85 | J101: 75.85 | K101: 75.85 | L101: 75.85 | M101: 75.85 | N101: 75.85 | O101: 75.85 | P101: 75.85 | Q101: 75.85 | R101: 75.85 | S101: 75.85 | T101: 75.85 | U101: 75.85 | V101: 75.85 | W101: 75.85 | X101: 75.85 | Y101: 75.85
A102: - инфраструктурные платежи | B102: =$B$17 -> 5.35 | C102: =$B102 -> 5.35 | D102: =$B102 -> 5.35 | E102: =$B102 -> 5.35 | F102: =$B102 -> 5.35 | G102: =$B102 -> 5.35 | H102: =$B102 -> 5.35 | I102: =$B102 -> 5.35 | J102: =$B102 -> 5.35 | ... Y102: =$B102 -> 5.35
A103: 19 | B103: =B104+B105+B106+B107 -> 3186.84 | C103: =C104+C105+C106+C107 -> 2931.4 | D103: =D104+D105+D106+D107 -> 2779.75 | E103: =E104+E105+E106+E107 -> 2571.97 | F103: =F104+F105+F106+F107 -> 2495.48 | G103: =G104+G105+G106+G107 -> 2582.45 | H103: =H104+H105+H106+H107 -> 2592.96 | I103: =I104+I105+I106+I107 -> 2825.24 | ... Y103: =Y104+Y105+Y106+Y107 -> 3532.09
A104: - средневзв. стоимость э/э (м) | B104: 1821.98 | C104: 1566.54 | D104: 1414.89 | E104: 1207.11 | F104: 1130.62 | G104: 1217.59 | H104: 1228.1 | I104: 1460.38 | J104: 2307.57 | K104: 2763.29 | L104: 2840.74 | M104: 2852.42 | N104: 2892.84 | O104: 2901.08 | P104: 2908.51 | Q104: 2899.29 | R104: 2920.11 | S104: 2886.88 | T104: 2864.08 | U104: 2834.44 | V104: 2820.7 | W104: 2800.72 | X104: 2645.04 | Y104: 2167.23
...

Sheet М_июль 6 цк
A2: ='М_июль 1 цк'!A2 -> Предельные уровни нерегулируемых цен на электрическую энергию (мощность), поставляемую АО "Мосэнергосбыт" потребителям
A3: ='М_июль 1 цк'!A3 -> с максимальной мощностью энергопринимающих устройств не менее 10 МВт
A4: ='М_июль 1 цк'!A4 -> г. Москва
A5: ='М_июль 1 цк'!A5 -> Июль 2025 г.
A7: VI. Шестая ценовая категория для объемов покупки электрической энергии (мощности), в отношении которых за расчетный период осуществляются почасовое планирование и учет, а стоимость услуг по передаче электрической энергии определяется по тарифу на услуги по передаче электрической энергии в двухставочном выражении
A9: 1.1. Ставка за электрическую энергию предельного уровня нерегулируемых цен для абонентов группы "Иные прочие потребители", рублей/МВт∙ч без НДС
A11: Дата | B11: Ставка для фактических почасовых объемов покупки электрической энергии, отпущенных на уровне напряжения ВН
B12: 0:00-1:00 | C12: 1:00-2:00 | D12: 2:00-3:00 | E12: 3:00-4:00 | F12: 4:00-5:00 | G12: 5:00-6:00 | H12: 6:00-7:00 | I12: 7:00-8:00 | J12: 8:00-9:00 | K12: 9:00-10:00 | L12: 10:00-11:00 | M12: 11:00-12:00 | N12: 12:00-13:00 | O12: 13:00-14:00 | P12: 14:00-15:00 | Q12: 15:00-16:00 | R12: 16:00-17:00 | S12: 17:00-18:00 | T12: 18:00-19:00 | U12: 19:00-20:00 | V12: 20:00-21:00 | W12: 21:00-22:00 | X12: 22:00-23:00 | Y12: 23:00-0:00
A13: 1 | B13: =B14+B15+B16+B17 -> 1790.64 | C13: =C14+C15+C16+C17 -> 1522.1 | D13: =D14+D15+D16+D17 -> 1407.02 | E13: =E14+E15+E16+E17 -> 1306.22 | F13: =F14+F15+F16+F17 -> 1328.29 | G13: =G14+G15+G16+G17 -> 1613.58 | H13: =H14+H15+H16+H17 -> 1738.81 | I13: =I14+I15+I16+I17 -> 2190.67 | ... Y13: =Y14+Y15+Y16+Y17 -> 2212.78
A14: - средневзв. стоимость э/э (м) | B14: 1628.86 | C14: 1360.32 | D14: 1245.24 | E14: 1144.44 | F14: 1166.51 | G14: 1451.8 | H14: 1577.03 | I14: 2028.89 | J14: 2529.56 | K14: 2667.84 | L14: 2730.2 | M14: 2729.08 | N14: 2714.65 | O14: 2724.92 | P14: 2753.98 | Q14: 2768.72 | R14: 2747.79 | S14: 2753.91 | T14: 2732.01 | U14: 2682.67 | V14: 2648.86 | W14: 2621.29 | X14: 2312.02 | Y14: 2051
A15: - услуги по передаче | B15: 80.58 | C15: =$B15 -> 80.58 | D15: =$B15 -> 80.58 | E15: =$B15 -> 80.58 | F15: =$B15 -> 80.58 | G15: =$B15 -> 80.58 | H15: =$B15 -> 80.58 | I15: =$B15 -> 80.58 | J15: =$B15 -> 80.58 | ... Y15: =$B15 -> 80.58
A16: - сбытовая надбавка ГП | B16: 75.85 | C16: 75.85 | D16: 75.85 | E16: 75.85 | F16: 75.85 | G16: 75.85 | H16: 75.85 | I16: 75.85 | J16: 75.85 | K16: 75.85 | L16: 75.85 | M16: 75.85 | N16: 75.85 | O16: 75.85 | P16: 75.85 | Q16: 75.85 | R16: 75.85 | S16: 75.85 | T16: 75.85 | U16: 75.85 | V16: 75.85 | W16: 75.85 | X16: 75.85 | Y16: 75.85
A17: - инфраструктурные платежи | B17: 5.35 | C17: =$B17 -> 5.35 | D17: =$B17 -> 5.35 | E17: =$B17 -> 5.35 | F17: =$B17 -> 5.35 | G17: =$B17 -> 5.35 | H17: =$B17 -> 5.35 | I17: =$B17 -> 5.35 | J17: =$B17 -> 5.35 | ... Y17: =$B17 -> 5.35
A18: 2 | B18: =B19+B20+B21+B22 -> 1835.99 | C18: =C19+C20+C21+C22 -> 1676.01 | D18: =D19+D20+D21+D22 -> 1592.36 | E18: =E19+E20+E21+E22 -> 1376.86 | F18: =F19+F20+F21+F22 -> 1471.17 | G18: =G19+G20+G21+G22 -> 1672.22 | H18: =H19+H20+H21+H22 -> 1754.32 | I18: =I19+I20+I21+I22 -> 2241.35 | ... Y18: =Y19+Y20+Y21+Y22 -> 2147.39
A19: - средневзв. стоимость э/э (м) | B19: 1674.21 | C19: 1514.23 | D19: 1430.58 | E19: 1215.08 | F19: 1309.39 | G19: 1510.44 | H19: 1592.54 | I19: 2079.57 | J19: 2692.19 | K19: 2789.44 | L19: 2822.69 | M19: 2813.51 | N19: 2828.33 | O19: 2858.33 | P19: 2859.57 | Q19: 2849.01 | R19: 2822.57 | S19: 2803.02 | T19: 2792.13 | U19: 2764.19 | V19: 2733.69 | W19: 2712.26 | X19: 2430.41 | Y19: 1985.61
A20: - услуги по передаче | B20: =$B$15 -> 80.58 | C20: =$B20 -> 80.58 | D20: =$B20 -> 80.58 | E20: =$B20 -> 80.58 | F20: =$B20 -> 80.58 | G20: =$B20 -> 80.58 | H20: =$B20 -> 80.58 | I20: =$B20 -> 80.58 | J20: =$B20 -> 80.58 | ... Y20: =$B20 -> 80.58
A21: - сбытовая надбавка ГП | B21: 75.85 | C21: 75.85 | D21: 75.85 | E21: 75.85 | F21: 75.85 | G21: 75.85 | H21: 75.85 | I21: 75.85 | J21: 75.85 | K21: 75.85 | L21: 75.85 | M21: 75.85 | N21: 75.85 | O21: 75.85 | P21: 75.85 | Q21: 75.85 | R21: 75.85 | S21: 75.85 | T21: 75.85 | U21: 75.85 | V21: 75.85 | W21: 75.85 | X21: 75.85 | Y21: 75.85
A22: - инфраструктурные платежи | B22: =$B$17 -> 5.35 | C22: =$B22 -> 5.35 | D22: =$B22 -> 5.35 | E22: =$B22 -> 5.35 | F22: =$B22 -> 5.35 | G22: =$B22 -> 5.35 | H22: =$B22 -> 5.35 | I22: =$B22 -> 5.35 | J22: =$B22 -> 5.35 | ... Y22: =$B22 -> 5.35
A23: 3 | B23: =B24+B25+B26+B27 -> 1717.91 | C23: =C24+C25+C26+C27 -> 1559.72 | D23: =D24+D25+D26+D27 -> 1436.53 | E23: =E24+E25+E26+E27 -> 1320.83 | F23: =F24+F25+F26+F27 -> 1332.44 | G23: =G24+G25+G26+G27 -> 1557.9 | H23: =H24+H25+H26+H27 -> 1701.86 | I23: =I24+I25+I26+I27 -> 2156.05 | ... Y23: =Y24+Y25+Y26+Y27 -> 2135.67
A24: - средневзв. стоимость э/э (м) | B24: 1556.13 | C24: 1397.94 | D24: 1274.75 | E24: 1159.05 | F24: 1170.66 | G24: 1396.12 | H24: 1540.08 | I24: 1994.27 | J24: 2544.78 | K24: 2584.11 | L24: 2626.41 | M24: 2659.13 | N24: 2652.3 | O24: 2636.86 | P24: 2858.16 | Q24: 2926.75 | R24: 2869.94 | S24: 2673.56 | T24: 2743.09 | U24: 2636.57 | V24: 2682.12 | W24: 2663.22 | X24: 2402.89 | Y24: 1973.89
A25: - услуги по передаче | B25: =$B$15 -> 80.58 | C25: =$B25 -> 80.58 | D25: =$B25 -> 80.58 | E25: =$B25 -> 80.58 | F25: =$B25 -> 80.58 | G25: =$B25 -> 80.58 | H25: =$B25 -> 80.58 | I25: =$B25 -> 80.58 | J25: =$B25 -> 80.58 | ... Y25: =$B25 -> 80.58
A26: - сбытовая надбавка ГП | B26: 75.85 | C26: 75.85 | D26: 75.85 | E26: 75.85 | F26: 75.85 | G26: 75.85 | H26: 75.85 | I26: 75.85 | J26: 75.85 | K26: 75.85 | L26: 75.85 | M26: 75.85 | N26: 75.85 | O26: 75.85 | P26: 75.85 | Q26: 75.85 | R26: 75.85 | S26: 75.85 | T26: 75.85 | U26: 75.85 | V26: 75.85 | W26: 75.85 | X26: 75.85 | Y26: 75.85
A27: - инфраструктурные платежи | B27: =$B$17 -> 5.35 | C27: =$B27 -> 5.35 | D27: =$B27 -> 5.35 | E27: =$B27 -> 5.35 | F27: =$B27 -> 5.35 | G27: =$B27 -> 5.35 | H27: =$B27 -> 5.35 | I27: =$B27 -> 5.35 | J27: =$B27 -> 5.35 | ... Y27: =$B27 -> 5.35
A28: 4 | B28: =B29+B30+B31+B32 -> 1808.53 | C28: =C29+C30+C31+C32 -> 1588.5 | D28: =D29+D30+D31+D32 -> 1443.05 | E28: =E29+E30+E31+E32 -> 1313.77 | F28: =F29+F30+F31+F32 -> 1330.26 | G28: =G29+G30+G31+G32 -> 1562.81 | H28: =H29+H30+H31+H32 -> 1714.89 | I28: =I29+I30+I31+I32 -> 2177.51 | ... Y28: =Y29+Y30+Y31+Y32 -> 2192.51
A29: - средневзв. стоимость э/э (м) | B29: 1646.75 | C29: 1426.72 | D29: 1281.27 | E29: 1151.99 | F29: 1168.48 | G29: 1401.03 | H29: 1553.11 | I29: 2015.73 | J29: 2553.88 | K29: 2673.17 | L29: 2626.61 | M29: 2625.16 | N29: 2692.98 | O29: 2624.48 | P29: 2769.95 | Q29: 2822.13 | R29: 2803.3 | S29: 2780.13 | T29: 2766.9 | U29: 2634.11 | V29: 2616.68 | W29: 2693.6 | X29: 2496.58 | Y29: 2030.73
A30: - услуги по передаче | B30: =$B$15 -> 80.58 | C30: =$B30 -> 80.58 | D30: =$B30 -> 80.58 | E30: =$B30 -> 80.58 | F30: =$B30 -> 80.58 | G30: =$B30 -> 80.58 | H30: =$B30 -> 80.58 | I30: =$B30 -> 80.58 | J30: =$B30 -> 80.58 | ... Y30: =$B30 -> 80.58
A31: - сбытовая надбавка ГП | B31: 75.85 | C31: 75.85 | D31: 75.85 | E31: 75.85 | F31: 75.85 | G31: 75.85 | H31: 75.85 | I31: 75.85 | J31: 75.85 | K31: 75.85 | L31: 75.85 | M31: 75.85 | N31: 75.85 | O31: 75.85 | P31: 75.85 | Q31: 75.85 | R31: 75.85 | S31: 75.85 | T31: 75.85 | U31: 75.85 | V31: 75.85 | W31: 75.85 | X31: 75.85 | Y31: 75.85
A32: - инфраструктурные платежи | B32: =$B$17 -> 5.35 | C32: =$B32 -> 5.35 | D32: =$B32 -> 5.35 | E32: =$B32 -> 5.35 | F32: =$B32 -> 5.35 | G32: =$B32 -> 5.35 | H32: =$B32 -> 5.35 | I32: =$B32 -> 5.35 | J32: =$B32 -> 5.35 | ... Y32: =$B32 -> 5.35
A33: 5 | B33: =B34+B35+B36+B37 -> 1900.37 | C33: =C34+C35+C36+C37 -> 1666.14 | D33: =D34+D35+D36+D37 -> 1559.09 | E33: =E34+E35+E36+E37 -> 1415.95 | F33: =F34+F35+F36+F37 -> 1357.66 | G33: =G34+G35+G36+G37 -> 1348.71 | H33: =H34+H35+H36+H37 -> 1451.87 | I33: =I34+I35+I36+I37 -> 1816.03 | ... Y33: =Y34+Y35+Y36+Y37 -> 2128.17
A34: - средневзв. стоимость э/э (м) | B34: 1738.59 | C34: 1504.36 | D34: 1397.31 | E34: 1254.17 | F34: 1195.88 | G34: 1186.93 | H34: 1290.09 | I34: 1654.25 | J34: 2120.14 | K34: 2356.02 | L34: 2424.84 | M34: 2454.2 | N34: 2449.57 | O34: 2453.65 | P34: 2450.03 | Q34: 2512.33 | R34: 2520.61 | S34: 2485.92 | T34: 2465.87 | U34: 2437.81 | V34: 2435.72 | W34: 2452.81 | X34: 2154.71 | Y34: 1966.39
A35: - услуги по передаче | B35: =$B$15 -> 80.58 | C35: =$B35 -> 80.58 | D35: =$B35 -> 80.58 | E35: =$B35 -> 80.58 | F35: =$B35 -> 80.58 | G35: =$B35 -> 80.58 | H35: =$B35 -> 80.58 | I35: =$B35 -> 80.58 | J35: =$B35 -> 80.58 | ... Y35: =$B35 -> 80.58
A36: - сбытовая надбавка ГП | B36: 75.85 | C36: 75.85 | D36: 75.85 | E36: 75.85 | F36: 75.85 | G36: 75.85 | H36: 75.85 | I36: 75.85 | J36: 75.85 | K36: 75.85 | L36: 75.85 | M36: 75.85 | N36: 75.85 | O36: 75.85 | P36: 75.85 | Q36: 75.85 | R36: 75.85 | S36: 75.85 | T36: 75.85 | U36: 75.85 | V36: 75.85 | W36: 75.85 | X36: 75.85 | Y36: 75.85
A37: - инфраструктурные платежи | B37: =$B$17 -> 5.35 | C37: =$B37 -> 5.35 | D37: =$B37 -> 5.35 | E37: =$B37 -> 5.35 | F37: =$B37 -> 5.35 | G37: =$B37 -> 5.35 | H37: =$B37 -> 5.35 | I37: =$B37 -> 5.35 | J37: =$B37 -> 5.35 | ... Y37: =$B37 -> 5.35
A38: 6 | B38: =B39+B40+B41+B42 -> 1908.66 | C38: =C39+C40+C41+C42 -> 1654.59 | D38: =D39+D40+D41+D42 -> 1533.61 | E38: =E39+E40+E41+E42 -> 1347.98 | F38: =F39+F40+F41+F42 -> 1290.49 | G38: =G39+G40+G41+G42 -> 1289.42 | H38: =H39+H40+H41+H42 -> 1234.17 | I38: =I39+I40+I41+I42 -> 1663.02 | ... Y38: =Y39+Y40+Y41+Y42 -> 1989.55
A39: - средневзв. стоимость э/э (м) | B39: 1746.88 | C39: 1492.81 | D39: 1371.83 | E39: 1186.2 | F39: 1128.71 | G39: 1127.64 | H39: 1072.39 | I39: 1501.24 | J39: 1906.15 | K39: 2244.04 | L39: 2381.13 | M39: 2381.09 | N39: 2383.85 | O39: 2390.93 | P39: 2395.78 | Q39: 2397.59 | R39: 2450.8 | S39: 2436.66 | T39: 2434.99 | U39: 2418.9 | V39: 2418.43 | W39: 2414.63 | X39: 2170.25 | Y39: 1827.77
A40: - услуги по передаче | B40: =$B$15 -> 80.58 | C40: =$B40 -> 80.58 | D40: =$B40 -> 80.58 | E40: =$B40 -> 80.58 | F40: =$B40 -> 80.58 | G40: =$B40 -> 80.58 | H40: =$B40 -> 80.58 | I40: =$B40 -> 80.58 | J40: =$B40 -> 80.58 | ... Y40: =$B40 -> 80.58
A41: - сбытовая надбавка ГП | B41: 75.85 | C41: 75.85 | D41: 75.85 | E41: 75.85 | F41: 75.85 | G41: 75.85 | H41: 75.85 | I41: 75.85 | J41: 75.85 | K41: 75.85 | L41: 75.85 | M41: 75.85 | N41: 75.85 | O41: 75.85 | P41: 75.85 | Q41: 75.85 | R41: 75.85 | S41: 75.85 | T41: 75.85 | U41: 75.85 | V41: 75.85 | W41: 75.85 | X41: 75.85 | Y41: 75.85
A42: - инфраструктурные платежи | B42: =$B$17 -> 5.35 | C42: =$B42 -> 5.35 | D42: =$B42 -> 5.35 | E42: =$B42 -> 5.35 | F42: =$B42 -> 5.35 | G42: =$B42 -> 5.35 | H42: =$B42 -> 5.35 | I42: =$B42 -> 5.35 | J42: =$B42 -> 5.35 | ... Y42: =$B42 -> 5.35
A43: 7 | B43: =B44+B45+B46+B47 -> 1832.92 | C43: =C44+C45+C46+C47 -> 1664.39 | D43: =D44+D45+D46+D47 -> 1463.76 | E43: =E44+E45+E46+E47 -> 1319.03 | F43: =F44+F45+F46+F47 -> 1287.83 | G43: =G44+G45+G46+G47 -> 1377.41 | H43: =H44+H45+H46+H47 -> 1683.55 | I43: =I44+I45+I46+I47 -> 2124.78 | ... Y43: =Y44+Y45+Y46+Y47 -> 2017.09
A44: - средневзв. стоимость э/э (м) | B44: 1671.14 | C44: 1502.61 | D44: 1301.98 | E44: 1157.25 | F44: 1126.05 | G44: 1215.63 | H44: 1521.77 | I44: 1963 | J44: 2501.65 | K44: 2628.05 | L44: 2688.27 | M44: 2729.07 | N44: 2713.73 | O44: 2738.01 | P44: 2723.11 | Q44: 2756.44 | R44: 2704.53 | S44: 2819.29 | T44: 2719.06 | U44: 2682.93 | V44: 2628.49 | W44: 2645.08 | X44: 2204.5 | Y44: 1855.31
A45: - услуги по передаче | B45: =$B$15 -> 80.58 | C45: =$B45 -> 80.58 | D45: =$B45 -> 80.58 | E45: =$B45 -> 80.58 | F45: =$B45 -> 80.58 | G45: =$B45 -> 80.58 | H45: =$B45 -> 80.58 | I45: =$B45 -> 80.58 | J45: =$B45 -> 80.58 | ... Y45: =$B45 -> 80.58
A46: - сбытовая надбавка ГП | B46: 75.85 | C46: 75.85 | D46: 75.85 | E46: 75.85 | F46: 75.85 | G46: 75.85 | H46: 75.85 | I46: 75.85 | J46: 75.85 | K46: 75.85 | L46: 75.85 | M46: 75.85 | N46: 75.85 | O46: 75.85 | P46: 75.85 | Q46: 75.85 | R46: 75.85 | S46: 75.85 | T46: 75.85 | U46: 75.85 | V46: 75.85 | W46: 75.85 | X46: 75.85 | Y46: 75.85
A47: - инфраструктурные платежи | B47: =$B$17 -> 5.35 | C47: =$B47 -> 5.35 | D47: =$B47 -> 5.35 | E47: =$B47 -> 5.35 | F47: =$B47 -> 5.35 | G47: =$B47 -> 5.35 | H47: =$B47 -> 5.35 | I47: =$B47 -> 5.35 | J47: =$B47 -> 5.35 | ... Y47: =$B47 -> 5.35
A48: 8 | B48: =B49+B50+B51+B52 -> 1666.14 | C48: =C49+C50+C51+C52 -> 1392.03 | D48: =D49+D50+D51+D52 -> 1229.03 | E48: =E49+E50+E51+E52 -> 337.16 | F48: =F49+F50+F51+F52 -> 295.59 | G48: =G49+G50+G51+G52 -> 310.8 | H48: =H49+H50+H51+H52 -> 1369.01 | I48: =I49+I50+I51+I52 -> 1964.58 | ... Y48: =Y49+Y50+Y51+Y52 -> 2002.55
A49: - средневзв. стоимость э/э (м) | B49: 1504.36 | C49: 1230.25 | D49: 1067.25 | E49: 175.38 | F49: 133.81 | G49: 149.02 | H49: 1207.23 | I49: 1802.8 | J49: 2372.03 | K49: 2606.12 | L49: 2739.12 | M49: 2751.76 | N49: 2735.29 | O49: 2737.68 | P49: 3066.38 | Q49: 2814.6 | R49: 2837.85 | S49: 2812.02 | T49: 2716.78 | U49: 2610 | V49: 2589.9 | W49: 2530.13 | X49: 2135.76 | Y49: 1840.77
A50: - услуги по передаче | B50: =$B$15 -> 80.58 | C50: =$B50 -> 80.58 | D50: =$B50 -> 80.58 | E50: =$B50 -> 80.58 | F50: =$B50 -> 80.58 | G50: =$B50 -> 80.58 | H50: =$B50 -> 80.58 | I50: =$B50 -> 80.58 | J50: =$B50 -> 80.58 | ... Y50: =$B50 -> 80.58
A51: - сбытовая надбавка ГП | B51: 75.85 | C51: 75.85 | D51: 75.85 | E51: 75.85 | F51: 75.85 | G51: 75.85 | H51: 75.85 | I51: 75.85 | J51: 75.85 | K51: 75.85 | L51: 75.85 | M51: 75.85 | N51: 75.85 | O51: 75.85 | P51: 75.85 | Q51: 75.85 | R51: 75.85 | S51: 75.85 | T51: 75.85 | U51: 75.85 | V51: 75.85 | W51: 75.85 | X51: 75.85 | Y51: 75.85
A52: - инфраструктурные платежи | B52: =$B$17 -> 5.35 | C52: =$B52 -> 5.35 | D52: =$B52 -> 5.35 | E52: =$B52 -> 5.35 | F52: =$B52 -> 5.35 | G52: =$B52 -> 5.35 | H52: =$B52 -> 5.35 | I52: =$B52 -> 5.35 | J52: =$B52 -> 5.35 | ... Y52: =$B52 -> 5.35
A53: 9 | B53: =B54+B55+B56+B57 -> 1839.64 | C53: =C54+C55+C56+C57 -> 1273.17 | D53: =D54+D55+D56+D57 -> 304.07 | E53: =E54+E55+E56+E57 -> 299.85 | F53: =F54+F55+F56+F57 -> 297.38 | G53: =G54+G55+G56+G57 -> 310.67 | H53: =H54+H55+H56+H57 -> 1276.58 | I53: =I54+I55+I56+I57 -> 1979.08 | ... Y53: =Y54+Y55+Y56+Y57 -> 1737.16
A54: - средневзв. стоимость э/э (м) | B54: 1677.86 | C54: 1111.39 | D54: 142.29 | E54: 138.07 | F54: 135.6 | G54: 148.89 | H54: 1114.8 | I54: 1817.3 | J54: 2119.11 | K54: 2482.57 | L54: 2678.73 | M54: 2743.21 | N54: 2741.25 | O54: 3037.78 | P54: 3195.02 | Q54: 3208.54 | R54: 3153.2 | S54: 3125.45 | T54: 2772.03 | U54: 2555.49 | V54: 2500.3 | W54: 2482.62 | X54: 2041.44 | Y54: 1575.38
A55: - услуги по передаче | B55: =$B$15 -> 80.58 | C55: =$B55 -> 80.58 | D55: =$B55 -> 80.58 | E55: =$B55 -> 80.58 | F55: =$B55 -> 80.58 | G55: =$B55 -> 80.58 | H55: =$B55 -> 80.58 | I55: =$B55 -> 80.58 | J55: =$B55 -> 80.58 | ... Y55: =$B55 -> 80.58
A56: - сбытовая надбавка ГП | B56: 75.85 | C56: 75.85 | D56: 75.85 | E56: 75.85 | F56: 75.85 | G56: 75.85 | H56: 75.85 | I56: 75.85 | J56: 75.85 | K56: 75.85 | L56: 75.85 | M56: 75.85 | N56: 75.85 | O56: 75.85 | P56: 75.85 | Q56: 75.85 | R56: 75.85 | S56: 75.85 | T56: 75.85 | U56: 75.85 | V56: 75.85 | W56: 75.85 | X56: 75.85 | Y56: 75.85
A57: - инфраструктурные платежи | B57: =$B$17 -> 5.35 | C57: =$B57 -> 5.35 | D57: =$B57 -> 5.35 | E57: =$B57 -> 5.35 | F57: =$B57 -> 5.35 | G57: =$B57 -> 5.35 | H57: =$B57 -> 5.35 | I57: =$B57 -> 5.35 | J57: =$B57 -> 5.35 | ... Y57: =$B57 -> 5.35
A58: 10 | B58: =B59+B60+B61+B62 -> 1491.77 | C58: =C59+C60+C61+C62 -> 1222.9 | D58: =D59+D60+D61+D62 -> 289.91 | E58: =E59+E60+E61+E62 -> 267.08 | F58: =F59+F60+F61+F62 -> 274.16 | G58: =G59+G60+G61+G62 -> 294.26 | H58: =H59+H60+H61+H62 -> 855.82 | I58: =I59+I60+I61+I62 -> 1767.51 | ... Y58: =Y59+Y60+Y61+Y62 -> 1956.76
A59: - средневзв. стоимость э/э (м) | B59: 1329.99 | C59: 1061.12 | D59: 128.13 | E59: 105.3 | F59: 112.38 | G59: 132.48 | H59: 694.04 | I59: 1605.73 | J59: 2205.54 | K59: 2716.25 | L59: 3022.68 | M59: 3163.37 | N59: 2642.32 | O59: 3014.75 | P59: 3222.34 | Q59: 3067.67 | R59: 3069.28 | S59: 2992.76 | T59: 2848.18 | U59: 2825.87 | V59: 2714.83 | W59: 2657.1 | X59: 2170.51 | Y59: 1794.98
A60: - услуги по передаче | B60: =$B$15 -> 80.58 | C60: =$B60 -> 80.58 | D60: =$B60 -> 80.58 | E60: =$B60 -> 80.58 | F60: =$B60 -> 80.58 | G60: =$B60 -> 80.58 | H60: =$B60 -> 80.58 | I60: =$B60 -> 80.58 | J60: =$B60 -> 80.58 | ... Y60: =$B60 -> 80.58
A61: - сбытовая надбавка ГП | B61: 75.85 | C61: 75.85 | D61: 75.85 | E61: 75.85 | F61: 75.85 | G61: 75.85 | H61: 75.85 | I61: 75.85 | J61: 75.85 | K61: 75.85 | L61: 75.85 | M61: 75.85 | N61: 75.85 | O61: 75.85 | P61: 75.85 | Q61: 75.85 | R61: 75.85 | S61: 75.85 | T61: 75.85 | U61: 75.85 | V61: 75.85 | W61: 75.85 | X61: 75.85 | Y61: 75.85
A62: - инфраструктурные платежи | B62: =$B$17 -> 5.35 | C62: =$B62 -> 5.35 | D62: =$B62 -> 5.35 | E62: =$B62 -> 5.35 | F62: =$B62 -> 5.35 | G62: =$B62 -> 5.35 | H62: =$B62 -> 5.35 | I62: =$B62 -> 5.35 | J62: =$B62 -> 5.35 | ... Y62: =$B62 -> 5.35
A63: 11 | B63: =B64+B65+B66+B67 -> 1610.53 | C63: =C64+C65+C66+C67 -> 1386.21 | D63: =D64+D65+D66+D67 -> 304.59 | E63: =E64+E65+E66+E67 -> 298.62 | F63: =F64+F65+F66+F67 -> 299.21 | G63: =G64+G65+G66+G67 -> 301.88 | H63: =H64+H65+H66+H67 -> 1492.83 | I63: =I64+I65+I66+I67 -> 1925.34 | ... Y63: =Y64+Y65+Y66+Y67 -> 2206.97
A64: - средневзв. стоимость э/э (м) | B64: 1448.75 | C64: 1224.43 | D64: 142.81 | E64: 136.84 | F64: 137.43 | G64: 140.1 | H64: 1331.05 | I64: 1763.56 | J64: 2502.42 | K64: 2764.81 | L64: 2784.94 | M64: 2887.65 | N64: 2900.09 | O64: 2967.59 | P64: 2739.34 | Q64: 3046.6 | R64: 3047.07 | S64: 3334.07 | T64: 2910.2 | U64: 2822.33 | V64: 2944.81 | W64: 2817.67 | X64: 2352.27 | Y64: 2045.19
A65: - услуги по передаче | B65: =$B$15 -> 80.58 | C65: =$B65 -> 80.58 | D65: =$B65 -> 80.58 | E65: =$B65 -> 80.58 | F65: =$B65 -> 80.58 | G65: =$B65 -> 80.58 | H65: =$B65 -> 80.58 | I65: =$B65 -> 80.58 | J65: =$B65 -> 80.58 | ... Y65: =$B65 -> 80.58
A66: - сбытовая надбавка ГП | B66: 75.85 | C66: 75.85 | D66: 75.85 | E66: 75.85 | F66: 75.85 | G66: 75.85 | H66: 75.85 | I66: 75.85 | J66: 75.85 | K66: 75.85 | L66: 75.85 | M66: 75.85 | N66: 75.85 | O66: 75.85 | P66: 75.85 | Q66: 75.85 | R66: 75.85 | S66: 75.85 | T66: 75.85 | U66: 75.85 | V66: 75.85 | W66: 75.85 | X66: 75.85 | Y66: 75.85
A67: - инфраструктурные платежи | B67: =$B$17 -> 5.35 | C67: =$B67 -> 5.35 | D67: =$B67 -> 5.35 | E67: =$B67 -> 5.35 | F67: =$B67 -> 5.35 | G67: =$B67 -> 5.35 | H67: =$B67 -> 5.35 | I67: =$B67 -> 5.35 | J67: =$B67 -> 5.35 | ... Y67: =$B67 -> 5.35
A68: 12 | B68: =B69+B70+B71+B72 -> 1921.67 | C68: =C69+C70+C71+C72 -> 1595.25 | D68: =D69+D70+D71+D72 -> 1429.88 | E68: =E69+E70+E71+E72 -> 509 | F68: =F69+F70+F71+F72 -> 324.76 | G68: =G69+G70+G71+G72 -> 321.89 | H68: =H69+H70+H71+H72 -> 1262.09 | I68: =I69+I70+I71+I72 -> 1777.52 | ... Y68: =Y69+Y70+Y71+Y72 -> 2298.07
A69: - средневзв. стоимость э/э (м) | B69: 1759.89 | C69: 1433.47 | D69: 1268.1 | E69: 347.22 | F69: 162.98 | G69: 160.11 | H69: 1100.31 | I69: 1615.74 | J69: 2200.28 | K69: 2549.89 | L69: 2728.84 | M69: 2742.61 | N69: 2736.31 | O69: 2831.32 | P69: 2846 | Q69: 2785 | R69: 3199.31 | S69: 3149.47 | T69: 2764.72 | U69: 2664.69 | V69: 2764.76 | W69: 2831.94 | X69: 2541.31 | Y69: 2136.29
A70: - услуги по передаче | B70: =$B$15 -> 80.58 | C70: =$B70 -> 80.58 | D70: =$B70 -> 80.58 | E70: =$B70 -> 80.58 | F70: =$B70 -> 80.58 | G70: =$B70 -> 80.58 | H70: =$B70 -> 80.58 | I70: =$B70 -> 80.58 | J70: =$B70 -> 80.58 | ... Y70: =$B70 -> 80.58
A71: - сбытовая надбавка ГП | B71: 75.85 | C71: 75.85 | D71: 75.85 | E71: 75.85 | F71: 75.85 | G71: 75.85 | H71: 75.85 | I71: 75.85 | J71: 75.85 | K71: 75.85 | L71: 75.85 | M71: 75.85 | N71: 75.85 | O71: 75.85 | P71: 75.85 | Q71: 75.85 | R71: 75.85 | S71: 75.85 | T71: 75.85 | U71: 75.85 | V71: 75.85 | W71: 75.85 | X71: 75.85 | Y71: 75.85
A72: - инфраструктурные платежи | B72: =$B$17 -> 5.35 | C72: =$B72 -> 5.35 | D72: =$B72 -> 5.35 | E72: =$B72 -> 5.35 | F72: =$B72 -> 5.35 | G72: =$B72 -> 5.35 | H72: =$B72 -> 5.35 | I72: =$B72 -> 5.35 | J72: =$B72 -> 5.35 | ... Y72: =$B72 -> 5.35
A73: 13 | B73: =B74+B75+B76+B77 -> 1845.39 | C73: =C74+C75+C76+C77 -> 1632.67 | D73: =D74+D75+D76+D77 -> 1464.01 | E73: =E74+E75+E76+E77 -> 349.64 | F73: =F74+F75+F76+F77 -> 314.45 | G73: =G74+G75+G76+G77 -> 311.18 | H73: =H74+H75+H76+H77 -> 1118.76 | I73: =I74+I75+I76+I77 -> 1581.6 | ... Y73: =Y74+Y75+Y76+Y77 -> 2157.42
A74: - средневзв. стоимость э/э (м) | B74: 1683.61 | C74: 1470.89 | D74: 1302.23 | E74: 187.86 | F74: 152.67 | G74: 149.4 | H74: 956.98 | I74: 1419.82 | J74: 1963.48 | K74: 2454.62 | L74: 2576.53 | M74: 2570.51 | N74: 2755.8 | O74: 2713.91 | P74: 2777.03 | Q74: 2793.84 | R74: 2770.44 | S74: 2896.82 | T74: 2816.88 | U74: 2738.11 | V74: 2717.75 | W74: 2712.31 | X74: 2446.01 | Y74: 1995.64
A75: - услуги по передаче | B75: =$B$15 -> 80.58 | C75: =$B75 -> 80.58 | D75: =$B75 -> 80.58 | E75: =$B75 -> 80.58 | F75: =$B75 -> 80.58 | G75: =$B75 -> 80.58 | H75: =$B75 -> 80.58 | I75: =$B75 -> 80.58 | J75: =$B75 -> 80.58 | ... Y75: =$B75 -> 80.58
A76: - сбытовая надбавка ГП | B76: 75.85 | C76: 75.85 | D76: 75.85 | E76: 75.85 | F76: 75.85 | G76: 75.85 | H76: 75.85 | I76: 75.85 | J76: 75.85 | K76: 75.85 | L76: 75.85 | M76: 75.85 | N76: 75.85 | O76: 75.85 | P76: 75.85 | Q76: 75.85 | R76: 75.85 | S76: 75.85 | T76: 75.85 | U76: 75.85 | V76: 75.85 | W76: 75.85 | X76: 75.85 | Y76: 75.85
A77: - инфраструктурные платежи | B77: =$B$17 -> 5.35 | C77: =$B77 -> 5.35 | D77: =$B77 -> 5.35 | E77: =$B77 -> 5.35 | F77: =$B77 -> 5.35 | G77: =$B77 -> 5.35 | H77: =$B77 -> 5.35 | I77: =$B77 -> 5.35 | J77: =$B77 -> 5.35 | ... Y77: =$B77 -> 5.35
A78: 14 | B78: =B79+B80+B81+B82 -> 1718.17 | C78: =C79+C80+C81+C82 -> 1521.54 | D78: =D79+D80+D81+D82 -> 416.73 | E78: =E79+E80+E81+E82 -> 324.04 | F78: =F79+F80+F81+F82 -> 319.76 | G78: =G79+G80+G81+G82 -> 324.06 | H78: =H79+H80+H81+H82 -> 1338.23 | I78: =I79+I80+I81+I82 -> 1992.19 | ... Y78: =Y79+Y80+Y81+Y82 -> 1963.79
A79: - средневзв. стоимость э/э (м) | B79: 1556.39 | C79: 1359.76 | D79: 254.95 | E79: 162.26 | F79: 157.98 | G79: 162.28 | H79: 1176.45 | I79: 1830.41 | J79: 2604.41 | K79: 2856.75 | L79: 2881.07 | M79: 2888.06 | N79: 2879.85 | O79: 2885.64 | P79: 2879.73 | Q79: 2945.29 | R79: 2924.98 | S79: 2912.14 | T79: 2862.41 | U79: 2782.39 | V79: 2770.5 | W79: 2737.42 | X79: 2214.19 | Y79: 1802.01
A80: - услуги по передаче | B80: =$B$15 -> 80.58 | C80: =$B80 -> 80.58 | D80: =$B80 -> 80.58 | E80: =$B80 -> 80.58 | F80: =$B80 -> 80.58 | G80: =$B80 -> 80.58 | H80: =$B80 -> 80.58 | I80: =$B80 -> 80.58 | J80: =$B80 -> 80.58 | ... Y80: =$B80 -> 80.58
A81: - сбытовая надбавка ГП | B81: 75.85 | C81: 75.85 | D81: 75.85 | E81: 75.85 | F81: 75.85 | G81: 75.85 | H81: 75.85 | I81: 75.85 | J81: 75.85 | K81: 75.85 | L81: 75.85 | M81: 75.85 | N81: 75.85 | O81: 75.85 | P81: 75.85 | Q81: 75.85 | R81: 75.85 | S81: 75.85 | T81: 75.85 | U81: 75.85 | V81: 75.85 | W81: 75.85 | X81: 75.85 | Y81: 75.85
A82: - инфраструктурные платежи | B82: =$B$17 -> 5.35 | C82: =$B82 -> 5.35 | D82: =$B82 -> 5.35 | E82: =$B82 -> 5.35 | F82: =$B82 -> 5.35 | G82: =$B82 -> 5.35 | H82: =$B82 -> 5.35 | I82: =$B82 -> 5.35 | J82: =$B82 -> 5.35 | ... Y82: =$B82 -> 5.35
A83: 15 | B83: =B84+B85+B86+B87 -> 1564.35 | C83: =C84+C85+C86+C87 -> 1374.82 | D83: =D84+D85+D86+D87 -> 1215.22 | E83: =E84+E85+E86+E87 -> 256.13 | F83: =F84+F85+F86+F87 -> 178.58 | G83: =G84+G85+G86+G87 -> 254.75 | H83: =H84+H85+H86+H87 -> 1170.5 | I83: =I84+I85+I86+I87 -> 1992.45 | ... Y83: =Y84+Y85+Y86+Y87 -> 2068.01
A84: - средневзв. стоимость э/э (м) | B84: 1402.57 | C84: 1213.04 | D84: 1053.44 | E84: 94.35 | F84: 16.8 | G84: 92.97 | H84: 1008.72 | I84: 1830.67 | J84: 2418.63 | K84: 2877.6 | L84: 2864.82 | M84: 2934.01 | N84: 2935.35 | O84: 2954.38 | P84: 2941.52 | Q84: 2963.32 | R84: 2998.29 | S84: 3034.97 | T84: 2947.25 | U84: 2831.49 | V84: 2731.14 | W84: 2727.39 | X84: 2181.36 | Y84: 1906.23
A85: - услуги по передаче | B85: =$B$15 -> 80.58 | C85: =$B85 -> 80.58 | D85: =$B85 -> 80.58 | E85: =$B85 -> 80.58 | F85: =$B85 -> 80.58 | G85: =$B85 -> 80.58 | H85: =$B85 -> 80.58 | I85: =$B85 -> 80.58 | J85: =$B85 -> 80.58 | ... Y85: =$B85 -> 80.58
A86: - сбытовая надбавка ГП | B86: 75.85 | C86: 75.85 | D86: 75.85 | E86: 75.85 | F86: 75.85 | G86: 75.85 | H86: 75.85 | I86: 75.85 | J86: 75.85 | K86: 75.85 | L86: 75.85 | M86: 75.85 | N86: 75.85 | O86: 75.85 | P86: 75.85 | Q86: 75.85 | R86: 75.85 | S86: 75.85 | T86: 75.85 | U86: 75.85 | V86: 75.85 | W86: 75.85 | X86: 75.85 | Y86: 75.85
A87: - инфраструктурные платежи | B87: =$B$17 -> 5.35 | C87: =$B87 -> 5.35 | D87: =$B87 -> 5.35 | E87: =$B87 -> 5.35 | F87: =$B87 -> 5.35 | G87: =$B87 -> 5.35 | H87: =$B87 -> 5.35 | I87: =$B87 -> 5.35 | J87: =$B87 -> 5.35 | ... Y87: =$B87 -> 5.35
A88: 16 | B88: =B89+B90+B91+B92 -> 1603.94 | C88: =C89+C90+C91+C92 -> 1426.94 | D88: =D89+D90+D91+D92 -> 1247.98 | E88: =E89+E90+E91+E92 -> 996.62 | F88: =F89+F90+F91+F92 -> 407.14 | G88: =G89+G90+G91+G92 -> 1190.49 | H88: =H89+H90+H91+H92 -> 1270.13 | I88: =I89+I90+I91+I92 -> 1729.58 | ... Y88: =Y89+Y90+Y91+Y92 -> 1963.02
A89: - средневзв. стоимость э/э (м) | B89: 1442.16 | C89: 1265.16 | D89: 1086.2 | E89: 834.84 | F89: 245.36 | G89: 1028.71 | H89: 1108.35 | I89: 1567.8 | J89: 2353.49 | K89: 2840.26 | L89: 2913.4 | M89: 3019.15 | N89: 3139.4 | O89: 3165.17 | P89: 3160.37 | Q89: 3077.56 | R89: 3104.6 | S89: 2908.63 | T89: 2839.87 | U89: 2723.3 | V89: 2695.03 | W89: 2675.32 | X89: 2427.84 | Y89: 1801.24
A90: - услуги по передаче | B90: =$B$15 -> 80.58 | C90: =$B90 -> 80.58 | D90: =$B90 -> 80.58 | E90: =$B90 -> 80.58 | F90: =$B90 -> 80.58 | G90: =$B90 -> 80.58 | H90: =$B90 -> 80.58 | I90: =$B90 -> 80.58 | J90: =$B90 -> 80.58 | ... Y90: =$B90 -> 80.58
A91: - сбытовая надбавка ГП | B91: 75.85 | C91: 75.85 | D91: 75.85 | E91: 75.85 | F91: 75.85 | G91: 75.85 | H91: 75.85 | I91: 75.85 | J91: 75.85 | K91: 75.85 | L91: 75.85 | M91: 75.85 | N91: 75.85 | O91: 75.85 | P91: 75.85 | Q91: 75.85 | R91: 75.85 | S91: 75.85 | T91: 75.85 | U91: 75.85 | V91: 75.85 | W91: 75.85 | X91: 75.85 | Y91: 75.85
A92: - инфраструктурные платежи | B92: =$B$17 -> 5.35 | C92: =$B92 -> 5.35 | D92: =$B92 -> 5.35 | E92: =$B92 -> 5.35 | F92: =$B92 -> 5.35 | G92: =$B92 -> 5.35 | H92: =$B92 -> 5.35 | I92: =$B92 -> 5.35 | J92: =$B92 -> 5.35 | ... Y92: =$B92 -> 5.35
A93: 17 | B93: =B94+B95+B96+B97 -> 1735.67 | C93: =C94+C95+C96+C97 -> 1464 | D93: =D94+D95+D96+D97 -> 1253.5 | E93: =E94+E95+E96+E97 -> 992.27 | F93: =F94+F95+F96+F97 -> 965.84 | G93: =G94+G95+G96+G97 -> 1203.62 | H93: =H94+H95+H96+H97 -> 1464.99 | I93: =I94+I95+I96+I97 -> 2059.88 | ... Y93: =Y94+Y95+Y96+Y97 -> 2116.47
A94: - средневзв. стоимость э/э (м) | B94: 1573.89 | C94: 1302.22 | D94: 1091.72 | E94: 830.49 | F94: 804.06 | G94: 1041.84 | H94: 1303.21 | I94: 1898.1 | J94: 2614.48 | K94: 2879.07 | L94: 2880.95 | M94: 2987.46 | N94: 2988.91 | O94: 3012.75 | P94: 3011.48 | Q94: 2998.42 | R94: 3003.29 | S94: 2956.9 | T94: 2893.27 | U94: 2833.01 | V94: 2809.18 | W94: 2792.54 | X94: 2598.47 | Y94: 1954.69
A95: - услуги по передаче | B95: =$B$15 -> 80.58 | C95: =$B95 -> 80.58 | D95: =$B95 -> 80.58 | E95: =$B95 -> 80.58 | F95: =$B95 -> 80.58 | G95: =$B95 -> 80.58 | H95: =$B95 -> 80.58 | I95: =$B95 -> 80.58 | J95: =$B95 -> 80.58 | ... Y95: =$B95 -> 80.58
A96: - сбытовая надбавка ГП | B96: 75.85 | C96: 75.85 | D96: 75.85 | E96: 75.85 | F96: 75.85 | G96: 75.85 | H96: 75.85 | I96: 75.85 | J96: 75.85 | K96: 75.85 | L96: 75.85 | M96: 75.85 | N96: 75.85 | O96: 75.85 | P96: 75.85 | Q96: 75.85 | R96: 75.85 | S96: 75.85 | T96: 75.85 | U96: 75.85 | V96: 75.85 | W96: 75.85 | X96: 75.85 | Y96: 75.85
A97: - инфраструктурные платежи | B97: =$B$17 -> 5.35 | C97: =$B97 -> 5.35 | D97: =$B97 -> 5.35 | E97: =$B97 -> 5.35 | F97: =$B97 -> 5.35 | G97: =$B97 -> 5.35 | H97: =$B97 -> 5.35 | I97: =$B97 -> 5.35 | J97: =$B97 -> 5.35 | ... Y97: =$B97 -> 5.35
A98: 18 | B98: =B99+B100+B101+B102 -> 1757.98 | C98: =C99+C100+C101+C102 -> 1549.38 | D98: =D99+D100+D101+D102 -> 1352.04 | E98: =E99+E100+E101+E102 -> 1216.2 | F98: =F99+F100+F101+F102 -> 980.39 | G98: =G99+G100+G101+G102 -> 1126.99 | H98: =H99+H100+H101+H102 -> 1574.38 | I98: =I99+I100+I101+I102 -> 2060.69 | ... Y98: =Y99+Y100+Y101+Y102 -> 2395.34
A99: - средневзв. стоимость э/э (м) | B99: 1596.2 | C99: 1387.6 | D99: 1190.26 | E99: 1054.42 | F99: 818.61 | G99: 965.21 | H99: 1412.6 | I99: 1898.91 | J99: 2860.17 | K99: 2989.82 | L99: 3086.44 | M99: 3307.34 | N99: 3295.17 | O99: 3432.71 | P99: 3454.66 | Q99: 3427.17 | R99: 3260.41 | S99: 3143.01 | T99: 3081.92 | U99: 2999.99 | V99: 2910.27 | W99: 2989.6 | X99: 2701.07 | Y99: 2233.56
A100: - услуги по передаче | B100: =$B$15 -> 80.58 | C100: =$B100 -> 80.58 | D100: =$B100 -> 80.58 | E100: =$B100 -> 80.58 | F100: =$B100 -> 80.58 | G100: =$B100 -> 80.58 | H100: =$B100 -> 80.58 | I100: =$B100 -> 80.58 | J100: =$B100 -> 80.58 | ... Y100: =$B100 -> 80.58
A101: - сбытовая надбавка ГП | B101: 75.85 | C101: 75.85 | D101: 75.85 | E101: 75.85 | F101: 75.85 | G101: 75.85 | H101: 75.85 | I101: 75.85 | J101: 75.85 | K101: 75.85 | L101: 75.85 | M101: 75.85 | N101: 75.85 | O101: 75.85 | P101: 75.85 | Q101: 75.85 | R101: 75.85 | S101: 75.85 | T101: 75.85 | U101: 75.85 | V101: 75.85 | W101: 75.85 | X101: 75.85 | Y101: 75.85
A102: - инфраструктурные платежи | B102: =$B$17 -> 5.35 | C102: =$B102 -> 5.35 | D102: =$B102 -> 5.35 | E102: =$B102 -> 5.35 | F102: =$B102 -> 5.35 | G102: =$B102 -> 5.35 | H102: =$B102 -> 5.35 | I102: =$B102 -> 5.35 | J102: =$B102 -> 5.35 | ... Y102: =$B102 -> 5.35
A103: 19 | B103: =B104+B105+B106+B107 -> 1983.76 | C103: =C104+C105+C106+C107 -> 1728.32 | D103: =D104+D105+D106+D107 -> 1576.67 | E103: =E104+E105+E106+E107 -> 1368.89 | F103: =F104+F105+F106+F107 -> 1292.4 | G103: =G104+G105+G106+G107 -> 1379.37 | H103: =H104+H105+H106+H107 -> 1389.88 | I103: =I104+I105+I106+I107 -> 1622.16 | ... Y103: =Y104+Y105+Y106+Y107 -> 2329.01
A104: - средневзв. стоимость э/э (м) | B104: 1821.98 | C104: 1566.54 | D104: 1414.89 | E104: 1207.11 | F104: 1130.62 | G104: 1217.59 | H104: 1228.1 | I104: 1460.38 | J104: 2307.57 | K104: 2763.29 | L104: 2840.74 | M104: 2852.42 | N104: 2892.84 | O104: 2901.08 | P104: 2908.51 | Q104: 2899.29 | R104: 2920.11 | S104: 2886.88 | T104: 2864.08 | U104: 2834.44 | V104: 2820.7 | W104: 2800.72 | X104: 2645.04 | Y104: 2167.23
...

Sheet О_июль 1 цк
A2: Предельные уровни нерегулируемых цен на электрическую энергию (мощность), поставляемую АО "Мосэнергосбыт" потребителям
A3: с максимальной мощностью энергопринимающих устройств не менее 10 МВт
A4: Московская область
A5: ='М_июль 1 цк'!A5:F5 -> Июль 2025 г.
A7: I. Первая ценовая категория для объемов покупки электрической энергии (мощности), учет которых осуществляется в целом за расчетный период
A9: 1. Предельный уровень нерегулируемых цен, руб./МВт∙ч без НДС
A11: № п/п | B11: Группа потребителей | C11: Уровень напряжения
C12: ВН | D12: СН I | E12: СН II | F12: НН
A13: 1.1. | B13: Прочие потребители
A14: 1.1.1. | B14: Иные прочие потребители | C14: =C15+C16+C17+C19+C18 -> 5638.34 | D14: =D15+D16+D17+D19+D18 -> 6491.32 | E14: =E15+E16+E17+E19+E18 -> 7021.03 | F14: =F15+F16+F17+F19+F18 -> 7975.53
B15: - средневзв. стоимость э/э (м) | C15: 3602.47 | D15: =C15 -> 3602.47 | E15: =C15 -> 3602.47 | F15: =C15 -> 3602.47
B16: - услуги по передаче | C16: 1922.63 | D16: 2775.61 | E16: 3305.32 | F16: 4259.82
B17: - сбытовая надбавка ГП | C17: 106.82 | D17: =C17 -> 106.82 | E17: =C17 -> 106.82 | F17: =C17 -> 106.82
B18: - плата за услуги по управлению изменением режима потребления электрической энергии | C18: 1.07 | D18: 1.07 | E18: 1.07 | F18: 1.07
B19: - инфраструктурные платежи | C19: 5.35 | D19: =C19 -> 5.35 | E19: =C19 -> 5.35 | F19: =C19 -> 5.35
A20: 1.1.2. | B20: Потребители, рассчитывающиеся по договорам купли-продажи | C20: =C21+C22+C24+C23 -> 3715.71 | D20: =D21+D22+D24+D23 -> 3715.71 | E20: =E21+E22+E24+E23 -> 3715.71 | F20: =F21+F22+F24+F23 -> 3715.71
B21: - средневзв. стоимость э/э (м) | C21: =C15 -> 3602.47 | D21: =C21 -> 3602.47 | E21: =C21 -> 3602.47 | F21: =C21 -> 3602.47
B22: - сбытовая надбавка ГП | C22: =C17 -> 106.82 | D22: =C22 -> 106.82 | E22: =C22 -> 106.82 | F22: =C22 -> 106.82
B23: - плата за услуги по управлению изменением режима потребления электрической энергии | C23: 1.07 | D23: 1.07 | E23: 1.07 | F23: 1.07
B24: - инфраструктурные платежи | C24: =C19 -> 5.35 | D24: =C24 -> 5.35 | E24: =C24 -> 5.35 | F24: =C24 -> 5.35
A27: 2. | B27: Средневзвешенная нерегулируемая цена на электрическую энергию (мощность), используемая для расчета предельного уровня нерегулируемых цен для первой ценовой категории, без НДС, руб./МВт∙ч | E27: ='М_июль 1 цк'!E27 -> 3602.47
A28: 3. | B28: Составляющие расчета средневзвешенной нерегулируемой цены на электрическую энергию (мощность), используемой для расчета предельного уровня нерегулируемых цен для первой ценовой категории:
A29: а) | B29: средневзвешенная нерегулируемая цена на электрическую энергию на оптовом рынке, руб./МВт∙ч | E29: ='М_июль 1 цк'!E29 -> 2324,93
A30: б) | B30: средневзвешенная нерегулируемая цена на мощность на оптовом рынке, руб./МВт | E30: ='М_июль 1 цк'!E30 -> 937404,45
A31: в) | B31: коэффициент оплаты мощности потребителями (покупателями), осуществляющими расчеты по первой ценовой категории, 1/час | E31: ='М_июль 1 цк'!E31 -> 0.0013628526
A32: г) | B32: объем фактического пикового потребления гарантирующего поставщика на оптовом рынке, МВт | E32: ='М_июль 1 цк'!E32 -> 12653.047
A33: д) | B33: величина мощности, соответствующей покупке электрической энергии гарантирующим поставщиком у производителей электрической энергии (мощности) на розничных рынках, МВт | E33: ='М_июль 1 цк'!E33 -> 8.244
A34: е) | B34: сумма величин мощности, оплачиваемой на розничном рынке потребителями (покупателями), осуществляющими расчеты по второй - шестой ценовым категориям, МВт | E34: ='М_июль 1 цк'!E34 -> 5425.2309
B35: в том числе:
B36: – по второй ценовой категории, МВт | E36: ='М_июль 1 цк'!E36 -> 31.37
B37: – по третьей ценовой категории, МВт | E37: ='М_июль 1 цк'!E37 -> 3055.548
B38: – по четвертой ценовой категории, МВт | E38: ='М_июль 1 цк'!E38 -> 1954.9029
B39: – по пятой ценовой категории, МВт | E39: ='М_июль 1 цк'!E39 -> 24.143838
B40: – по шестой ценовой категории, МВт | E40: ='М_июль 1 цк'!E40 -> 359.26613
A41: ж) | B41: объем потребления мощности населением и приравненными к нему категориями потребителей, МВт | E41: ='М_июль 1 цк'!E41 -> 3942.223
A42: з) | B42: объем потребления электрической энергии потребителями (покупателями), осуществляющими расчеты по второй ценовой категории, МВт∙ч | E42: ='М_июль 1 цк'!E42 -> 13059.656
B43: в том числе:
B44: для трех зон суток, МВт∙ч | E44: ='М_июль 1 цк'!E44 -> 10179.74
B45: – по ночной зоне суток, МВт∙ч | E45: ='М_июль 1 цк'!E45 -> 3314.096
B46: – по полупиковой зоне суток, МВт∙ч | E46: ='М_июль 1 цк'!E46 -> 4121.4071
B47: – по пиковой зоне суток, МВт∙ч | E47: ='М_июль 1 цк'!E47 -> 2744.2369
B48: для двух зон суток, МВт∙ч | E48: ='М_июль 1 цк'!E48 -> 2879.9156
B49: – по ночной зоне суток, МВт∙ч | E49: ='М_июль 1 цк'!E49 -> 1178.6676
B50: – по пиковой зоне суток, МВт∙ч | E50: ='М_июль 1 цк'!E50 -> 1701.248
A51: и) | B51: фактический объем потребления электрической энергии гарантирующим поставщиком на оптовом рынке, МВт∙ч | E51: ='М_июль 1 цк'!E51 -> 7890017.1
A52: к) | B52: совокупный объем покупки электрической энергии гарантирующим поставщиком у производителей электрической энергии (мощности) на розничных рынках, МВт∙ч | E52: ='М_июль 1 цк'!E52 -> 4273.582
B53: объем покупки электрической энергии гарантирующим поставщиком у собственников и иных законных владельцев объектов микрогенерации, МВт∙ч * | E53: ='М_июль 1 цк'!E53 -> 44.239
A54: л) | B54: сумма объемов потребления электрической энергии потребителями (покупателями), осуществляющими расчеты по второй - шестой ценовым категориям, МВт∙ч | E54: ='М_июль 1 цк'!E54 -> 3379781.4
B55: в том числе:
B56: – по второй ценовой категории, МВт∙ч | E56: ='М_июль 1 цк'!E56 -> 13059.656
B57: – по третьей ценовой категории, МВт∙ч | E57: ='М_июль 1 цк'!E57 -> 1705602.8
B58: – по четвертой ценовой категории, МВт∙ч | E58: ='М_июль 1 цк'!E58 -> 1375077.5
B59: – по пятой ценовой категории, МВт∙ч | E59: ='М_июль 1 цк'!E59 -> 11664.351
B60: – по шестой ценовой категории, МВт∙ч | E60: ='М_июль 1 цк'!E60 -> 274377.05
A61: м) | B61: объем потребления электрической энергии населением и приравненными к нему категориями потребителей, МВт∙ч | E61: ='М_июль 1 цк'!E61 -> 2097639.6
A62: н) | B62: величина изменения средневзвешенной нерегулируемой цены на электрическую энергию (мощность), связанная с учетом данных за предыдущие расчетные периоды **, руб./МВт∙ч | E62: ='М_июль 1 цк'!E62 -> 0
A63: 44409
A64: 2. | B64: средневзвешенная нерегулируемая цена на электрическую энергию (мощность) за предыдущий расчетный период (август 2021 г.), определяемая с учетом данных, известных в расчетный период (июль 2025 г.), без НДС, руб./МВт∙ч | E64: 2790.14
A65: 3. | B65: Составляющие расчета средневзвешенной нерегулируемой цены на электрическую энергию (мощность), используемой для расчета предельного уровня нерегулируемых цен для первой ценовой категории:
A66: а) | B66: средневзвешенная нерегулируемая цена на электрическую энергию на оптовом рынке, руб./МВт∙ч | E66: 1694.92
A67: б) | B67: средневзвешенная нерегулируемая цена на мощность на оптовом рынке, руб./МВт | E67: 806602,09
A68: в) | B68: коэффициент оплаты мощности потребителями (покупателями), осуществляющими расчеты по первой ценовой категории, 1/час | E68: 0.0013553174
A69: г) | B69: объем фактического пикового потребления гарантирующего поставщика на оптовом рынке, МВт | E69: 10612.696
A70: д) | B70: величина мощности, соответствующей покупке электрической энергии гарантирующим поставщиком у производителей электрической энергии (мощности) на розничных рынках, МВт | E70: 4.476
A71: е) | B71: сумма величин мощности, оплачиваемой на розничном рынке потребителями (покупателями), осуществляющими расчеты по второй - шестой ценовым категориям, МВт | E71: 4485.8591
B72: в том числе:
B73: – по второй ценовой категории, МВт | E73: 34.433
B74: – по третьей ценовой категории, МВт | E74: 2569.4251
B75: – по четвертой ценовой категории, МВт | E75: 1560.442
B76: – по пятой ценовой категории, МВт | E76: 25.231
B77: – по шестой ценовой категории, МВт | E77: 296.328
A78: ж) | B78: объем потребления мощности населением и приравненными к нему категориями потребителей, МВт | E78: 3438.978
A79: з) | B79: объем потребления электрической энергии потребителями (покупателями), осуществляющими расчеты по второй ценовой категории, МВт∙ч | E79: 15426.098
B80: в том числе:
B81: для трех зон суток, МВт∙ч | E81: 13167.436
B82: – по ночной зоне суток, МВт∙ч | E82: 4664.081
B83: – по полупиковой зоне суток, МВт∙ч | E83: 4980.798
B84: – по пиковой зоне суток, МВт∙ч | E84: 3522.557
B85: для двух зон суток, МВт∙ч | E85: 2258.662
B86: – по ночной зоне суток, МВт∙ч | E86: 815.592
B87: – по пиковой зоне суток, МВт∙ч | E87: 1443.07
A88: и) | B88: фактический объем потребления электрической энергии гарантирующим поставщиком на оптовом рынке, МВт∙ч | E88: 6622343.5
A89: к) | B89: объем покупки электрической энергии гарантирующим поставщиком у производителей электрической энергии (мощности) на розничных рынках, МВт∙ч | E89: 2580.69
B90: в том числе: – объем покупки электрической энергии у собственников и иных законных владельцев объектов микрогенерации | E90: 0.19
A91: л) | B91: сумма объемов потребления электрической энергии потребителями (покупателями), осуществляющими расчеты по второй - шестой ценовым категориям, МВт∙ч | E91: 2797831.4
B92: в том числе:
B93: – по второй ценовой категории, МВт∙ч | E93: 15426.098
B94: – по третьей ценовой категории, МВт∙ч | E94: 1498035
B95: – по четвертой ценовой категории, МВт∙ч | E95: 1052136.8
B96: – по пятой ценовой категории, МВт∙ч | E96: 14445.146
B97: – по шестой ценовой категории, МВт∙ч | E97: 217788.4
A98: м) | B98: объем потребления электрической энергии населением и приравненными к нему категориями потребителей, МВт∙ч | E98: 1840595.2
A99: 44927
A100: 2. | B100: средневзвешенная нерегулируемая цена на электрическую энергию (мощность) за предыдущий расчетный период (январь 2023 г.), определяемая с учетом данных, известных в расчетный период (июль 2025 г.), без НДС, руб./МВт∙ч | E100: 2735.71
A101: 3. | B101: Составляющие расчета средневзвешенной нерегулируемой цены на электрическую энергию (мощность), используемой для расчета предельного уровня нерегулируемых цен для первой ценовой категории:
A102: а) | B102: средневзвешенная нерегулируемая цена на электрическую энергию на оптовом рынке, руб./МВт∙ч | E102: 1583,59
A103: б) | B103: средневзвешенная нерегулируемая цена на мощность на оптовом рынке, руб./МВт | E103: 854060,08
A104: в) | B104: коэффициент оплаты мощности потребителями (покупателями), осуществляющими расчеты по первой ценовой категории, 1/час | E104: 0.0013489874
A105: г) | B105: объем фактического пикового потребления гарантирующего поставщика на оптовом рынке, МВт | E105: 14776.262
A106: д) | B106: величина мощности, соответствующей покупке электрической энергии гарантирующим поставщиком у производителей электрической энергии (мощности) на розничных рынках, МВт | E106: 8.943
...

Sheet О_июль 2 цк
A2: ='О_июль 1 цк'!A2 -> Предельные уровни нерегулируемых цен на электрическую энергию (мощность), поставляемую АО "Мосэнергосбыт" потребителям
A3: ='О_июль 1 цк'!A3 -> с максимальной мощностью энергопринимающих устройств не менее 10 МВт
A4: ='О_июль 1 цк'!A4 -> Московская область
A5: ='О_июль 1 цк'!A5 -> Июль 2025 г.
A7: II. Вторая ценовая категория для объемов покупки электрической энергии (мощности), учет которых осуществляется по зонам суток расчетного периода
A9: 1. Предельный уровень нерегулируемых цен для трех зон суток, руб./МВт∙ч без НДС
A11: № п/п | B11: Группа потребителей | C11: Уровень напряжения
C12: ВН | D12: СН I | E12: СН II | F12: НН
A13: 1.1. | B13: Прочие потребители
A14: 1.1.1. | B14: Иные прочие потребители
A15: 1.1.1.1. | B15: ночная зона | C15: =C16+C17+C18+C20+C19 -> 3241.58 | D15: =D16+D17+D18+D20+D19 -> 4094.56 | E15: =E16+E17+E18+E20+E19 -> 4624.27 | F15: =F16+F17+F18+F20+F19 -> 5578.77
B16: - средневзв. стоимость э/э (м) | C16: 1205.71 | D16: =C16 -> 1205.71 | E16: =C16 -> 1205.71 | F16: =C16 -> 1205.71
B17: - услуги по передаче | C17: 1922.63 | D17: 2775.61 | E17: 3305.32 | F17: 4259.82
B18: - сбытовая надбавка ГП | C18: 106.82 | D18: =C18 -> 106.82 | E18: =C18 -> 106.82 | F18: =C18 -> 106.82
B19: - плата за услуги по управлению изменением режима потребления электрической энергии | C19: 1.07 | D19: 1.07 | E19: 1.07 | F19: 1.07
B20: - инфраструктурные платежи | C20: 5.35 | D20: =C20 -> 5.35 | E20: =C20 -> 5.35 | F20: =C20 -> 5.35
A21: 1.1.1.2. | B21: полупиковая зона | C21: =C22+C23+C24+C26+C25 -> 6157.81 | D21: =D22+D23+D24+D26+D25 -> 7010.79 | E21: =E22+E23+E24+E26+E25 -> 7540.5 | F21: =F22+F23+F24+F26+F25 -> 8495
B22: - средневзв. стоимость э/э (м) | C22: 4121.94 | D22: =C22 -> 4121.94 | E22: =C22 -> 4121.94 | F22: =C22 -> 4121.94
B23: - услуги по передаче | C23: =C17 -> 1922.63 | D23: =D17 -> 2775.61 | E23: =E17 -> 3305.32 | F23: =F17 -> 4259.82
B24: - сбытовая надбавка ГП | C24: 106.82 | D24: =C24 -> 106.82 | E24: =C24 -> 106.82 | F24: =C24 -> 106.82
B25: - плата за услуги по управлению изменением режима потребления электрической энергии | C25: 1.07 | D25: 1.07 | E25: 1.07 | F25: 1.07
B26: - инфраструктурные платежи | C26: =C20 -> 5.35 | D26: =C26 -> 5.35 | E26: =C26 -> 5.35 | F26: =C26 -> 5.35
A27: 1.1.1.3. | B27: пиковая зона | C27: =C28+C29+C30+C32+C31 -> 11323.21 | D27: =D28+D29+D30+D32+D31 -> 12176.19 | E27: =E28+E29+E30+E32+E31 -> 12705.9 | F27: =F28+F29+F30+F32+F31 -> 13660.4
B28: - средневзв. стоимость э/э (м) | C28: 9287.34 | D28: =C28 -> 9287.34 | E28: =C28 -> 9287.34 | F28: =C28 -> 9287.34
B29: - услуги по передаче | C29: =C17 -> 1922.63 | D29: =D17 -> 2775.61 | E29: =E17 -> 3305.32 | F29: =F17 -> 4259.82
B30: - сбытовая надбавка ГП | C30: 106.82 | D30: =C30 -> 106.82 | E30: =C30 -> 106.82 | F30: =C30 -> 106.82
B31: - плата за услуги по управлению изменением режима потребления электрической энергии | C31: 1.07 | D31: 1.07 | E31: 1.07 | F31: 1.07
B32: - инфраструктурные платежи | C32: =C20 -> 5.35 | D32: =C32 -> 5.35 | E32: =C32 -> 5.35 | F32: =C32 -> 5.35
A33: 1.1.2. | B33: Потребители, рассчитывающиеся по договорам купли-продажи
A34: 1.1.2.1. | B34: ночная зона | C34: =C35+C36+C38+C37 -> 1318.95 | D34: =D35+D36+D38+D37 -> 1318.95 | E34: =E35+E36+E38+E37 -> 1318.95 | F34: =F35+F36+F38+F37 -> 1318.95
B35: - средневзв. стоимость э/э (м) | C35: =C16 -> 1205.71 | D35: =C35 -> 1205.71 | E35: =C35 -> 1205.71 | F35: =C35 -> 1205.71
B36: - сбытовая надбавка ГП | C36: =C18 -> 106.82 | D36: =C36 -> 106.82 | E36: =C36 -> 106.82 | F36: =C36 -> 106.82
B37: - плата за услуги по управлению изменением режима потребления электрической энергии | C37: 1.07 | D37: 1.07 | E37: 1.07 | F37: 1.07
B38: - инфраструктурные платежи | C38: =C20 -> 5.35 | D38: =C38 -> 5.35 | E38: =C38 -> 5.35 | F38: =C38 -> 5.35
A39: 1.1.2.2. | B39: полупиковая зона | C39: =C40+C41+C43+C42 -> 4235.18 | D39: =D40+D41+D43+D42 -> 4235.18 | E39: =E40+E41+E43+E42 -> 4235.18 | F39: =F40+F41+F43+F42 -> 4235.18
B40: - средневзв. стоимость э/э (м) | C40: =C22 -> 4121.94 | D40: =C40 -> 4121.94 | E40: =C40 -> 4121.94 | F40: =C40 -> 4121.94
B41: - сбытовая надбавка ГП | C41: =C24 -> 106.82 | D41: =C41 -> 106.82 | E41: =C41 -> 106.82 | F41: =C41 -> 106.82
B42: - плата за услуги по управлению изменением режима потребления электрической энергии | C42: 1.07 | D42: 1.07 | E42: 1.07 | F42: 1.07
B43: - инфраструктурные платежи | C43: =C38 -> 5.35 | D43: =C43 -> 5.35 | E43: =C43 -> 5.35 | F43: =C43 -> 5.35
A44: 1.1.2.3. | B44: пиковая зона | C44: =C45+C46+C48+C47 -> 9400.58 | D44: =D45+D46+D48+D47 -> 9400.58 | E44: =E45+E46+E48+E47 -> 9400.58 | F44: =F45+F46+F48+F47 -> 9400.58
B45: - средневзв. стоимость э/э (м) | C45: =C28 -> 9287.34 | D45: =C45 -> 9287.34 | E45: =C45 -> 9287.34 | F45: =C45 -> 9287.34
B46: - сбытовая надбавка ГП | C46: =C30 -> 106.82 | D46: =C46 -> 106.82 | E46: =C46 -> 106.82 | F46: =C46 -> 106.82
B47: - плата за услуги по управлению изменением режима потребления электрической энергии | C47: 1.07 | D47: 1.07 | E47: 1.07 | F47: 1.07
B48: - инфраструктурные платежи | C48: =C38 -> 5.35 | D48: =C48 -> 5.35 | E48: =C48 -> 5.35 | F48: =C48 -> 5.35
A50: 2. Предельный уровень нерегулируемых цен для двух зон суток, руб./МВт∙ч без НДС
A52: № п/п | B52: Группа потребителей | C52: Уровень напряжения
C53: ВН | D53: СН I | E53: СН II | F53: НН
A54: 2.1. | B54: Прочие потребители
A55: 2.1.1. | B55: Иные прочие потребители
A56: 2.1.1.1. | B56: ночная зона | C56: =C57+C58+C59+C61+C60 -> 3241.58 | D56: =D57+D58+D59+D61+D60 -> 4094.56 | E56: =E57+E58+E59+E61+E60 -> 4624.27 | F56: =F57+F58+F59+F61+F60 -> 5578.77
B57: - средневзв. стоимость э/э (м) | C57: 1205.71 | D57: =C57 -> 1205.71 | E57: =C57 -> 1205.71 | F57: =C57 -> 1205.71
B58: - услуги по передаче | C58: =C17 -> 1922.63 | D58: =D17 -> 2775.61 | E58: =E17 -> 3305.32 | F58: =F17 -> 4259.82
B59: - сбытовая надбавка ГП | C59: 106.82 | D59: =C59 -> 106.82 | E59: =C59 -> 106.82 | F59: =C59 -> 106.82
B60: - плата за услуги по управлению изменением режима потребления электрической энергии | C60: 1.07 | D60: 1.07 | E60: 1.07 | F60: 1.07
B61: - инфраструктурные платежи | C61: =C20 -> 5.35 | D61: =C61 -> 5.35 | E61: =C61 -> 5.35 | F61: =C61 -> 5.35
A62: 2.1.1.2. | B62: дневная зона | C62: =C63+C64+C65+C67+C66 -> 8326.93 | D62: =D63+D64+D65+D67+D66 -> 9179.91 | E62: =E63+E64+E65+E67+E66 -> 9709.62 | F62: =F63+F64+F65+F67+F66 -> 10664.12
B63: - средневзв. стоимость э/э (м) | C63: 6291.06 | D63: =C63 -> 6291.06 | E63: =C63 -> 6291.06 | F63: =C63 -> 6291.06
B64: - услуги по передаче | C64: =C17 -> 1922.63 | D64: =D17 -> 2775.61 | E64: =E17 -> 3305.32 | F64: =F17 -> 4259.82
B65: - сбытовая надбавка ГП | C65: 106.82 | D65: =C65 -> 106.82 | E65: =C65 -> 106.82 | F65: =C65 -> 106.82
B66: - плата за услуги по управлению изменением режима потребления электрической энергии | C66: 1.07 | D66: 1.07 | E66: 1.07 | F66: 1.07
B67: - инфраструктурные платежи | C67: =C20 -> 5.35 | D67: =C67 -> 5.35 | E67: =C67 -> 5.35 | F67: =C67 -> 5.35
A68: 2.1.2. | B68: Потребители, рассчитывающиеся по договорам купли-продажи
A69: 2.1.2.1. | B69: ночная зона | C69: =C70+C71+C73+C72 -> 1318.95 | D69: =D70+D71+D73+D72 -> 1318.95 | E69: =E70+E71+E73+E72 -> 1318.95 | F69: =F70+F71+F73+F72 -> 1318.95
B70: - средневзв. стоимость э/э (м) | C70: 1205.71 | D70: =C70 -> 1205.71 | E70: =C70 -> 1205.71 | F70: =C70 -> 1205.71
B71: - сбытовая надбавка ГП | C71: 106.82 | D71: =C71 -> 106.82 | E71: =C71 -> 106.82 | F71: =C71 -> 106.82
B72: - плата за услуги по управлению изменением режима потребления электрической энергии | C72: 1.07 | D72: 1.07 | E72: 1.07 | F72: 1.07
B73: - инфраструктурные платежи | C73: 5.35 | D73: =C73 -> 5.35 | E73: =C73 -> 5.35 | F73: =C73 -> 5.35
A74: 2.1.2.2. | B74: дневная зона | C74: =C75+C76+C78+C77 -> 6404.3 | D74: =D75+D76+D78+D77 -> 6404.3 | E74: =E75+E76+E78+E77 -> 6404.3 | F74: =F75+F76+F78+F77 -> 6404.3
B75: - средневзв. стоимость э/э (м) | C75: 6291.06 | D75: =C75 -> 6291.06 | E75: =C75 -> 6291.06 | F75: =C75 -> 6291.06
B76: - сбытовая надбавка ГП | C76: 106.82 | D76: =C76 -> 106.82 | E76: =C76 -> 106.82 | F76: =C76 -> 106.82
B77: - плата за услуги по управлению изменением режима потребления электрической энергии | C77: 1.07 | D77: 1.07 | E77: 1.07 | F77: 1.07
B78: - инфраструктурные платежи | C78: =C73 -> 5.35 | D78: =C78 -> 5.35 | E78: =C78 -> 5.35 | F78: =C78 -> 5.35

Sheet О_июль 3 цк
A2: ='О_июль 1 цк'!A2:F2 -> Предельные уровни нерегулируемых цен на электрическую энергию (мощность), поставляемую АО "Мосэнергосбыт" потребителям
A3: ='О_июль 1 цк'!A3:F3 -> с максимальной мощностью энергопринимающих устройств не менее 10 МВт
A4: ='О_июль 1 цк'!A4:F4 -> Московская область
A5: ='О_июль 1 цк'!A5:F5 -> Июль 2025 г.
A7: III. Третья ценовая категория для объемов покупки электрической энергии (мощности), в отношении которых за расчетный период осуществляется почасовой учет, но не осуществляется почасовое планирование, а стоимость услуг по передаче электрической энергии определяется по тарифу на услуги по передаче электрической энергии в одноставочном выражении
A9: 1.1. Ставка за электрическую энергию предельного уровня нерегулируемых цен для абонентов группы "Иные прочие потребители", рублей/МВт∙ч без НДС
A11: Дата | B11: Ставка для фактических почасовых объемов покупки электрической энергии, отпущенных на уровне напряжения ВН
B12: 0:00-1:00 | C12: 1:00-2:00 | D12: 2:00-3:00 | E12: 3:00-4:00 | F12: 4:00-5:00 | G12: 5:00-6:00 | H12: 6:00-7:00 | I12: 7:00-8:00 | J12: 8:00-9:00 | K12: 9:00-10:00 | L12: 10:00-11:00 | M12: 11:00-12:00 | N12: 12:00-13:00 | O12: 13:00-14:00 | P12: 14:00-15:00 | Q12: 15:00-16:00 | R12: 16:00-17:00 | S12: 17:00-18:00 | T12: 18:00-19:00 | U12: 19:00-20:00 | V12: 20:00-21:00 | W12: 21:00-22:00 | X12: 22:00-23:00 | Y12: 23:00-0:00
A13: 1 | B13: =B14+B15+B16+B17 -> 3678.43 | C13: =C14+C15+C16+C17 -> 3409.89 | D13: =D14+D15+D16+D17 -> 3294.81 | E13: =E14+E15+E16+E17 -> 3194.01 | F13: =F14+F15+F16+F17 -> 3216.08 | G13: =G14+G15+G16+G17 -> 3501.37 | H13: =H14+H15+H16+H17 -> 3626.6 | I13: =I14+I15+I16+I17 -> 4078.46 | ... Y13: =Y14+Y15+Y16+Y17 -> 4100.57
A14: - средневзв. стоимость э/э (м) | B14: 1643.63 | C14: 1375.09 | D14: 1260.01 | E14: 1159.21 | F14: 1181.28 | G14: 1466.57 | H14: 1591.8 | I14: 2043.66 | J14: 2544.33 | K14: 2682.61 | L14: 2744.97 | M14: 2743.85 | N14: 2729.42 | O14: 2739.69 | P14: 2768.75 | Q14: 2783.49 | R14: 2762.56 | S14: 2768.68 | T14: 2746.78 | U14: 2697.44 | V14: 2663.63 | W14: 2636.06 | X14: 2326.79 | Y14: 2065.77
A15: - услуги по передаче | B15: 1922.63 | C15: =$B15 -> 1922.63 | D15: =$B15 -> 1922.63 | E15: =$B15 -> 1922.63 | F15: =$B15 -> 1922.63 | G15: =$B15 -> 1922.63 | H15: =$B15 -> 1922.63 | I15: =$B15 -> 1922.63 | J15: =$B15 -> 1922.63 | ... Y15: =$B15 -> 1922.63
A16: - сбытовая надбавка ГП | B16: 106.82 | C16: 106.82 | D16: 106.82 | E16: 106.82 | F16: 106.82 | G16: 106.82 | H16: 106.82 | I16: 106.82 | J16: 106.82 | K16: 106.82 | L16: 106.82 | M16: 106.82 | N16: 106.82 | O16: 106.82 | P16: 106.82 | Q16: 106.82 | R16: 106.82 | S16: 106.82 | T16: 106.82 | U16: 106.82 | V16: 106.82 | W16: 106.82 | X16: 106.82 | Y16: 106.82
A17: - инфраструктурные платежи | B17: 5.35 | C17: =$B17 -> 5.35 | D17: =$B17 -> 5.35 | E17: =$B17 -> 5.35 | F17: =$B17 -> 5.35 | G17: =$B17 -> 5.35 | H17: =$B17 -> 5.35 | I17: =$B17 -> 5.35 | J17: =$B17 -> 5.35 | ... Y17: =$B17 -> 5.35
A18: 2 | B18: =B19+B20+B21+B22 -> 3723.78 | C18: =C19+C20+C21+C22 -> 3563.8 | D18: =D19+D20+D21+D22 -> 3480.15 | E18: =E19+E20+E21+E22 -> 3264.65 | F18: =F19+F20+F21+F22 -> 3358.96 | G18: =G19+G20+G21+G22 -> 3560.01 | H18: =H19+H20+H21+H22 -> 3642.11 | I18: =I19+I20+I21+I22 -> 4129.14 | ... Y18: =Y19+Y20+Y21+Y22 -> 4035.18
A19: - средневзв. стоимость э/э (м) | B19: 1688.98 | C19: 1529 | D19: 1445.35 | E19: 1229.85 | F19: 1324.16 | G19: 1525.21 | H19: 1607.31 | I19: 2094.34 | J19: 2706.96 | K19: 2804.21 | L19: 2837.46 | M19: 2828.28 | N19: 2843.1 | O19: 2873.1 | P19: 2874.34 | Q19: 2863.78 | R19: 2837.34 | S19: 2817.79 | T19: 2806.9 | U19: 2778.96 | V19: 2748.46 | W19: 2727.03 | X19: 2445.18 | Y19: 2000.38
A20: - услуги по передаче | B20: =$B$15 -> 1922.63 | C20: =$B20 -> 1922.63 | D20: =$B20 -> 1922.63 | E20: =$B20 -> 1922.63 | F20: =$B20 -> 1922.63 | G20: =$B20 -> 1922.63 | H20: =$B20 -> 1922.63 | I20: =$B20 -> 1922.63 | J20: =$B20 -> 1922.63 | ... Y20: =$B20 -> 1922.63
A21: - сбытовая надбавка ГП | B21: 106.82 | C21: 106.82 | D21: 106.82 | E21: 106.82 | F21: 106.82 | G21: 106.82 | H21: 106.82 | I21: 106.82 | J21: 106.82 | K21: 106.82 | L21: 106.82 | M21: 106.82 | N21: 106.82 | O21: 106.82 | P21: 106.82 | Q21: 106.82 | R21: 106.82 | S21: 106.82 | T21: 106.82 | U21: 106.82 | V21: 106.82 | W21: 106.82 | X21: 106.82 | Y21: 106.82
A22: - инфраструктурные платежи | B22: =$B$17 -> 5.35 | C22: =$B22 -> 5.35 | D22: =$B22 -> 5.35 | E22: =$B22 -> 5.35 | F22: =$B22 -> 5.35 | G22: =$B22 -> 5.35 | H22: =$B22 -> 5.35 | I22: =$B22 -> 5.35 | J22: =$B22 -> 5.35 | ... Y22: =$B22 -> 5.35
A23: 3 | B23: =B24+B25+B26+B27 -> 3605.7 | C23: =C24+C25+C26+C27 -> 3447.51 | D23: =D24+D25+D26+D27 -> 3324.32 | E23: =E24+E25+E26+E27 -> 3208.62 | F23: =F24+F25+F26+F27 -> 3220.23 | G23: =G24+G25+G26+G27 -> 3445.69 | H23: =H24+H25+H26+H27 -> 3589.65 | I23: =I24+I25+I26+I27 -> 4043.84 | ... Y23: =Y24+Y25+Y26+Y27 -> 4023.46
A24: - средневзв. стоимость э/э (м) | B24: 1570.9 | C24: 1412.71 | D24: 1289.52 | E24: 1173.82 | F24: 1185.43 | G24: 1410.89 | H24: 1554.85 | I24: 2009.04 | J24: 2559.55 | K24: 2598.88 | L24: 2641.18 | M24: 2673.9 | N24: 2667.07 | O24: 2651.63 | P24: 2872.93 | Q24: 2941.52 | R24: 2884.71 | S24: 2688.33 | T24: 2757.86 | U24: 2651.34 | V24: 2696.89 | W24: 2677.99 | X24: 2417.66 | Y24: 1988.66
A25: - услуги по передаче | B25: =$B$15 -> 1922.63 | C25: =$B25 -> 1922.63 | D25: =$B25 -> 1922.63 | E25: =$B25 -> 1922.63 | F25: =$B25 -> 1922.63 | G25: =$B25 -> 1922.63 | H25: =$B25 -> 1922.63 | I25: =$B25 -> 1922.63 | J25: =$B25 -> 1922.63 | ... Y25: =$B25 -> 1922.63
A26: - сбытовая надбавка ГП | B26: 106.82 | C26: 106.82 | D26: 106.82 | E26: 106.82 | F26: 106.82 | G26: 106.82 | H26: 106.82 | I26: 106.82 | J26: 106.82 | K26: 106.82 | L26: 106.82 | M26: 106.82 | N26: 106.82 | O26: 106.82 | P26: 106.82 | Q26: 106.82 | R26: 106.82 | S26: 106.82 | T26: 106.82 | U26: 106.82 | V26: 106.82 | W26: 106.82 | X26: 106.82 | Y26: 106.82
A27: - инфраструктурные платежи | B27: =$B$17 -> 5.35 | C27: =$B27 -> 5.35 | D27: =$B27 -> 5.35 | E27: =$B27 -> 5.35 | F27: =$B27 -> 5.35 | G27: =$B27 -> 5.35 | H27: =$B27 -> 5.35 | I27: =$B27 -> 5.35 | J27: =$B27 -> 5.35 | ... Y27: =$B27 -> 5.35
A28: 4 | B28: =B29+B30+B31+B32 -> 3696.32 | C28: =C29+C30+C31+C32 -> 3476.29 | D28: =D29+D30+D31+D32 -> 3330.84 | E28: =E29+E30+E31+E32 -> 3201.56 | F28: =F29+F30+F31+F32 -> 3218.05 | G28: =G29+G30+G31+G32 -> 3450.6 | H28: =H29+H30+H31+H32 -> 3602.68 | I28: =I29+I30+I31+I32 -> 4065.3 | ... Y28: =Y29+Y30+Y31+Y32 -> 4080.3
A29: - средневзв. стоимость э/э (м) | B29: 1661.52 | C29: 1441.49 | D29: 1296.04 | E29: 1166.76 | F29: 1183.25 | G29: 1415.8 | H29: 1567.88 | I29: 2030.5 | J29: 2568.65 | K29: 2687.94 | L29: 2641.38 | M29: 2639.93 | N29: 2707.75 | O29: 2639.25 | P29: 2784.72 | Q29: 2836.9 | R29: 2818.07 | S29: 2794.9 | T29: 2781.67 | U29: 2648.88 | V29: 2631.45 | W29: 2708.37 | X29: 2511.35 | Y29: 2045.5
A30: - услуги по передаче | B30: =$B$15 -> 1922.63 | C30: =$B30 -> 1922.63 | D30: =$B30 -> 1922.63 | E30: =$B30 -> 1922.63 | F30: =$B30 -> 1922.63 | G30: =$B30 -> 1922.63 | H30: =$B30 -> 1922.63 | I30: =$B30 -> 1922.63 | J30: =$B30 -> 1922.63 | ... Y30: =$B30 -> 1922.63
A31: - сбытовая надбавка ГП | B31: 106.82 | C31: 106.82 | D31: 106.82 | E31: 106.82 | F31: 106.82 | G31: 106.82 | H31: 106.82 | I31: 106.82 | J31: 106.82 | K31: 106.82 | L31: 106.82 | M31: 106.82 | N31: 106.82 | O31: 106.82 | P31: 106.82 | Q31: 106.82 | R31: 106.82 | S31: 106.82 | T31: 106.82 | U31: 106.82 | V31: 106.82 | W31: 106.82 | X31: 106.82 | Y31: 106.82
A32: - инфраструктурные платежи | B32: =$B$17 -> 5.35 | C32: =$B32 -> 5.35 | D32: =$B32 -> 5.35 | E32: =$B32 -> 5.35 | F32: =$B32 -> 5.35 | G32: =$B32 -> 5.35 | H32: =$B32 -> 5.35 | I32: =$B32 -> 5.35 | J32: =$B32 -> 5.35 | ... Y32: =$B32 -> 5.35
A33: 5 | B33: =B34+B35+B36+B37 -> 3788.16 | C33: =C34+C35+C36+C37 -> 3553.93 | D33: =D34+D35+D36+D37 -> 3446.88 | E33: =E34+E35+E36+E37 -> 3303.74 | F33: =F34+F35+F36+F37 -> 3245.45 | G33: =G34+G35+G36+G37 -> 3236.5 | H33: =H34+H35+H36+H37 -> 3339.66 | I33: =I34+I35+I36+I37 -> 3703.82 | ... Y33: =Y34+Y35+Y36+Y37 -> 4015.96
A34: - средневзв. стоимость э/э (м) | B34: 1753.36 | C34: 1519.13 | D34: 1412.08 | E34: 1268.94 | F34: 1210.65 | G34: 1201.7 | H34: 1304.86 | I34: 1669.02 | J34: 2134.91 | K34: 2370.79 | L34: 2439.61 | M34: 2468.97 | N34: 2464.34 | O34: 2468.42 | P34: 2464.8 | Q34: 2527.1 | R34: 2535.38 | S34: 2500.69 | T34: 2480.64 | U34: 2452.58 | V34: 2450.49 | W34: 2467.58 | X34: 2169.48 | Y34: 1981.16
A35: - услуги по передаче | B35: =$B$15 -> 1922.63 | C35: =$B35 -> 1922.63 | D35: =$B35 -> 1922.63 | E35: =$B35 -> 1922.63 | F35: =$B35 -> 1922.63 | G35: =$B35 -> 1922.63 | H35: =$B35 -> 1922.63 | I35: =$B35 -> 1922.63 | J35: =$B35 -> 1922.63 | ... Y35: =$B35 -> 1922.63
A36: - сбытовая надбавка ГП | B36: 106.82 | C36: 106.82 | D36: 106.82 | E36: 106.82 | F36: 106.82 | G36: 106.82 | H36: 106.82 | I36: 106.82 | J36: 106.82 | K36: 106.82 | L36: 106.82 | M36: 106.82 | N36: 106.82 | O36: 106.82 | P36: 106.82 | Q36: 106.82 | R36: 106.82 | S36: 106.82 | T36: 106.82 | U36: 106.82 | V36: 106.82 | W36: 106.82 | X36: 106.82 | Y36: 106.82
A37: - инфраструктурные платежи | B37: =$B$17 -> 5.35 | C37: =$B37 -> 5.35 | D37: =$B37 -> 5.35 | E37: =$B37 -> 5.35 | F37: =$B37 -> 5.35 | G37: =$B37 -> 5.35 | H37: =$B37 -> 5.35 | I37: =$B37 -> 5.35 | J37: =$B37 -> 5.35 | ... Y37: =$B37 -> 5.35
A38: 6 | B38: =B39+B40+B41+B42 -> 3796.45 | C38: =C39+C40+C41+C42 -> 3542.38 | D38: =D39+D40+D41+D42 -> 3421.4 | E38: =E39+E40+E41+E42 -> 3235.77 | F38: =F39+F40+F41+F42 -> 3178.28 | G38: =G39+G40+G41+G42 -> 3177.21 | H38: =H39+H40+H41+H42 -> 3121.96 | I38: =I39+I40+I41+I42 -> 3550.81 | ... Y38: =Y39+Y40+Y41+Y42 -> 3877.34
A39: - средневзв. стоимость э/э (м) | B39: 1761.65 | C39: 1507.58 | D39: 1386.6 | E39: 1200.97 | F39: 1143.48 | G39: 1142.41 | H39: 1087.16 | I39: 1516.01 | J39: 1920.92 | K39: 2258.81 | L39: 2395.9 | M39: 2395.86 | N39: 2398.62 | O39: 2405.7 | P39: 2410.55 | Q39: 2412.36 | R39: 2465.57 | S39: 2451.43 | T39: 2449.76 | U39: 2433.67 | V39: 2433.2 | W39: 2429.4 | X39: 2185.02 | Y39: 1842.54
A40: - услуги по передаче | B40: =$B$15 -> 1922.63 | C40: =$B40 -> 1922.63 | D40: =$B40 -> 1922.63 | E40: =$B40 -> 1922.63 | F40: =$B40 -> 1922.63 | G40: =$B40 -> 1922.63 | H40: =$B40 -> 1922.63 | I40: =$B40 -> 1922.63 | J40: =$B40 -> 1922.63 | ... Y40: =$B40 -> 1922.63
A41: - сбытовая надбавка ГП | B41: 106.82 | C41: 106.82 | D41: 106.82 | E41: 106.82 | F41: 106.82 | G41: 106.82 | H41: 106.82 | I41: 106.82 | J41: 106.82 | K41: 106.82 | L41: 106.82 | M41: 106.82 | N41: 106.82 | O41: 106.82 | P41: 106.82 | Q41: 106.82 | R41: 106.82 | S41: 106.82 | T41: 106.82 | U41: 106.82 | V41: 106.82 | W41: 106.82 | X41: 106.82 | Y41: 106.82
A42: - инфраструктурные платежи | B42: =$B$17 -> 5.35 | C42: =$B42 -> 5.35 | D42: =$B42 -> 5.35 | E42: =$B42 -> 5.35 | F42: =$B42 -> 5.35 | G42: =$B42 -> 5.35 | H42: =$B42 -> 5.35 | I42: =$B42 -> 5.35 | J42: =$B42 -> 5.35 | ... Y42: =$B42 -> 5.35
A43: 7 | B43: =B44+B45+B46+B47 -> 3720.71 | C43: =C44+C45+C46+C47 -> 3552.18 | D43: =D44+D45+D46+D47 -> 3351.55 | E43: =E44+E45+E46+E47 -> 3206.82 | F43: =F44+F45+F46+F47 -> 3175.62 | G43: =G44+G45+G46+G47 -> 3265.2 | H43: =H44+H45+H46+H47 -> 3571.34 | I43: =I44+I45+I46+I47 -> 4012.57 | ... Y43: =Y44+Y45+Y46+Y47 -> 3904.88
A44: - средневзв. стоимость э/э (м) | B44: 1685.91 | C44: 1517.38 | D44: 1316.75 | E44: 1172.02 | F44: 1140.82 | G44: 1230.4 | H44: 1536.54 | I44: 1977.77 | J44: 2516.42 | K44: 2642.82 | L44: 2703.04 | M44: 2743.84 | N44: 2728.5 | O44: 2752.78 | P44: 2737.88 | Q44: 2771.21 | R44: 2719.3 | S44: 2834.06 | T44: 2733.83 | U44: 2697.7 | V44: 2643.26 | W44: 2659.85 | X44: 2219.27 | Y44: 1870.08
A45: - услуги по передаче | B45: =$B$15 -> 1922.63 | C45: =$B45 -> 1922.63 | D45: =$B45 -> 1922.63 | E45: =$B45 -> 1922.63 | F45: =$B45 -> 1922.63 | G45: =$B45 -> 1922.63 | H45: =$B45 -> 1922.63 | I45: =$B45 -> 1922.63 | J45: =$B45 -> 1922.63 | ... Y45: =$B45 -> 1922.63
A46: - сбытовая надбавка ГП | B46: 106.82 | C46: 106.82 | D46: 106.82 | E46: 106.82 | F46: 106.82 | G46: 106.82 | H46: 106.82 | I46: 106.82 | J46: 106.82 | K46: 106.82 | L46: 106.82 | M46: 106.82 | N46: 106.82 | O46: 106.82 | P46: 106.82 | Q46: 106.82 | R46: 106.82 | S46: 106.82 | T46: 106.82 | U46: 106.82 | V46: 106.82 | W46: 106.82 | X46: 106.82 | Y46: 106.82
A47: - инфраструктурные платежи | B47: =$B$17 -> 5.35 | C47: =$B47 -> 5.35 | D47: =$B47 -> 5.35 | E47: =$B47 -> 5.35 | F47: =$B47 -> 5.35 | G47: =$B47 -> 5.35 | H47: =$B47 -> 5.35 | I47: =$B47 -> 5.35 | J47: =$B47 -> 5.35 | ... Y47: =$B47 -> 5.35
A48: 8 | B48: =B49+B50+B51+B52 -> 3553.93 | C48: =C49+C50+C51+C52 -> 3279.82 | D48: =D49+D50+D51+D52 -> 3116.82 | E48: =E49+E50+E51+E52 -> 2224.95 | F48: =F49+F50+F51+F52 -> 2183.38 | G48: =G49+G50+G51+G52 -> 2198.59 | H48: =H49+H50+H51+H52 -> 3256.8 | I48: =I49+I50+I51+I52 -> 3852.37 | ... Y48: =Y49+Y50+Y51+Y52 -> 3890.34
A49: - средневзв. стоимость э/э (м) | B49: 1519.13 | C49: 1245.02 | D49: 1082.02 | E49: 190.15 | F49: 148.58 | G49: 163.79 | H49: 1222 | I49: 1817.57 | J49: 2386.8 | K49: 2620.89 | L49: 2753.89 | M49: 2766.53 | N49: 2750.06 | O49: 2752.45 | P49: 3081.15 | Q49: 2829.37 | R49: 2852.62 | S49: 2826.79 | T49: 2731.55 | U49: 2624.77 | V49: 2604.67 | W49: 2544.9 | X49: 2150.53 | Y49: 1855.54
A50: - услуги по передаче | B50: =$B$15 -> 1922.63 | C50: =$B50 -> 1922.63 | D50: =$B50 -> 1922.63 | E50: =$B50 -> 1922.63 | F50: =$B50 -> 1922.63 | G50: =$B50 -> 1922.63 | H50: =$B50 -> 1922.63 | I50: =$B50 -> 1922.63 | J50: =$B50 -> 1922.63 | ... Y50: =$B50 -> 1922.63
A51: - сбытовая надбавка ГП | B51: 106.82 | C51: 106.82 | D51: 106.82 | E51: 106.82 | F51: 106.82 | G51: 106.82 | H51: 106.82 | I51: 106.82 | J51: 106.82 | K51: 106.82 | L51: 106.82 | M51: 106.82 | N51: 106.82 | O51: 106.82 | P51: 106.82 | Q51: 106.82 | R51: 106.82 | S51: 106.82 | T51: 106.82 | U51: 106.82 | V51: 106.82 | W51: 106.82 | X51: 106.82 | Y51: 106.82
A52: - инфраструктурные платежи | B52: =$B$17 -> 5.35 | C52: =$B52 -> 5.35 | D52: =$B52 -> 5.35 | E52: =$B52 -> 5.35 | F52: =$B52 -> 5.35 | G52: =$B52 -> 5.35 | H52: =$B52 -> 5.35 | I52: =$B52 -> 5.35 | J52: =$B52 -> 5.35 | ... Y52: =$B52 -> 5.35
A53: 9 | B53: =B54+B55+B56+B57 -> 3727.43 | C53: =C54+C55+C56+C57 -> 3160.96 | D53: =D54+D55+D56+D57 -> 2191.86 | E53: =E54+E55+E56+E57 -> 2187.64 | F53: =F54+F55+F56+F57 -> 2185.17 | G53: =G54+G55+G56+G57 -> 2198.46 | H53: =H54+H55+H56+H57 -> 3164.37 | I53: =I54+I55+I56+I57 -> 3866.87 | ... Y53: =Y54+Y55+Y56+Y57 -> 3624.95
A54: - средневзв. стоимость э/э (м) | B54: 1692.63 | C54: 1126.16 | D54: 157.06 | E54: 152.84 | F54: 150.37 | G54: 163.66 | H54: 1129.57 | I54: 1832.07 | J54: 2133.88 | K54: 2497.34 | L54: 2693.5 | M54: 2757.98 | N54: 2756.02 | O54: 3052.55 | P54: 3209.79 | Q54: 3223.31 | R54: 3167.97 | S54: 3140.22 | T54: 2786.8 | U54: 2570.26 | V54: 2515.07 | W54: 2497.39 | X54: 2056.21 | Y54: 1590.15
A55: - услуги по передаче | B55: =$B$15 -> 1922.63 | C55: =$B55 -> 1922.63 | D55: =$B55 -> 1922.63 | E55: =$B55 -> 1922.63 | F55: =$B55 -> 1922.63 | G55: =$B55 -> 1922.63 | H55: =$B55 -> 1922.63 | I55: =$B55 -> 1922.63 | J55: =$B55 -> 1922.63 | ... Y55: =$B55 -> 1922.63
A56: - сбытовая надбавка ГП | B56: 106.82 | C56: 106.82 | D56: 106.82 | E56: 106.82 | F56: 106.82 | G56: 106.82 | H56: 106.82 | I56: 106.82 | J56: 106.82 | K56: 106.82 | L56: 106.82 | M56: 106.82 | N56: 106.82 | O56: 106.82 | P56: 106.82 | Q56: 106.82 | R56: 106.82 | S56: 106.82 | T56: 106.82 | U56: 106.82 | V56: 106.82 | W56: 106.82 | X56: 106.82 | Y56: 106.82
A57: - инфраструктурные платежи | B57: =$B$17 -> 5.35 | C57: =$B57 -> 5.35 | D57: =$B57 -> 5.35 | E57: =$B57 -> 5.35 | F57: =$B57 -> 5.35 | G57: =$B57 -> 5.35 | H57: =$B57 -> 5.35 | I57: =$B57 -> 5.35 | J57: =$B57 -> 5.35 | ... Y57: =$B57 -> 5.35
A58: 10 | B58: =B59+B60+B61+B62 -> 3379.56 | C58: =C59+C60+C61+C62 -> 3110.69 | D58: =D59+D60+D61+D62 -> 2177.7 | E58: =E59+E60+E61+E62 -> 2154.87 | F58: =F59+F60+F61+F62 -> 2161.95 | G58: =G59+G60+G61+G62 -> 2182.05 | H58: =H59+H60+H61+H62 -> 2743.61 | I58: =I59+I60+I61+I62 -> 3655.3 | ... Y58: =Y59+Y60+Y61+Y62 -> 3844.55
A59: - средневзв. стоимость э/э (м) | B59: 1344.76 | C59: 1075.89 | D59: 142.9 | E59: 120.07 | F59: 127.15 | G59: 147.25 | H59: 708.81 | I59: 1620.5 | J59: 2220.31 | K59: 2731.02 | L59: 3037.45 | M59: 3178.14 | N59: 2657.09 | O59: 3029.52 | P59: 3237.11 | Q59: 3082.44 | R59: 3084.05 | S59: 3007.53 | T59: 2862.95 | U59: 2840.64 | V59: 2729.6 | W59: 2671.87 | X59: 2185.28 | Y59: 1809.75
A60: - услуги по передаче | B60: =$B$15 -> 1922.63 | C60: =$B60 -> 1922.63 | D60: =$B60 -> 1922.63 | E60: =$B60 -> 1922.63 | F60: =$B60 -> 1922.63 | G60: =$B60 -> 1922.63 | H60: =$B60 -> 1922.63 | I60: =$B60 -> 1922.63 | J60: =$B60 -> 1922.63 | ... Y60: =$B60 -> 1922.63
A61: - сбытовая надбавка ГП | B61: 106.82 | C61: 106.82 | D61: 106.82 | E61: 106.82 | F61: 106.82 | G61: 106.82 | H61: 106.82 | I61: 106.82 | J61: 106.82 | K61: 106.82 | L61: 106.82 | M61: 106.82 | N61: 106.82 | O61: 106.82 | P61: 106.82 | Q61: 106.82 | R61: 106.82 | S61: 106.82 | T61: 106.82 | U61: 106.82 | V61: 106.82 | W61: 106.82 | X61: 106.82 | Y61: 106.82
A62: - инфраструктурные платежи | B62: =$B$17 -> 5.35 | C62: =$B62 -> 5.35 | D62: =$B62 -> 5.35 | E62: =$B62 -> 5.35 | F62: =$B62 -> 5.35 | G62: =$B62 -> 5.35 | H62: =$B62 -> 5.35 | I62: =$B62 -> 5.35 | J62: =$B62 -> 5.35 | ... Y62: =$B62 -> 5.35
A63: 11 | B63: =B64+B65+B66+B67 -> 3498.32 | C63: =C64+C65+C66+C67 -> 3274 | D63: =D64+D65+D66+D67 -> 2192.38 | E63: =E64+E65+E66+E67 -> 2186.41 | F63: =F64+F65+F66+F67 -> 2187 | G63: =G64+G65+G66+G67 -> 2189.67 | H63: =H64+H65+H66+H67 -> 3380.62 | I63: =I64+I65+I66+I67 -> 3813.13 | ... Y63: =Y64+Y65+Y66+Y67 -> 4094.76
A64: - средневзв. стоимость э/э (м) | B64: 1463.52 | C64: 1239.2 | D64: 157.58 | E64: 151.61 | F64: 152.2 | G64: 154.87 | H64: 1345.82 | I64: 1778.33 | J64: 2517.19 | K64: 2779.58 | L64: 2799.71 | M64: 2902.42 | N64: 2914.86 | O64: 2982.36 | P64: 2754.11 | Q64: 3061.37 | R64: 3061.84 | S64: 3348.84 | T64: 2924.97 | U64: 2837.1 | V64: 2959.58 | W64: 2832.44 | X64: 2367.04 | Y64: 2059.96
A65: - услуги по передаче | B65: =$B$15 -> 1922.63 | C65: =$B65 -> 1922.63 | D65: =$B65 -> 1922.63 | E65: =$B65 -> 1922.63 | F65: =$B65 -> 1922.63 | G65: =$B65 -> 1922.63 | H65: =$B65 -> 1922.63 | I65: =$B65 -> 1922.63 | J65: =$B65 -> 1922.63 | ... Y65: =$B65 -> 1922.63
A66: - сбытовая надбавка ГП | B66: 106.82 | C66: 106.82 | D66: 106.82 | E66: 106.82 | F66: 106.82 | G66: 106.82 | H66: 106.82 | I66: 106.82 | J66: 106.82 | K66: 106.82 | L66: 106.82 | M66: 106.82 | N66: 106.82 | O66: 106.82 | P66: 106.82 | Q66: 106.82 | R66: 106.82 | S66: 106.82 | T66: 106.82 | U66: 106.82 | V66: 106.82 | W66: 106.82 | X66: 106.82 | Y66: 106.82
A67: - инфраструктурные платежи | B67: =$B$17 -> 5.35 | C67: =$B67 -> 5.35 | D67: =$B67 -> 5.35 | E67: =$B67 -> 5.35 | F67: =$B67 -> 5.35 | G67: =$B67 -> 5.35 | H67: =$B67 -> 5.35 | I67: =$B67 -> 5.35 | J67: =$B67 -> 5.35 | ... Y67: =$B67 -> 5.35
A68: 12 | B68: =B69+B70+B71+B72 -> 3809.46 | C68: =C69+C70+C71+C72 -> 3483.04 | D68: =D69+D70+D71+D72 -> 3317.67 | E68: =E69+E70+E71+E72 -> 2396.79 | F68: =F69+F70+F71+F72 -> 2212.55 | G68: =G69+G70+G71+G72 -> 2209.68 | H68: =H69+H70+H71+H72 -> 3149.88 | I68: =I69+I70+I71+I72 -> 3665.31 | ... Y68: =Y69+Y70+Y71+Y72 -> 4185.86
A69: - средневзв. стоимость э/э (м) | B69: 1774.66 | C69: 1448.24 | D69: 1282.87 | E69: 361.99 | F69: 177.75 | G69: 174.88 | H69: 1115.08 | I69: 1630.51 | J69: 2215.05 | K69: 2564.66 | L69: 2743.61 | M69: 2757.38 | N69: 2751.08 | O69: 2846.09 | P69: 2860.77 | Q69: 2799.77 | R69: 3214.08 | S69: 3164.24 | T69: 2779.49 | U69: 2679.46 | V69: 2779.53 | W69: 2846.71 | X69: 2556.08 | Y69: 2151.06
A70: - услуги по передаче | B70: =$B$15 -> 1922.63 | C70: =$B70 -> 1922.63 | D70: =$B70 -> 1922.63 | E70: =$B70 -> 1922.63 | F70: =$B70 -> 1922.63 | G70: =$B70 -> 1922.63 | H70: =$B70 -> 1922.63 | I70: =$B70 -> 1922.63 | J70: =$B70 -> 1922.63 | ... Y70: =$B70 -> 1922.63
A71: - сбытовая надбавка ГП | B71: 106.82 | C71: 106.82 | D71: 106.82 | E71: 106.82 | F71: 106.82 | G71: 106.82 | H71: 106.82 | I71: 106.82 | J71: 106.82 | K71: 106.82 | L71: 106.82 | M71: 106.82 | N71: 106.82 | O71: 106.82 | P71: 106.82 | Q71: 106.82 | R71: 106.82 | S71: 106.82 | T71: 106.82 | U71: 106.82 | V71: 106.82 | W71: 106.82 | X71: 106.82 | Y71: 106.82
A72: - инфраструктурные платежи | B72: =$B$17 -> 5.35 | C72: =$B72 -> 5.35 | D72: =$B72 -> 5.35 | E72: =$B72 -> 5.35 | F72: =$B72 -> 5.35 | G72: =$B72 -> 5.35 | H72: =$B72 -> 5.35 | I72: =$B72 -> 5.35 | J72: =$B72 -> 5.35 | ... Y72: =$B72 -> 5.35
A73: 13 | B73: =B74+B75+B76+B77 -> 3733.18 | C73: =C74+C75+C76+C77 -> 3520.46 | D73: =D74+D75+D76+D77 -> 3351.8 | E73: =E74+E75+E76+E77 -> 2237.43 | F73: =F74+F75+F76+F77 -> 2202.24 | G73: =G74+G75+G76+G77 -> 2198.97 | H73: =H74+H75+H76+H77 -> 3006.55 | I73: =I74+I75+I76+I77 -> 3469.39 | ... Y73: =Y74+Y75+Y76+Y77 -> 4045.21
A74: - средневзв. стоимость э/э (м) | B74: 1698.38 | C74: 1485.66 | D74: 1317 | E74: 202.63 | F74: 167.44 | G74: 164.17 | H74: 971.75 | I74: 1434.59 | J74: 1978.25 | K74: 2469.39 | L74: 2591.3 | M74: 2585.28 | N74: 2770.57 | O74: 2728.68 | P74: 2791.8 | Q74: 2808.61 | R74: 2785.21 | S74: 2911.59 | T74: 2831.65 | U74: 2752.88 | V74: 2732.52 | W74: 2727.08 | X74: 2460.78 | Y74: 2010.41
A75: - услуги по передаче | B75: =$B$15 -> 1922.63 | C75: =$B75 -> 1922.63 | D75: =$B75 -> 1922.63 | E75: =$B75 -> 1922.63 | F75: =$B75 -> 1922.63 | G75: =$B75 -> 1922.63 | H75: =$B75 -> 1922.63 | I75: =$B75 -> 1922.63 | J75: =$B75 -> 1922.63 | ... Y75: =$B75 -> 1922.63
A76: - сбытовая надбавка ГП | B76: 106.82 | C76: 106.82 | D76: 106.82 | E76: 106.82 | F76: 106.82 | G76: 106.82 | H76: 106.82 | I76: 106.82 | J76: 106.82 | K76: 106.82 | L76: 106.82 | M76: 106.82 | N76: 106.82 | O76: 106.82 | P76: 106.82 | Q76: 106.82 | R76: 106.82 | S76: 106.82 | T76: 106.82 | U76: 106.82 | V76: 106.82 | W76: 106.82 | X76: 106.82 | Y76: 106.82
A77: - инфраструктурные платежи | B77: =$B$17 -> 5.35 | C77: =$B77 -> 5.35 | D77: =$B77 -> 5.35 | E77: =$B77 -> 5.35 | F77: =$B77 -> 5.35 | G77: =$B77 -> 5.35 | H77: =$B77 -> 5.35 | I77: =$B77 -> 5.35 | J77: =$B77 -> 5.35 | ... Y77: =$B77 -> 5.35
A78: 14 | B78: =B79+B80+B81+B82 -> 3605.96 | C78: =C79+C80+C81+C82 -> 3409.33 | D78: =D79+D80+D81+D82 -> 2304.52 | E78: =E79+E80+E81+E82 -> 2211.83 | F78: =F79+F80+F81+F82 -> 2207.55 | G78: =G79+G80+G81+G82 -> 2211.85 | H78: =H79+H80+H81+H82 -> 3226.02 | I78: =I79+I80+I81+I82 -> 3879.98 | ... Y78: =Y79+Y80+Y81+Y82 -> 3851.58
A79: - средневзв. стоимость э/э (м) | B79: 1571.16 | C79: 1374.53 | D79: 269.72 | E79: 177.03 | F79: 172.75 | G79: 177.05 | H79: 1191.22 | I79: 1845.18 | J79: 2619.18 | K79: 2871.52 | L79: 2895.84 | M79: 2902.83 | N79: 2894.62 | O79: 2900.41 | P79: 2894.5 | Q79: 2960.06 | R79: 2939.75 | S79: 2926.91 | T79: 2877.18 | U79: 2797.16 | V79: 2785.27 | W79: 2752.19 | X79: 2228.96 | Y79: 1816.78
A80: - услуги по передаче | B80: =$B$15 -> 1922.63 | C80: =$B80 -> 1922.63 | D80: =$B80 -> 1922.63 | E80: =$B80 -> 1922.63 | F80: =$B80 -> 1922.63 | G80: =$B80 -> 1922.63 | H80: =$B80 -> 1922.63 | I80: =$B80 -> 1922.63 | J80: =$B80 -> 1922.63 | ... Y80: =$B80 -> 1922.63
A81: - сбытовая надбавка ГП | B81: 106.82 | C81: 106.82 | D81: 106.82 | E81: 106.82 | F81: 106.82 | G81: 106.82 | H81: 106.82 | I81: 106.82 | J81: 106.82 | K81: 106.82 | L81: 106.82 | M81: 106.82 | N81: 106.82 | O81: 106.82 | P81: 106.82 | Q81: 106.82 | R81: 106.82 | S81: 106.82 | T81: 106.82 | U81: 106.82 | V81: 106.82 | W81: 106.82 | X81: 106.82 | Y81: 106.82
A82: - инфраструктурные платежи | B82: =$B$17 -> 5.35 | C82: =$B82 -> 5.35 | D82: =$B82 -> 5.35 | E82: =$B82 -> 5.35 | F82: =$B82 -> 5.35 | G82: =$B82 -> 5.35 | H82: =$B82 -> 5.35 | I82: =$B82 -> 5.35 | J82: =$B82 -> 5.35 | ... Y82: =$B82 -> 5.35
A83: 15 | B83: =B84+B85+B86+B87 -> 3452.14 | C83: =C84+C85+C86+C87 -> 3262.61 | D83: =D84+D85+D86+D87 -> 3103.01 | E83: =E84+E85+E86+E87 -> 2143.92 | F83: =F84+F85+F86+F87 -> 2066.37 | G83: =G84+G85+G86+G87 -> 2142.54 | H83: =H84+H85+H86+H87 -> 3058.29 | I83: =I84+I85+I86+I87 -> 3880.24 | ... Y83: =Y84+Y85+Y86+Y87 -> 3955.8
A84: - средневзв. стоимость э/э (м) | B84: 1417.34 | C84: 1227.81 | D84: 1068.21 | E84: 109.12 | F84: 31.57 | G84: 107.74 | H84: 1023.49 | I84: 1845.44 | J84: 2433.4 | K84: 2892.37 | L84: 2879.59 | M84: 2948.78 | N84: 2950.12 | O84: 2969.15 | P84: 2956.29 | Q84: 2978.09 | R84: 3013.06 | S84: 3049.74 | T84: 2962.02 | U84: 2846.26 | V84: 2745.91 | W84: 2742.16 | X84: 2196.13 | Y84: 1921
A85: - услуги по передаче | B85: =$B$15 -> 1922.63 | C85: =$B85 -> 1922.63 | D85: =$B85 -> 1922.63 | E85: =$B85 -> 1922.63 | F85: =$B85 -> 1922.63 | G85: =$B85 -> 1922.63 | H85: =$B85 -> 1922.63 | I85: =$B85 -> 1922.63 | J85: =$B85 -> 1922.63 | ... Y85: =$B85 -> 1922.63
A86: - сбытовая надбавка ГП | B86: 106.82 | C86: 106.82 | D86: 106.82 | E86: 106.82 | F86: 106.82 | G86: 106.82 | H86: 106.82 | I86: 106.82 | J86: 106.82 | K86: 106.82 | L86: 106.82 | M86: 106.82 | N86: 106.82 | O86: 106.82 | P86: 106.82 | Q86: 106.82 | R86: 106.82 | S86: 106.82 | T86: 106.82 | U86: 106.82 | V86: 106.82 | W86: 106.82 | X86: 106.82 | Y86: 106.82
A87: - инфраструктурные платежи | B87: =$B$17 -> 5.35 | C87: =$B87 -> 5.35 | D87: =$B87 -> 5.35 | E87: =$B87 -> 5.35 | F87: =$B87 -> 5.35 | G87: =$B87 -> 5.35 | H87: =$B87 -> 5.35 | I87: =$B87 -> 5.35 | J87: =$B87 -> 5.35 | ... Y87: =$B87 -> 5.35
A88: 16 | B88: =B89+B90+B91+B92 -> 3491.73 | C88: =C89+C90+C91+C92 -> 3314.73 | D88: =D89+D90+D91+D92 -> 3135.77 | E88: =E89+E90+E91+E92 -> 2884.41 | F88: =F89+F90+F91+F92 -> 2294.93 | G88: =G89+G90+G91+G92 -> 3078.28 | H88: =H89+H90+H91+H92 -> 3157.92 | I88: =I89+I90+I91+I92 -> 3617.37 | ... Y88: =Y89+Y90+Y91+Y92 -> 3850.81
A89: - средневзв. стоимость э/э (м) | B89: 1456.93 | C89: 1279.93 | D89: 1100.97 | E89: 849.61 | F89: 260.13 | G89: 1043.48 | H89: 1123.12 | I89: 1582.57 | J89: 2368.26 | K89: 2855.03 | L89: 2928.17 | M89: 3033.92 | N89: 3154.17 | O89: 3179.94 | P89: 3175.14 | Q89: 3092.33 | R89: 3119.37 | S89: 2923.4 | T89: 2854.64 | U89: 2738.07 | V89: 2709.8 | W89: 2690.09 | X89: 2442.61 | Y89: 1816.01
A90: - услуги по передаче | B90: =$B$15 -> 1922.63 | C90: =$B90 -> 1922.63 | D90: =$B90 -> 1922.63 | E90: =$B90 -> 1922.63 | F90: =$B90 -> 1922.63 | G90: =$B90 -> 1922.63 | H90: =$B90 -> 1922.63 | I90: =$B90 -> 1922.63 | J90: =$B90 -> 1922.63 | ... Y90: =$B90 -> 1922.63
A91: - сбытовая надбавка ГП | B91: 106.82 | C91: 106.82 | D91: 106.82 | E91: 106.82 | F91: 106.82 | G91: 106.82 | H91: 106.82 | I91: 106.82 | J91: 106.82 | K91: 106.82 | L91: 106.82 | M91: 106.82 | N91: 106.82 | O91: 106.82 | P91: 106.82 | Q91: 106.82 | R91: 106.82 | S91: 106.82 | T91: 106.82 | U91: 106.82 | V91: 106.82 | W91: 106.82 | X91: 106.82 | Y91: 106.82
A92: - инфраструктурные платежи | B92: =$B$17 -> 5.35 | C92: =$B92 -> 5.35 | D92: =$B92 -> 5.35 | E92: =$B92 -> 5.35 | F92: =$B92 -> 5.35 | G92: =$B92 -> 5.35 | H92: =$B92 -> 5.35 | I92: =$B92 -> 5.35 | J92: =$B92 -> 5.35 | ... Y92: =$B92 -> 5.35
A93: 17 | B93: =B94+B95+B96+B97 -> 3623.46 | C93: =C94+C95+C96+C97 -> 3351.79 | D93: =D94+D95+D96+D97 -> 3141.29 | E93: =E94+E95+E96+E97 -> 2880.06 | F93: =F94+F95+F96+F97 -> 2853.63 | G93: =G94+G95+G96+G97 -> 3091.41 | H93: =H94+H95+H96+H97 -> 3352.78 | I93: =I94+I95+I96+I97 -> 3947.67 | ... Y93: =Y94+Y95+Y96+Y97 -> 4004.26
A94: - средневзв. стоимость э/э (м) | B94: 1588.66 | C94: 1316.99 | D94: 1106.49 | E94: 845.26 | F94: 818.83 | G94: 1056.61 | H94: 1317.98 | I94: 1912.87 | J94: 2629.25 | K94: 2893.84 | L94: 2895.72 | M94: 3002.23 | N94: 3003.68 | O94: 3027.52 | P94: 3026.25 | Q94: 3013.19 | R94: 3018.06 | S94: 2971.67 | T94: 2908.04 | U94: 2847.78 | V94: 2823.95 | W94: 2807.31 | X94: 2613.24 | Y94: 1969.46
A95: - услуги по передаче | B95: =$B$15 -> 1922.63 | C95: =$B95 -> 1922.63 | D95: =$B95 -> 1922.63 | E95: =$B95 -> 1922.63 | F95: =$B95 -> 1922.63 | G95: =$B95 -> 1922.63 | H95: =$B95 -> 1922.63 | I95: =$B95 -> 1922.63 | J95: =$B95 -> 1922.63 | ... Y95: =$B95 -> 1922.63
A96: - сбытовая надбавка ГП | B96: 106.82 | C96: 106.82 | D96: 106.82 | E96: 106.82 | F96: 106.82 | G96: 106.82 | H96: 106.82 | I96: 106.82 | J96: 106.82 | K96: 106.82 | L96: 106.82 | M96: 106.82 | N96: 106.82 | O96: 106.82 | P96: 106.82 | Q96: 106.82 | R96: 106.82 | S96: 106.82 | T96: 106.82 | U96: 106.82 | V96: 106.82 | W96: 106.82 | X96: 106.82 | Y96: 106.82
A97: - инфраструктурные платежи | B97: =$B$17 -> 5.35 | C97: =$B97 -> 5.35 | D97: =$B97 -> 5.35 | E97: =$B97 -> 5.35 | F97: =$B97 -> 5.35 | G97: =$B97 -> 5.35 | H97: =$B97 -> 5.35 | I97: =$B97 -> 5.35 | J97: =$B97 -> 5.35 | ... Y97: =$B97 -> 5.35
A98: 18 | B98: =B99+B100+B101+B102 -> 3645.77 | C98: =C99+C100+C101+C102 -> 3437.17 | D98: =D99+D100+D101+D102 -> 3239.83 | E98: =E99+E100+E101+E102 -> 3103.99 | F98: =F99+F100+F101+F102 -> 2868.18 | G98: =G99+G100+G101+G102 -> 3014.78 | H98: =H99+H100+H101+H102 -> 3462.17 | I98: =I99+I100+I101+I102 -> 3948.48 | ... Y98: =Y99+Y100+Y101+Y102 -> 4283.13
A99: - средневзв. стоимость э/э (м) | B99: 1610.97 | C99: 1402.37 | D99: 1205.03 | E99: 1069.19 | F99: 833.38 | G99: 979.98 | H99: 1427.37 | I99: 1913.68 | J99: 2874.94 | K99: 3004.59 | L99: 3101.21 | M99: 3322.11 | N99: 3309.94 | O99: 3447.48 | P99: 3469.43 | Q99: 3441.94 | R99: 3275.18 | S99: 3157.78 | T99: 3096.69 | U99: 3014.76 | V99: 2925.04 | W99: 3004.37 | X99: 2715.84 | Y99: 2248.33
A100: - услуги по передаче | B100: =$B$15 -> 1922.63 | C100: =$B100 -> 1922.63 | D100: =$B100 -> 1922.63 | E100: =$B100 -> 1922.63 | F100: =$B100 -> 1922.63 | G100: =$B100 -> 1922.63 | H100: =$B100 -> 1922.63 | I100: =$B100 -> 1922.63 | J100: =$B100 -> 1922.63 | ... Y100: =$B100 -> 1922.63
A101: - сбытовая надбавка ГП | B101: 106.82 | C101: 106.82 | D101: 106.82 | E101: 106.82 | F101: 106.82 | G101: 106.82 | H101: 106.82 | I101: 106.82 | J101: 106.82 | K101: 106.82 | L101: 106.82 | M101: 106.82 | N101: 106.82 | O101: 106.82 | P101: 106.82 | Q101: 106.82 | R101: 106.82 | S101: 106.82 | T101: 106.82 | U101: 106.82 | V101: 106.82 | W101: 106.82 | X101: 106.82 | Y101: 106.82
A102: - инфраструктурные платежи | B102: =$B$17 -> 5.35 | C102: =$B102 -> 5.35 | D102: =$B102 -> 5.35 | E102: =$B102 -> 5.35 | F102: =$B102 -> 5.35 | G102: =$B102 -> 5.35 | H102: =$B102 -> 5.35 | I102: =$B102 -> 5.35 | J102: =$B102 -> 5.35 | ... Y102: =$B102 -> 5.35
A103: 19 | B103: =B104+B105+B106+B107 -> 3871.55 | C103: =C104+C105+C106+C107 -> 3616.11 | D103: =D104+D105+D106+D107 -> 3464.46 | E103: =E104+E105+E106+E107 -> 3256.68 | F103: =F104+F105+F106+F107 -> 3180.19 | G103: =G104+G105+G106+G107 -> 3267.16 | H103: =H104+H105+H106+H107 -> 3277.67 | I103: =I104+I105+I106+I107 -> 3509.95 | ... Y103: =Y104+Y105+Y106+Y107 -> 4216.8
A104: - средневзв. стоимость э/э (м) | B104: 1836.75 | C104: 1581.31 | D104: 1429.66 | E104: 1221.88 | F104: 1145.39 | G104: 1232.36 | H104: 1242.87 | I104: 1475.15 | J104: 2322.34 | K104: 2778.06 | L104: 2855.51 | M104: 2867.19 | N104: 2907.61 | O104: 2915.85 | P104: 2923.28 | Q104: 2914.06 | R104: 2934.88 | S104: 2901.65 | T104: 2878.85 | U104: 2849.21 | V104: 2835.47 | W104: 2815.49 | X104: 2659.81 | Y104: 2182
...

Sheet О_июль 4 цк
A2: ='О_июль 1 цк'!A2:F2 -> Предельные уровни нерегулируемых цен на электрическую энергию (мощность), поставляемую АО "Мосэнергосбыт" потребителям
A3: ='О_июль 1 цк'!A3:F3 -> с максимальной мощностью энергопринимающих устройств не менее 10 МВт
A4: ='О_июль 1 цк'!A4:F4 -> Московская область
A5: ='О_июль 1 цк'!A5:F5 -> Июль 2025 г.
A7: IV. Четвертая ценовая категория для объемов покупки электрической энергии (мощности), в отношении которых за расчетный период осуществляется почасовой учет, но не осуществляется почасовое планирование, а стоимость услуг по передаче электрической энергии определяется по тарифу на услуги по передаче электрической энергии в двухставочном выражении
A9: 1.1. Ставка за электрическую энергию предельного уровня нерегулируемых цен для абонентов группы "Иные прочие потребители", рублей/МВт∙ч без НДС
A11: Дата | B11: Ставка для фактических почасовых объемов покупки электрической энергии, отпущенных на уровне напряжения ВН
B12: 0:00-1:00 | C12: 1:00-2:00 | D12: 2:00-3:00 | E12: 3:00-4:00 | F12: 4:00-5:00 | G12: 5:00-6:00 | H12: 6:00-7:00 | I12: 7:00-8:00 | J12: 8:00-9:00 | K12: 9:00-10:00 | L12: 10:00-11:00 | M12: 11:00-12:00 | N12: 12:00-13:00 | O12: 13:00-14:00 | P12: 14:00-15:00 | Q12: 15:00-16:00 | R12: 16:00-17:00 | S12: 17:00-18:00 | T12: 18:00-19:00 | U12: 19:00-20:00 | V12: 20:00-21:00 | W12: 21:00-22:00 | X12: 22:00-23:00 | Y12: 23:00-0:00
A13: 1 | B13: =B14+B15+B16+B17 -> 1862.87 | C13: =C14+C15+C16+C17 -> 1594.33 | D13: =D14+D15+D16+D17 -> 1479.25 | E13: =E14+E15+E16+E17 -> 1378.45 | F13: =F14+F15+F16+F17 -> 1400.52 | G13: =G14+G15+G16+G17 -> 1685.81 | H13: =H14+H15+H16+H17 -> 1811.04 | I13: =I14+I15+I16+I17 -> 2262.9 | ... Y13: =Y14+Y15+Y16+Y17 -> 2285.01
A14: - средневзв. стоимость э/э (м) | B14: 1643.63 | C14: 1375.09 | D14: 1260.01 | E14: 1159.21 | F14: 1181.28 | G14: 1466.57 | H14: 1591.8 | I14: 2043.66 | J14: 2544.33 | K14: 2682.61 | L14: 2744.97 | M14: 2743.85 | N14: 2729.42 | O14: 2739.69 | P14: 2768.75 | Q14: 2783.49 | R14: 2762.56 | S14: 2768.68 | T14: 2746.78 | U14: 2697.44 | V14: 2663.63 | W14: 2636.06 | X14: 2326.79 | Y14: 2065.77
A15: - услуги по передаче | B15: 107.07 | C15: =$B15 -> 107.07 | D15: =$B15 -> 107.07 | E15: =$B15 -> 107.07 | F15: =$B15 -> 107.07 | G15: =$B15 -> 107.07 | H15: =$B15 -> 107.07 | I15: =$B15 -> 107.07 | J15: =$B15 -> 107.07 | ... Y15: =$B15 -> 107.07
A16: - сбытовая надбавка ГП | B16: 106.82 | C16: 106.82 | D16: 106.82 | E16: 106.82 | F16: 106.82 | G16: 106.82 | H16: 106.82 | I16: 106.82 | J16: 106.82 | K16: 106.82 | L16: 106.82 | M16: 106.82 | N16: 106.82 | O16: 106.82 | P16: 106.82 | Q16: 106.82 | R16: 106.82 | S16: 106.82 | T16: 106.82 | U16: 106.82 | V16: 106.82 | W16: 106.82 | X16: 106.82 | Y16: 106.82
A17: - инфраструктурные платежи | B17: 5.35 | C17: =$B17 -> 5.35 | D17: =$B17 -> 5.35 | E17: =$B17 -> 5.35 | F17: =$B17 -> 5.35 | G17: =$B17 -> 5.35 | H17: =$B17 -> 5.35 | I17: =$B17 -> 5.35 | J17: =$B17 -> 5.35 | ... Y17: =$B17 -> 5.35
A18: 2 | B18: =B19+B20+B21+B22 -> 1908.22 | C18: =C19+C20+C21+C22 -> 1748.24 | D18: =D19+D20+D21+D22 -> 1664.59 | E18: =E19+E20+E21+E22 -> 1449.09 | F18: =F19+F20+F21+F22 -> 1543.4 | G18: =G19+G20+G21+G22 -> 1744.45 | H18: =H19+H20+H21+H22 -> 1826.55 | I18: =I19+I20+I21+I22 -> 2313.58 | ... Y18: =Y19+Y20+Y21+Y22 -> 2219.62
A19: - средневзв. стоимость э/э (м) | B19: 1688.98 | C19: 1529 | D19: 1445.35 | E19: 1229.85 | F19: 1324.16 | G19: 1525.21 | H19: 1607.31 | I19: 2094.34 | J19: 2706.96 | K19: 2804.21 | L19: 2837.46 | M19: 2828.28 | N19: 2843.1 | O19: 2873.1 | P19: 2874.34 | Q19: 2863.78 | R19: 2837.34 | S19: 2817.79 | T19: 2806.9 | U19: 2778.96 | V19: 2748.46 | W19: 2727.03 | X19: 2445.18 | Y19: 2000.38
A20: - услуги по передаче | B20: =$B$15 -> 107.07 | C20: =$B20 -> 107.07 | D20: =$B20 -> 107.07 | E20: =$B20 -> 107.07 | F20: =$B20 -> 107.07 | G20: =$B20 -> 107.07 | H20: =$B20 -> 107.07 | I20: =$B20 -> 107.07 | J20: =$B20 -> 107.07 | ... Y20: =$B20 -> 107.07
A21: - сбытовая надбавка ГП | B21: 106.82 | C21: 106.82 | D21: 106.82 | E21: 106.82 | F21: 106.82 | G21: 106.82 | H21: 106.82 | I21: 106.82 | J21: 106.82 | K21: 106.82 | L21: 106.82 | M21: 106.82 | N21: 106.82 | O21: 106.82 | P21: 106.82 | Q21: 106.82 | R21: 106.82 | S21: 106.82 | T21: 106.82 | U21: 106.82 | V21: 106.82 | W21: 106.82 | X21: 106.82 | Y21: 106.82
A22: - инфраструктурные платежи | B22: =$B$17 -> 5.35 | C22: =$B22 -> 5.35 | D22: =$B22 -> 5.35 | E22: =$B22 -> 5.35 | F22: =$B22 -> 5.35 | G22: =$B22 -> 5.35 | H22: =$B22 -> 5.35 | I22: =$B22 -> 5.35 | J22: =$B22 -> 5.35 | ... Y22: =$B22 -> 5.35
A23: 3 | B23: =B24+B25+B26+B27 -> 1790.14 | C23: =C24+C25+C26+C27 -> 1631.95 | D23: =D24+D25+D26+D27 -> 1508.76 | E23: =E24+E25+E26+E27 -> 1393.06 | F23: =F24+F25+F26+F27 -> 1404.67 | G23: =G24+G25+G26+G27 -> 1630.13 | H23: =H24+H25+H26+H27 -> 1774.09 | I23: =I24+I25+I26+I27 -> 2228.28 | ... Y23: =Y24+Y25+Y26+Y27 -> 2207.9
A24: - средневзв. стоимость э/э (м) | B24: 1570.9 | C24: 1412.71 | D24: 1289.52 | E24: 1173.82 | F24: 1185.43 | G24: 1410.89 | H24: 1554.85 | I24: 2009.04 | J24: 2559.55 | K24: 2598.88 | L24: 2641.18 | M24: 2673.9 | N24: 2667.07 | O24: 2651.63 | P24: 2872.93 | Q24: 2941.52 | R24: 2884.71 | S24: 2688.33 | T24: 2757.86 | U24: 2651.34 | V24: 2696.89 | W24: 2677.99 | X24: 2417.66 | Y24: 1988.66
A25: - услуги по передаче | B25: =$B$15 -> 107.07 | C25: =$B25 -> 107.07 | D25: =$B25 -> 107.07 | E25: =$B25 -> 107.07 | F25: =$B25 -> 107.07 | G25: =$B25 -> 107.07 | H25: =$B25 -> 107.07 | I25: =$B25 -> 107.07 | J25: =$B25 -> 107.07 | ... Y25: =$B25 -> 107.07
A26: - сбытовая надбавка ГП | B26: 106.82 | C26: 106.82 | D26: 106.82 | E26: 106.82 | F26: 106.82 | G26: 106.82 | H26: 106.82 | I26: 106.82 | J26: 106.82 | K26: 106.82 | L26: 106.82 | M26: 106.82 | N26: 106.82 | O26: 106.82 | P26: 106.82 | Q26: 106.82 | R26: 106.82 | S26: 106.82 | T26: 106.82 | U26: 106.82 | V26: 106.82 | W26: 106.82 | X26: 106.82 | Y26: 106.82
A27: - инфраструктурные платежи | B27: =$B$17 -> 5.35 | C27: =$B27 -> 5.35 | D27: =$B27 -> 5.35 | E27: =$B27 -> 5.35 | F27: =$B27 -> 5.35 | G27: =$B27 -> 5.35 | H27: =$B27 -> 5.35 | I27: =$B27 -> 5.35 | J27: =$B27 -> 5.35 | ... Y27: =$B27 -> 5.35
A28: 4 | B28: =B29+B30+B31+B32 -> 1880.76 | C28: =C29+C30+C31+C32 -> 1660.73 | D28: =D29+D30+D31+D32 -> 1515.28 | E28: =E29+E30+E31+E32 -> 1386 | F28: =F29+F30+F31+F32 -> 1402.49 | G28: =G29+G30+G31+G32 -> 1635.04 | H28: =H29+H30+H31+H32 -> 1787.12 | I28: =I29+I30+I31+I32 -> 2249.74 | ... Y28: =Y29+Y30+Y31+Y32 -> 2264.74
A29: - средневзв. стоимость э/э (м) | B29: 1661.52 | C29: 1441.49 | D29: 1296.04 | E29: 1166.76 | F29: 1183.25 | G29: 1415.8 | H29: 1567.88 | I29: 2030.5 | J29: 2568.65 | K29: 2687.94 | L29: 2641.38 | M29: 2639.93 | N29: 2707.75 | O29: 2639.25 | P29: 2784.72 | Q29: 2836.9 | R29: 2818.07 | S29: 2794.9 | T29: 2781.67 | U29: 2648.88 | V29: 2631.45 | W29: 2708.37 | X29: 2511.35 | Y29: 2045.5
A30: - услуги по передаче | B30: =$B$15 -> 107.07 | C30: =$B30 -> 107.07 | D30: =$B30 -> 107.07 | E30: =$B30 -> 107.07 | F30: =$B30 -> 107.07 | G30: =$B30 -> 107.07 | H30: =$B30 -> 107.07 | I30: =$B30 -> 107.07 | J30: =$B30 -> 107.07 | ... Y30: =$B30 -> 107.07
A31: - сбытовая надбавка ГП | B31: 106.82 | C31: 106.82 | D31: 106.82 | E31: 106.82 | F31: 106.82 | G31: 106.82 | H31: 106.82 | I31: 106.82 | J31: 106.82 | K31: 106.82 | L31: 106.82 | M31: 106.82 | N31: 106.82 | O31: 106.82 | P31: 106.82 | Q31: 106.82 | R31: 106.82 | S31: 106.82 | T31: 106.82 | U31: 106.82 | V31: 106.82 | W31: 106.82 | X31: 106.82 | Y31: 106.82
A32: - инфраструктурные платежи | B32: =$B$17 -> 5.35 | C32: =$B32 -> 5.35 | D32: =$B32 -> 5.35 | E32: =$B32 -> 5.35 | F32: =$B32 -> 5.35 | G32: =$B32 -> 5.35 | H32: =$B32 -> 5.35 | I32: =$B32 -> 5.35 | J32: =$B32 -> 5.35 | ... Y32: =$B32 -> 5.35
A33: 5 | B33: =B34+B35+B36+B37 -> 1972.6 | C33: =C34+C35+C36+C37 -> 1738.37 | D33: =D34+D35+D36+D37 -> 1631.32 | E33: =E34+E35+E36+E37 -> 1488.18 | F33: =F34+F35+F36+F37 -> 1429.89 | G33: =G34+G35+G36+G37 -> 1420.94 | H33: =H34+H35+H36+H37 -> 1524.1 | I33: =I34+I35+I36+I37 -> 1888.26 | ... Y33: =Y34+Y35+Y36+Y37 -> 2200.4
A34: - средневзв. стоимость э/э (м) | B34: 1753.36 | C34: 1519.13 | D34: 1412.08 | E34: 1268.94 | F34: 1210.65 | G34: 1201.7 | H34: 1304.86 | I34: 1669.02 | J34: 2134.91 | K34: 2370.79 | L34: 2439.61 | M34: 2468.97 | N34: 2464.34 | O34: 2468.42 | P34: 2464.8 | Q34: 2527.1 | R34: 2535.38 | S34: 2500.69 | T34: 2480.64 | U34: 2452.58 | V34: 2450.49 | W34: 2467.58 | X34: 2169.48 | Y34: 1981.16
A35: - услуги по передаче | B35: =$B$15 -> 107.07 | C35: =$B35 -> 107.07 | D35: =$B35 -> 107.07 | E35: =$B35 -> 107.07 | F35: =$B35 -> 107.07 | G35: =$B35 -> 107.07 | H35: =$B35 -> 107.07 | I35: =$B35 -> 107.07 | J35: =$B35 -> 107.07 | ... Y35: =$B35 -> 107.07
A36: - сбытовая надбавка ГП | B36: 106.82 | C36: 106.82 | D36: 106.82 | E36: 106.82 | F36: 106.82 | G36: 106.82 | H36: 106.82 | I36: 106.82 | J36: 106.82 | K36: 106.82 | L36: 106.82 | M36: 106.82 | N36: 106.82 | O36: 106.82 | P36: 106.82 | Q36: 106.82 | R36: 106.82 | S36: 106.82 | T36: 106.82 | U36: 106.82 | V36: 106.82 | W36: 106.82 | X36: 106.82 | Y36: 106.82
